Workbook

Sheet Executive Dashboard
A1: E-Commerce Sales Performance Dashboard
A2: 2025 | Sales, Profitability & Market Performance
A4: Revenue | D4: Gross Profit | G4: Profit Margin | J4: Total Orders
A5: =KPI_Summary!B2 -> 147019.1 | D5: =KPI_Summary!B4 -> 58998.1 | G5: =KPI_Summary!B5 -> 0.40129548 | J5: =KPI_Summary!B6 -> 550
A8: Average Order Value | D8: Top Revenue Market
A9: =KPI_Summary!B7 -> 267.30745 | D9: =INDEX(Pivot_Country!A4:A11,MATCH(MAX(Pivot_Country!B4:B11),Pivot_Country!B4:B11,0)) -> United Arab Emirates
A12: Performance Overview
A50: Key Business Insights
A52: Insight 1 — Top market
A53: UAE is the highest-revenue market at $24.44K.
A55: Insight 2 — Product concentration
A56: 🖥️ The two monitor products generate $61.35K, approximately 41.7% of total revenue.
A58: Insight 3 — Margin opportunity
A59: 💰 Accessories have the highest gross margin at 50.23%, while Electronics has the lowest at 37.55%.
A61: Insight 4 — Monthly performance
A62: 📈 November was the strongest month with $17.11K in revenue, while February was the weakest at $6.60K.

Sheet Project_Brief
A1: PROJECT 1 | B1: International E-commerce Sales Data Cleaning & Executive Dashboard | C1: Status
A2: OBJECTIVE | B2: Clean a messy sales dataset, calculate business KPIs, and create an executive dashboard in Excel. | C2: Done
A3: TASK 1 | B3: Identify and remove duplicate records. | C3: Done
A4: TASK 2 | B4: Standardize Country, Customer_Name, Payment_Method and Order_Status. | C4: Done
A5: TASK 3 | B5: Handle missing values appropriately and document your approach. | C5: Done
A6: TASK 4 | B6: Validate email addresses and flag invalid records. | C6: Done
A7: TASK 5 | B7: Create Total Sales = Quantity × Unit Price × (1 − Discount). | C7: Done
A8: TASK 6 | B8: Create Total Cost = Quantity × Unit Cost. | C8: Done
A9: TASK 7 | B9: Create Gross Profit = Total Sales − Total Cost. | C9: Done
A10: TASK 8 | B10: Create Profit Margin % = Gross Profit ÷ Total Sales. | C10: Done
A11: TASK 9 | B11: Analyse Sales, Profit, Orders and Average Order Value by month and country. | C11: Done
A12: TASK 10 | B12: Identify top 5 products and best-performing countries. | C12: Done
... A14: TASK 12 | B14: Write 5 business insights and 3 recommendations based on your analysis. | C14: Done
A18: Task | B18: Status
A19: Data Cleaning | B19: Done
A20: Data Validation | B20: Done
A21: KPI Analysis | B21: Done
A22: Category Analysis | B22: Done
A23: Country Analysis | B23: Done
A24: Time Analysis | B24: Done
A25: Product Analysis | B25: Done
A26: Dashboard | B26: Done
A27: Documentation | B27: Done
A29: Percentage | B29: =COUNTIF(B19:B27,"Done")/COUNTA(B19:B27) -> 1

Sheet Pivot_Product
A3: Row Labels | B3: Sum of Revenue_USD | C3: Sum of Gross_Profit_USD | D3: Gross Margin
A4: Monitor 27-inch | B4: 33920.25 | C4: 11420.25 | D4: =C4/B4 -> 0.33667942
A5: Monitor 24-inch | B5: 27431.25 | C5: 10001.25 | D5: =C5/B5 -> 0.3645933
A6: Office Chair | B6: 17598 | C6: 6473 | D6: =C6/B6 -> 0.36782589
A7: Headphones | B7: 13986.75 | C7: 6242.75 | D7: =C7/B7 -> 0.44633314
A8: SSD 1TB | B8: 10014.2 | C8: 3972.2 | D8: =C8/B8 -> 0.39665675
A9: Webcam | B9: 8496 | C9: 3816 | D9: =C9/B9 -> 0.44915254
A10: Mechanical Keyboard | B10: 8414.25 | C10: 4136.25 | D10: =C10/B10 -> 0.49157679
A11: External HDD 2TB | B11: 7538.7 | C11: 2858.7 | D11: =C11/B11 -> 0.37920331
A12: USB-C Hub | B12: 6885.9 | C12: 3231.9 | D12: =C12/B12 -> 0.46935041
A13: Desk Lamp | B13: 5283 | C13: 2787 | D13: =C13/B13 -> 0.52754117
A14: Laptop Stand | B14: 5209.8 | C14: 2727.8 | D14: =C14/B14 -> 0.52359016
A15: Wireless Mouse | B15: 2241 | C15: 1331 | D15: =C15/B15 -> 0.59393128
A16: Grand Total | B16: 147019.1 | C16: 58998.1 | D16: =C16/B16 -> 0.40129548

Sheet Pivot_Country
A3: Row Labels | B3: Sum of Revenue_USD
A4: Australia | B4: 19511.05
A5: Canada | B5: 14616
A6: Germany | B6: 15601.1
A7: India | B7: 17289
A8: Singapore | B8: 21326.35
A9: United Arab Emirates | B9: 24443.25
A10: United Kingdom | B10: 15647.9
A11: United States | B11: 17255.75
A12: Unknown | B12: 1328.7
A13: Grand Total | B13: 147019.1

Sheet Pivot _Category
A3: Row Labels | B3: Sum of Revenue_USD | C3: Sum of Gross_Profit_USD
A4: Accessories | B4: 22750.95 | C4: 11426.95
A5: Electronics | B5: 83834.25 | C5: 31480.25
A6: Furniture | B6: 22881 | C6: 9260
A7: Storage | B7: 17552.9 | C7: 6830.9
A8: Grand Total | B8: 147019.1 | C8: 58998.1
A12: Row Labels | B12: Sum of Gross Margin
A13: Accessories | B13: 0.50226254
A14: Electronics | B14: 0.37550583
A15: Furniture | B15: 0.40470259
A16: Storage | B16: 0.38916077
A17: Grand Total | B17: 0.40129548

Sheet Pivot_Monthly
A3: Row Labels | B3: Sum of Revenue_USD | C3: Sum of Gross_Profit_USD
A4: 2025 | B4: 147019.1 | C4: 58998.1
A5: Jan | B5: 8896.65 | C5: 3504.65
A6: Feb | B6: 6599.5 | C6: 2987.5
A7: Mar | B7: 12881.55 | C7: 5040.55
A8: Apr | B8: 16177.35 | C8: 6337.35
A9: May | B9: 12989.75 | C9: 5413.75
A10: Jun | B10: 12847.4 | C10: 5248.4
A11: Jul | B11: 11353.95 | C11: 4496.95
A12: Aug | B12: 14305.05 | C12: 5677.05
A13: Sep | B13: 10804.6 | C13: 4532.6
A14: Oct | B14: 12654.5 | C14: 4841.5
A15: Nov | B15: 17111.2 | C15: 6660.2
... A17: Grand Total | B17: 147019.1 | C17: 58998.1

Sheet Clean_Data
A1: Order_ID | B1: Order_Date | C1: Customer_Name | D1: Customer_Name_Clean | E1: Country | F1: Country_clean | G1: Product | H1: Category | I1: Quantity | J1: Unit_Price_USD | K1: Unit_Cost_USD | L1: Discount | M1: Payment_Method | N1: Payment_Method_clean | O1: Order_Status | P1: Order_Status_Clean | Q1: Email_Validation | R1: Customer_Email | S1: Revenue_USD | T1: Cost_USD | U1: Gross_Profit_USD | V1: Profit_Margin
A2: ORD-10087 | B2: 45735 | C2: Liam Miller | D2: =PROPER(TRIM(C2)) -> Liam Miller | E2: UAE | F2: =IF(OR(UPPER(TRIM(E2))="AUS",UPPER(TRIM(E2))="AUSTRALIA"),"Australia",IF(OR(UPPER(TRIM(E2))="CAN",UPPER(TRIM(E2))="CANADA"),"Canada",IF(OR(UPPER(TRIM(E2))="DE",UPPER(TRIM(E2))="GERMANY"),"Germany",IF(OR(UPPER(TRIM(E2))="IN",UPPER(TRIM(E2))="INDIA"),"India",IF(OR(UPPER(TRIM(E2))="US",UPPER(TRIM(E2))="USA",UPPER(TRIM(E2))="UNITED STATES"),"United States",IF(OR(UPPER(TRIM(E2))="UK",UPPER(TRIM(E2))="U.K.",UPPER(TRIM(E2))="UNITED KINGDOM"),"United Kingdom",IF(OR(UPPER(TRIM(E2))="UAE",UPPER(TRIM(E2))="U.A.E.",UPPER(TRIM(E2))="UNITED ARAB EMIRATES"),"United Arab Emirates",IF(OR(UPPER(TRIM(E2))="SG",UPPER(TRIM(E2))="SINGAPORE"),"Singapore",TRIM(E2))))))))) -> United Arab Emirates | G2: Desk Lamp | H2: Furniture | I2: 3 | J2: 36 | K2: 16 | L2: 0 | M2: paypal | N2: PayPal | O2: Completed | P2: =PROPER(TRIM(O2)) -> Completed | Q2: =IF(TRIM(R2)="","Missing",IF(AND(ISNUMBER(SEARCH("@",R2)),ISNUMBER(SEARCH(".",R2,SEARCH("@",R2)+2))),"Valid","Invalid")) -> Valid | R2: liam.miller@example.com | S2: =I2*J2*(1-L2) -> 108 | T2: =I2*K2 -> 48 | U2: =S2-T2 -> 60 | V2: =IF(S2=0,0,U2/S2) -> 0.55555556
A3: ORD-10007 | B3: 45894 | C3: Ava Thomas | D3: =PROPER(TRIM(C3)) -> Ava Thomas | E3: UAE | F3: =IF(OR(UPPER(TRIM(E3))="AUS",UPPER(TRIM(E3))="AUSTRALIA"),"Australia",IF(OR(UPPER(TRIM(E3))="CAN",UPPER(TRIM(E3))="CANADA"),"Canada",IF(OR(UPPER(TRIM(E3))="DE",UPPER(TRIM(E3))="GERMANY"),"Germany",IF(OR(UPPER(TRIM(E3))="IN",UPPER(TRIM(E3))="INDIA"),"India",IF(OR(UPPER(TRIM(E3))="US",UPPER(TRIM(E3))="USA",UPPER(TRIM(E3))="UNITED STATES"),"United States",IF(OR(UPPER(TRIM(E3))="UK",UPPER(TRIM(E3))="U.K.",UPPER(TRIM(E3))="UNITED KINGDOM"),"United Kingdom",IF(OR(UPPER(TRIM(E3))="UAE",UPPER(TRIM(E3))="U.A.E.",UPPER(TRIM(E3))="UNITED ARAB EMIRATES"),"United Arab Emirates",IF(OR(UPPER(TRIM(E3))="SG",UPPER(TRIM(E3))="SINGAPORE"),"Singapore",TRIM(E3))))))))) -> United Arab Emirates | G3: Laptop Stand | H3: Accessories | I3: 4 | J3: 38 | K3: 17 | L3: 0 | M3: credit card | N3: =PROPER(TRIM(M3)) -> Credit Card | O3: Completed | P3: =PROPER(TRIM(O3)) -> Completed | Q3: =IF(TRIM(R3)="","Missing",IF(AND(ISNUMBER(SEARCH("@",R3)),ISNUMBER(SEARCH(".",R3,SEARCH("@",R3)+2))),"Valid","Invalid")) -> Valid | R3: ava.thomas@example.com | S3: =I3*J3*(1-L3) -> 152 | T3: =I3*K3 -> 68 | U3: =S3-T3 -> 84 | V3: =IF(S3=0,0,U3/S3) -> 0.55263158
A4: ORD-10143 | B4: 45777 | C4: alex morgan | D4: =PROPER(TRIM(C4)) -> Alex Morgan | E4: australia | F4: =IF(OR(UPPER(TRIM(E4))="AUS",UPPER(TRIM(E4))="AUSTRALIA"),"Australia",IF(OR(UPPER(TRIM(E4))="CAN",UPPER(TRIM(E4))="CANADA"),"Canada",IF(OR(UPPER(TRIM(E4))="DE",UPPER(TRIM(E4))="GERMANY"),"Germany",IF(OR(UPPER(TRIM(E4))="IN",UPPER(TRIM(E4))="INDIA"),"India",IF(OR(UPPER(TRIM(E4))="US",UPPER(TRIM(E4))="USA",UPPER(TRIM(E4))="UNITED STATES"),"United States",IF(OR(UPPER(TRIM(E4))="UK",UPPER(TRIM(E4))="U.K.",UPPER(TRIM(E4))="UNITED KINGDOM"),"United Kingdom",IF(OR(UPPER(TRIM(E4))="UAE",UPPER(TRIM(E4))="U.A.E.",UPPER(TRIM(E4))="UNITED ARAB EMIRATES"),"United Arab Emirates",IF(OR(UPPER(TRIM(E4))="SG",UPPER(TRIM(E4))="SINGAPORE"),"Singapore",TRIM(E4))))))))) -> Australia | G4: Wireless Mouse | H4: Accessories | I4: 1 | J4: 18 | K4: 7 | L4: 0.05 | M4: PayPal | N4: PayPal | O4: Completed | P4: =PROPER(TRIM(O4)) -> Completed | Q4: =IF(TRIM(R4)="","Missing",IF(AND(ISNUMBER(SEARCH("@",R4)),ISNUMBER(SEARCH(".",R4,SEARCH("@",R4)+2))),"Valid","Invalid")) -> Valid | R4: alex.morgan@example.com | S4: =I4*J4*(1-L4) -> 17.1 | T4: =I4*K4 -> 7 | U4: =S4-T4 -> 10.1 | V4: =IF(S4=0,0,U4/S4) -> 0.59064327
A5: ORD-10127 | B5: 45834 | C5: Liam Miller | D5: =PROPER(TRIM(C5)) -> Liam Miller | E5: UK | F5: =IF(OR(UPPER(TRIM(E5))="AUS",UPPER(TRIM(E5))="AUSTRALIA"),"Australia",IF(OR(UPPER(TRIM(E5))="CAN",UPPER(TRIM(E5))="CANADA"),"Canada",IF(OR(UPPER(TRIM(E5))="DE",UPPER(TRIM(E5))="GERMANY"),"Germany",IF(OR(UPPER(TRIM(E5))="IN",UPPER(TRIM(E5))="INDIA"),"India",IF(OR(UPPER(TRIM(E5))="US",UPPER(TRIM(E5))="USA",UPPER(TRIM(E5))="UNITED STATES"),"United States",IF(OR(UPPER(TRIM(E5))="UK",UPPER(TRIM(E5))="U.K.",UPPER(TRIM(E5))="UNITED KINGDOM"),"United Kingdom",IF(OR(UPPER(TRIM(E5))="UAE",UPPER(TRIM(E5))="U.A.E.",UPPER(TRIM(E5))="UNITED ARAB EMIRATES"),"United Arab Emirates",IF(OR(UPPER(TRIM(E5))="SG",UPPER(TRIM(E5))="SINGAPORE"),"Singapore",TRIM(E5))))))))) -> United Kingdom | G5: SSD 1TB | H5: Storage | I5: 1 | J5: 92 | K5: 53 | L5: 0 | M5: credit card | N5: =PROPER(TRIM(M5)) -> Credit Card | O5: Completed | P5: =PROPER(TRIM(O5)) -> Completed | Q5: =IF(TRIM(R5)="","Missing",IF(AND(ISNUMBER(SEARCH("@",R5)),ISNUMBER(SEARCH(".",R5,SEARCH("@",R5)+2))),"Valid","Invalid")) -> Valid | R5: liam.miller@example.com | S5: =I5*J5*(1-L5) -> 92 | T5: =I5*K5 -> 53 | U5: =S5-T5 -> 39 | V5: =IF(S5=0,0,U5/S5) -> 0.42391304
A6: ORD-10470 | B6: 46000 | C6: Lily Hall | D6: =PROPER(TRIM(C6)) -> Lily Hall | E6: AUS | F6: =IF(OR(UPPER(TRIM(E6))="AUS",UPPER(TRIM(E6))="AUSTRALIA"),"Australia",IF(OR(UPPER(TRIM(E6))="CAN",UPPER(TRIM(E6))="CANADA"),"Canada",IF(OR(UPPER(TRIM(E6))="DE",UPPER(TRIM(E6))="GERMANY"),"Germany",IF(OR(UPPER(TRIM(E6))="IN",UPPER(TRIM(E6))="INDIA"),"India",IF(OR(UPPER(TRIM(E6))="US",UPPER(TRIM(E6))="USA",UPPER(TRIM(E6))="UNITED STATES"),"United States",IF(OR(UPPER(TRIM(E6))="UK",UPPER(TRIM(E6))="U.K.",UPPER(TRIM(E6))="UNITED KINGDOM"),"United Kingdom",IF(OR(UPPER(TRIM(E6))="UAE",UPPER(TRIM(E6))="U.A.E.",UPPER(TRIM(E6))="UNITED ARAB EMIRATES"),"United Arab Emirates",IF(OR(UPPER(TRIM(E6))="SG",UPPER(TRIM(E6))="SINGAPORE"),"Singapore",TRIM(E6))))))))) -> Australia | G6: SSD 1TB | H6: Storage | I6: 1 | J6: 92 | K6: 53 | L6: 0.05 | M6: Bank Transfer | N6: =PROPER(TRIM(M6)) -> Bank Transfer | O6: Pending | P6: =PROPER(TRIM(O6)) -> Pending | Q6: =IF(TRIM(R6)="","Missing",IF(AND(ISNUMBER(SEARCH("@",R6)),ISNUMBER(SEARCH(".",R6,SEARCH("@",R6)+2))),"Valid","Invalid")) -> Valid | R6: lily.hall@example.com | S6: =I6*J6*(1-L6) -> 87.4 | T6: =I6*K6 -> 53 | U6: =S6-T6 -> 34.4 | V6: =IF(S6=0,0,U6/S6) -> 0.39359268
A7: ORD-10279 | B7: 45764 | C7: Sophia Taylor | D7: =PROPER(TRIM(C7)) -> Sophia Taylor | E7: germany | F7: =IF(OR(UPPER(TRIM(E7))="AUS",UPPER(TRIM(E7))="AUSTRALIA"),"Australia",IF(OR(UPPER(TRIM(E7))="CAN",UPPER(TRIM(E7))="CANADA"),"Canada",IF(OR(UPPER(TRIM(E7))="DE",UPPER(TRIM(E7))="GERMANY"),"Germany",IF(OR(UPPER(TRIM(E7))="IN",UPPER(TRIM(E7))="INDIA"),"India",IF(OR(UPPER(TRIM(E7))="US",UPPER(TRIM(E7))="USA",UPPER(TRIM(E7))="UNITED STATES"),"United States",IF(OR(UPPER(TRIM(E7))="UK",UPPER(TRIM(E7))="U.K.",UPPER(TRIM(E7))="UNITED KINGDOM"),"United Kingdom",IF(OR(UPPER(TRIM(E7))="UAE",UPPER(TRIM(E7))="U.A.E.",UPPER(TRIM(E7))="UNITED ARAB EMIRATES"),"United Arab Emirates",IF(OR(UPPER(TRIM(E7))="SG",UPPER(TRIM(E7))="SINGAPORE"),"Singapore",TRIM(E7))))))))) -> Germany | G7: External HDD 2TB | H7: Storage | I7: 5 | J7: 78 | K7: 45 | L7: 0.1 | M7: Debit Card | N7: =PROPER(TRIM(M7)) -> Debit Card | O7: Completed | P7: =PROPER(TRIM(O7)) -> Completed | Q7: =IF(TRIM(R7)="","Missing",IF(AND(ISNUMBER(SEARCH("@",R7)),ISNUMBER(SEARCH(".",R7,SEARCH("@",R7)+2))),"Valid","Invalid")) -> Valid | R7: sophia.taylor@example.com | S7: =I7*J7*(1-L7) -> 351 | T7: =I7*K7 -> 225 | U7: =S7-T7 -> 126 | V7: =IF(S7=0,0,U7/S7) -> 0.35897436
A8: ORD-10463 | B8: 45900 | C8: Daniel Harris | D8: =PROPER(TRIM(C8)) -> Daniel Harris | E8: USA | F8: =IF(OR(UPPER(TRIM(E8))="AUS",UPPER(TRIM(E8))="AUSTRALIA"),"Australia",IF(OR(UPPER(TRIM(E8))="CAN",UPPER(TRIM(E8))="CANADA"),"Canada",IF(OR(UPPER(TRIM(E8))="DE",UPPER(TRIM(E8))="GERMANY"),"Germany",IF(OR(UPPER(TRIM(E8))="IN",UPPER(TRIM(E8))="INDIA"),"India",IF(OR(UPPER(TRIM(E8))="US",UPPER(TRIM(E8))="USA",UPPER(TRIM(E8))="UNITED STATES"),"United States",IF(OR(UPPER(TRIM(E8))="UK",UPPER(TRIM(E8))="U.K.",UPPER(TRIM(E8))="UNITED KINGDOM"),"United Kingdom",IF(OR(UPPER(TRIM(E8))="UAE",UPPER(TRIM(E8))="U.A.E.",UPPER(TRIM(E8))="UNITED ARAB EMIRATES"),"United Arab Emirates",IF(OR(UPPER(TRIM(E8))="SG",UPPER(TRIM(E8))="SINGAPORE"),"Singapore",TRIM(E8))))))))) -> United States | G8: Desk Lamp | H8: Furniture | I8: 2 | J8: 36 | K8: 16 | L8: 0.15 | M8: Bank Transfer | N8: =PROPER(TRIM(M8)) -> Bank Transfer | O8: Completed | P8: =PROPER(TRIM(O8)) -> Completed | Q8: =IF(TRIM(R8)="","Missing",IF(AND(ISNUMBER(SEARCH("@",R8)),ISNUMBER(SEARCH(".",R8,SEARCH("@",R8)+2))),"Valid","Invalid")) -> Invalid | R8: daniel.harris@example | S8: =I8*J8*(1-L8) -> 61.2 | T8: =I8*K8 -> 32 | U8: =S8-T8 -> 29.2 | V8: =IF(S8=0,0,U8/S8) -> 0.47712418
A9: ORD-10041 | B9: 45753 | C9: Mia White | D9: =PROPER(TRIM(C9)) -> Mia White | E9: germany | F9: =IF(OR(UPPER(TRIM(E9))="AUS",UPPER(TRIM(E9))="AUSTRALIA"),"Australia",IF(OR(UPPER(TRIM(E9))="CAN",UPPER(TRIM(E9))="CANADA"),"Canada",IF(OR(UPPER(TRIM(E9))="DE",UPPER(TRIM(E9))="GERMANY"),"Germany",IF(OR(UPPER(TRIM(E9))="IN",UPPER(TRIM(E9))="INDIA"),"India",IF(OR(UPPER(TRIM(E9))="US",UPPER(TRIM(E9))="USA",UPPER(TRIM(E9))="UNITED STATES"),"United States",IF(OR(UPPER(TRIM(E9))="UK",UPPER(TRIM(E9))="U.K.",UPPER(TRIM(E9))="UNITED KINGDOM"),"United Kingdom",IF(OR(UPPER(TRIM(E9))="UAE",UPPER(TRIM(E9))="U.A.E.",UPPER(TRIM(E9))="UNITED ARAB EMIRATES"),"United Arab Emirates",IF(OR(UPPER(TRIM(E9))="SG",UPPER(TRIM(E9))="SINGAPORE"),"Singapore",TRIM(E9))))))))) -> Germany | G9: Headphones | H9: Electronics | I9: 4 | J9: 85 | K9: 44 | L9: 0 | M9: credit card | N9: =PROPER(TRIM(M9)) -> Credit Card | O9: Completed | P9: =PROPER(TRIM(O9)) -> Completed | Q9: =IF(TRIM(R9)="","Missing",IF(AND(ISNUMBER(SEARCH("@",R9)),ISNUMBER(SEARCH(".",R9,SEARCH("@",R9)+2))),"Valid","Invalid")) -> Valid | R9: mia.white@example.com | S9: =I9*J9*(1-L9) -> 340 | T9: =I9*K9 -> 176 | U9: =S9-T9 -> 164 | V9: =IF(S9=0,0,U9/S9) -> 0.48235294
A10: ORD-10207 | B10: 45743 | C10: Grace Moore | D10: =PROPER(TRIM(C10)) -> Grace Moore | E10: SG | F10: =IF(OR(UPPER(TRIM(E10))="AUS",UPPER(TRIM(E10))="AUSTRALIA"),"Australia",IF(OR(UPPER(TRIM(E10))="CAN",UPPER(TRIM(E10))="CANADA"),"Canada",IF(OR(UPPER(TRIM(E10))="DE",UPPER(TRIM(E10))="GERMANY"),"Germany",IF(OR(UPPER(TRIM(E10))="IN",UPPER(TRIM(E10))="INDIA"),"India",IF(OR(UPPER(TRIM(E10))="US",UPPER(TRIM(E10))="USA",UPPER(TRIM(E10))="UNITED STATES"),"United States",IF(OR(UPPER(TRIM(E10))="UK",UPPER(TRIM(E10))="U.K.",UPPER(TRIM(E10))="UNITED KINGDOM"),"United Kingdom",IF(OR(UPPER(TRIM(E10))="UAE",UPPER(TRIM(E10))="U.A.E.",UPPER(TRIM(E10))="UNITED ARAB EMIRATES"),"United Arab Emirates",IF(OR(UPPER(TRIM(E10))="SG",UPPER(TRIM(E10))="SINGAPORE"),"Singapore",TRIM(E10))))))))) -> Singapore | G10: USB-C Hub | H10: Accessories | I10: 3 | J10: 42 | K10: 21 | L10: 0.05 | M10: paypal | N10: PayPal | O10: Cancelled | P10: =PROPER(TRIM(O10)) -> Cancelled | Q10: =IF(TRIM(R10)="","Missing",IF(AND(ISNUMBER(SEARCH("@",R10)),ISNUMBER(SEARCH(".",R10,SEARCH("@",R10)+2))),"Valid","Invalid")) -> Valid | R10: grace.moore@example.com | S10: =I10*J10*(1-L10) -> 119.7 | T10: =I10*K10 -> 63 | U10: =S10-T10 -> 56.7 | V10: =IF(S10=0,0,U10/S10) -> 0.47368421
A11: ORD-10011 | B11: 45914 | C11: Henry Clark | D11: =PROPER(TRIM(C11)) -> Henry Clark | E11: CAN | F11: =IF(OR(UPPER(TRIM(E11))="AUS",UPPER(TRIM(E11))="AUSTRALIA"),"Australia",IF(OR(UPPER(TRIM(E11))="CAN",UPPER(TRIM(E11))="CANADA"),"Canada",IF(OR(UPPER(TRIM(E11))="DE",UPPER(TRIM(E11))="GERMANY"),"Germany",IF(OR(UPPER(TRIM(E11))="IN",UPPER(TRIM(E11))="INDIA"),"India",IF(OR(UPPER(TRIM(E11))="US",UPPER(TRIM(E11))="USA",UPPER(TRIM(E11))="UNITED STATES"),"United States",IF(OR(UPPER(TRIM(E11))="UK",UPPER(TRIM(E11))="U.K.",UPPER(TRIM(E11))="UNITED KINGDOM"),"United Kingdom",IF(OR(UPPER(TRIM(E11))="UAE",UPPER(TRIM(E11))="U.A.E.",UPPER(TRIM(E11))="UNITED ARAB EMIRATES"),"United Arab Emirates",IF(OR(UPPER(TRIM(E11))="SG",UPPER(TRIM(E11))="SINGAPORE"),"Singapore",TRIM(E11))))))))) -> Canada | G11: Office Chair | H11: Furniture | I11: 1 | J11: 210 | K11: 125 | L11: 0.05 | M11: PayPal | N11: PayPal | O11: Cancelled | P11: =PROPER(TRIM(O11)) -> Cancelled | Q11: =IF(TRIM(R11)="","Missing",IF(AND(ISNUMBER(SEARCH("@",R11)),ISNUMBER(SEARCH(".",R11,SEARCH("@",R11)+2))),"Valid","Invalid")) -> Valid | R11: henry.clark@example.com | S11: =I11*J11*(1-L11) -> 199.5 | T11: =I11*K11 -> 125 | U11: =S11-T11 -> 74.5 | V11: =IF(S11=0,0,U11/S11) -> 0.37343358
A12: ORD-10049 | B12: 45801 | C12: Olivia Davis | D12: =PROPER(TRIM(C12)) -> Olivia Davis | E12: DE | F12: =IF(OR(UPPER(TRIM(E12))="AUS",UPPER(TRIM(E12))="AUSTRALIA"),"Australia",IF(OR(UPPER(TRIM(E12))="CAN",UPPER(TRIM(E12))="CANADA"),"Canada",IF(OR(UPPER(TRIM(E12))="DE",UPPER(TRIM(E12))="GERMANY"),"Germany",IF(OR(UPPER(TRIM(E12))="IN",UPPER(TRIM(E12))="INDIA"),"India",IF(OR(UPPER(TRIM(E12))="US",UPPER(TRIM(E12))="USA",UPPER(TRIM(E12))="UNITED STATES"),"United States",IF(OR(UPPER(TRIM(E12))="UK",UPPER(TRIM(E12))="U.K.",UPPER(TRIM(E12))="UNITED KINGDOM"),"United Kingdom",IF(OR(UPPER(TRIM(E12))="UAE",UPPER(TRIM(E12))="U.A.E.",UPPER(TRIM(E12))="UNITED ARAB EMIRATES"),"United Arab Emirates",IF(OR(UPPER(TRIM(E12))="SG",UPPER(TRIM(E12))="SINGAPORE"),"Singapore",TRIM(E12))))))))) -> Germany | G12: Webcam | H12: Electronics | I12: 3 | J12: 59 | K12: 30 | L12: 0.05 | M12: credit card | N12: =PROPER(TRIM(M12)) -> Credit Card | O12: Completed | P12: =PROPER(TRIM(O12)) -> Completed | Q12: =IF(TRIM(R12)="","Missing",IF(AND(ISNUMBER(SEARCH("@",R12)),ISNUMBER(SEARCH(".",R12,SEARCH("@",R12)+2))),"Valid","Invalid")) -> Valid | R12: olivia.davis@example.com | S12: =I12*J12*(1-L12) -> 168.15 | T12: =I12*K12 -> 90 | U12: =S12-T12 -> 78.15 | V12: =IF(S12=0,0,U12/S12) -> 0.4647636
A13: ORD-10215 | B13: 45918 | C13: Daniel Harris | D13: =PROPER(TRIM(C13)) -> Daniel Harris | E13: SG | F13: =IF(OR(UPPER(TRIM(E13))="AUS",UPPER(TRIM(E13))="AUSTRALIA"),"Australia",IF(OR(UPPER(TRIM(E13))="CAN",UPPER(TRIM(E13))="CANADA"),"Canada",IF(OR(UPPER(TRIM(E13))="DE",UPPER(TRIM(E13))="GERMANY"),"Germany",IF(OR(UPPER(TRIM(E13))="IN",UPPER(TRIM(E13))="INDIA"),"India",IF(OR(UPPER(TRIM(E13))="US",UPPER(TRIM(E13))="USA",UPPER(TRIM(E13))="UNITED STATES"),"United States",IF(OR(UPPER(TRIM(E13))="UK",UPPER(TRIM(E13))="U.K.",UPPER(TRIM(E13))="UNITED KINGDOM"),"United Kingdom",IF(OR(UPPER(TRIM(E13))="UAE",UPPER(TRIM(E13))="U.A.E.",UPPER(TRIM(E13))="UNITED ARAB EMIRATES"),"United Arab Emirates",IF(OR(UPPER(TRIM(E13))="SG",UPPER(TRIM(E13))="SINGAPORE"),"Singapore",TRIM(E13))))))))) -> Singapore | G13: USB-C Hub | H13: Accessories | I13: 3 | J13: 42 | K13: 21 | L13: 0 | M13: paypal | N13: PayPal | O13: Pending | P13: =PROPER(TRIM(O13)) -> Pending | Q13: =IF(TRIM(R13)="","Missing",IF(AND(ISNUMBER(SEARCH("@",R13)),ISNUMBER(SEARCH(".",R13,SEARCH("@",R13)+2))),"Valid","Invalid")) -> Valid | R13: daniel.harris@example.com | S13: =I13*J13*(1-L13) -> 126 | T13: =I13*K13 -> 63 | U13: =S13-T13 -> 63 | V13: =IF(S13=0,0,U13/S13) -> 0.5
A14: ORD-10333 | B14: 45830 | C14: Noah Brown | D14: =PROPER(TRIM(C14)) -> Noah Brown | E14: germany | F14: =IF(OR(UPPER(TRIM(E14))="AUS",UPPER(TRIM(E14))="AUSTRALIA"),"Australia",IF(OR(UPPER(TRIM(E14))="CAN",UPPER(TRIM(E14))="CANADA"),"Canada",IF(OR(UPPER(TRIM(E14))="DE",UPPER(TRIM(E14))="GERMANY"),"Germany",IF(OR(UPPER(TRIM(E14))="IN",UPPER(TRIM(E14))="INDIA"),"India",IF(OR(UPPER(TRIM(E14))="US",UPPER(TRIM(E14))="USA",UPPER(TRIM(E14))="UNITED STATES"),"United States",IF(OR(UPPER(TRIM(E14))="UK",UPPER(TRIM(E14))="U.K.",UPPER(TRIM(E14))="UNITED KINGDOM"),"United Kingdom",IF(OR(UPPER(TRIM(E14))="UAE",UPPER(TRIM(E14))="U.A.E.",UPPER(TRIM(E14))="UNITED ARAB EMIRATES"),"United Arab Emirates",IF(OR(UPPER(TRIM(E14))="SG",UPPER(TRIM(E14))="SINGAPORE"),"Singapore",TRIM(E14))))))))) -> Germany | G14: Headphones | H14: Electronics | I14: 3 | J14: 85 | K14: 44 | L14: 0 | M14: Debit Card | N14: =PROPER(TRIM(M14)) -> Debit Card | O14: Completed | P14: =PROPER(TRIM(O14)) -> Completed | Q14: =IF(TRIM(R14)="","Missing",IF(AND(ISNUMBER(SEARCH("@",R14)),ISNUMBER(SEARCH(".",R14,SEARCH("@",R14)+2))),"Valid","Invalid")) -> Valid | R14: noah.brown@example.com | S14: =I14*J14*(1-L14) -> 255 | T14: =I14*K14 -> 132 | U14: =S14-T14 -> 123 | V14: =IF(S14=0,0,U14/S14) -> 0.48235294
A15: ORD-10531 | B15: 45825 | C15: Henry Clark | D15: =PROPER(TRIM(C15)) -> Henry Clark | E15: India | F15: =IF(OR(UPPER(TRIM(E15))="AUS",UPPER(TRIM(E15))="AUSTRALIA"),"Australia",IF(OR(UPPER(TRIM(E15))="CAN",UPPER(TRIM(E15))="CANADA"),"Canada",IF(OR(UPPER(TRIM(E15))="DE",UPPER(TRIM(E15))="GERMANY"),"Germany",IF(OR(UPPER(TRIM(E15))="IN",UPPER(TRIM(E15))="INDIA"),"India",IF(OR(UPPER(TRIM(E15))="US",UPPER(TRIM(E15))="USA",UPPER(TRIM(E15))="UNITED STATES"),"United States",IF(OR(UPPER(TRIM(E15))="UK",UPPER(TRIM(E15))="U.K.",UPPER(TRIM(E15))="UNITED KINGDOM"),"United Kingdom",IF(OR(UPPER(TRIM(E15))="UAE",UPPER(TRIM(E15))="U.A.E.",UPPER(TRIM(E15))="UNITED ARAB EMIRATES"),"United Arab Emirates",IF(OR(UPPER(TRIM(E15))="SG",UPPER(TRIM(E15))="SINGAPORE"),"Singapore",TRIM(E15))))))))) -> India | G15: Desk Lamp | H15: Furniture | I15: 4 | J15: 36 | K15: 16 | L15: 0 | M15: credit card | N15: =PROPER(TRIM(M15)) -> Credit Card | O15: Completed | P15: =PROPER(TRIM(O15)) -> Completed | Q15: =IF(TRIM(R15)="","Missing",IF(AND(ISNUMBER(SEARCH("@",R15)),ISNUMBER(SEARCH(".",R15,SEARCH("@",R15)+2))),"Valid","Invalid")) -> Valid | R15: henry.clark@example.com | S15: =I15*J15*(1-L15) -> 144 | T15: =I15*K15 -> 64 | U15: =S15-T15 -> 80 | V15: =IF(S15=0,0,U15/S15) -> 0.55555556
A16: ORD-10341 | B16: 45795 | C16: sophia taylor | D16: =PROPER(TRIM(C16)) -> Sophia Taylor | E16: singapore | F16: =IF(OR(UPPER(TRIM(E16))="AUS",UPPER(TRIM(E16))="AUSTRALIA"),"Australia",IF(OR(UPPER(TRIM(E16))="CAN",UPPER(TRIM(E16))="CANADA"),"Canada",IF(OR(UPPER(TRIM(E16))="DE",UPPER(TRIM(E16))="GERMANY"),"Germany",IF(OR(UPPER(TRIM(E16))="IN",UPPER(TRIM(E16))="INDIA"),"India",IF(OR(UPPER(TRIM(E16))="US",UPPER(TRIM(E16))="USA",UPPER(TRIM(E16))="UNITED STATES"),"United States",IF(OR(UPPER(TRIM(E16))="UK",UPPER(TRIM(E16))="U.K.",UPPER(TRIM(E16))="UNITED KINGDOM"),"United Kingdom",IF(OR(UPPER(TRIM(E16))="UAE",UPPER(TRIM(E16))="U.A.E.",UPPER(TRIM(E16))="UNITED ARAB EMIRATES"),"United Arab Emirates",IF(OR(UPPER(TRIM(E16))="SG",UPPER(TRIM(E16))="SINGAPORE"),"Singapore",TRIM(E16))))))))) -> Singapore | G16: Webcam | H16: Electronics | I16: 5 | J16: 59 | K16: 30 | L16: 0.1 | M16: credit card | N16: =PROPER(TRIM(M16)) -> Credit Card | O16: Pending | P16: =PROPER(TRIM(O16)) -> Pending | Q16: =IF(TRIM(R16)="","Missing",IF(AND(ISNUMBER(SEARCH("@",R16)),ISNUMBER(SEARCH(".",R16,SEARCH("@",R16)+2))),"Valid","Invalid")) -> Valid | R16: sophia.taylor@example.com | S16: =I16*J16*(1-L16) -> 265.5 | T16: =I16*K16 -> 150 | U16: =S16-T16 -> 115.5 | V16: =IF(S16=0,0,U16/S16) -> 0.43502825
A17: ORD-10054 | B17: 46018 | C17: Ava Thomas | D17: =PROPER(TRIM(C17)) -> Ava Thomas | E17: United Arab Emirates | F17: =IF(OR(UPPER(TRIM(E17))="AUS",UPPER(TRIM(E17))="AUSTRALIA"),"Australia",IF(OR(UPPER(TRIM(E17))="CAN",UPPER(TRIM(E17))="CANADA"),"Canada",IF(OR(UPPER(TRIM(E17))="DE",UPPER(TRIM(E17))="GERMANY"),"Germany",IF(OR(UPPER(TRIM(E17))="IN",UPPER(TRIM(E17))="INDIA"),"India",IF(OR(UPPER(TRIM(E17))="US",UPPER(TRIM(E17))="USA",UPPER(TRIM(E17))="UNITED STATES"),"United States",IF(OR(UPPER(TRIM(E17))="UK",UPPER(TRIM(E17))="U.K.",UPPER(TRIM(E17))="UNITED KINGDOM"),"United Kingdom",IF(OR(UPPER(TRIM(E17))="UAE",UPPER(TRIM(E17))="U.A.E.",UPPER(TRIM(E17))="UNITED ARAB EMIRATES"),"United Arab Emirates",IF(OR(UPPER(TRIM(E17))="SG",UPPER(TRIM(E17))="SINGAPORE"),"Singapore",TRIM(E17))))))))) -> United Arab Emirates | G17: Desk Lamp | H17: Furniture | I17: 2 | J17: 36 | K17: 16 | L17: 0.1 | M17: Bank Transfer | N17: =PROPER(TRIM(M17)) -> Bank Transfer | O17: Completed | P17: =PROPER(TRIM(O17)) -> Completed | Q17: =IF(TRIM(R17)="","Missing",IF(AND(ISNUMBER(SEARCH("@",R17)),ISNUMBER(SEARCH(".",R17,SEARCH("@",R17)+2))),"Valid","Invalid")) -> Valid | R17: ava.thomas@example.com | S17: =I17*J17*(1-L17) -> 64.8 | T17: =I17*K17 -> 32 | U17: =S17-T17 -> 32.8 | V17: =IF(S17=0,0,U17/S17) -> 0.50617284
A18: ORD-10065 | B18: 45908 | C18: Liam Miller | D18: =PROPER(TRIM(C18)) -> Liam Miller | E18: australia | F18: =IF(OR(UPPER(TRIM(E18))="AUS",UPPER(TRIM(E18))="AUSTRALIA"),"Australia",IF(OR(UPPER(TRIM(E18))="CAN",UPPER(TRIM(E18))="CANADA"),"Canada",IF(OR(UPPER(TRIM(E18))="DE",UPPER(TRIM(E18))="GERMANY"),"Germany",IF(OR(UPPER(TRIM(E18))="IN",UPPER(TRIM(E18))="INDIA"),"India",IF(OR(UPPER(TRIM(E18))="US",UPPER(TRIM(E18))="USA",UPPER(TRIM(E18))="UNITED STATES"),"United States",IF(OR(UPPER(TRIM(E18))="UK",UPPER(TRIM(E18))="U.K.",UPPER(TRIM(E18))="UNITED KINGDOM"),"United Kingdom",IF(OR(UPPER(TRIM(E18))="UAE",UPPER(TRIM(E18))="U.A.E.",UPPER(TRIM(E18))="UNITED ARAB EMIRATES"),"United Arab Emirates",IF(OR(UPPER(TRIM(E18))="SG",UPPER(TRIM(E18))="SINGAPORE"),"Singapore",TRIM(E18))))))))) -> Australia | G18: Mechanical Keyboard | H18: Accessories | I18: 1 | J18: 65 | K18: 31 | L18: 0.05 | M18: Credit Card | N18: =PROPER(TRIM(M18)) -> Credit Card | O18: Completed | P18: =PROPER(TRIM(O18)) -> Completed | Q18: =IF(TRIM(R18)="","Missing",IF(AND(ISNUMBER(SEARCH("@",R18)),ISNUMBER(SEARCH(".",R18,SEARCH("@",R18)+2))),"Valid","Invalid")) -> Valid | R18: liam.miller@example.com | S18: =I18*J18*(1-L18) -> 61.75 | T18: =I18*K18 -> 31 | U18: =S18-T18 -> 30.75 | V18: =IF(S18=0,0,U18/S18) -> 0.49797571
A19: ORD-10072 | B19: 45704 | C19: Lucas Jackson | D19: =PROPER(TRIM(C19)) -> Lucas Jackson | E19: USA | F19: =IF(OR(UPPER(TRIM(E19))="AUS",UPPER(TRIM(E19))="AUSTRALIA"),"Australia",IF(OR(UPPER(TRIM(E19))="CAN",UPPER(TRIM(E19))="CANADA"),"Canada",IF(OR(UPPER(TRIM(E19))="DE",UPPER(TRIM(E19))="GERMANY"),"Germany",IF(OR(UPPER(TRIM(E19))="IN",UPPER(TRIM(E19))="INDIA"),"India",IF(OR(UPPER(TRIM(E19))="US",UPPER(TRIM(E19))="USA",UPPER(TRIM(E19))="UNITED STATES"),"United States",IF(OR(UPPER(TRIM(E19))="UK",UPPER(TRIM(E19))="U.K.",UPPER(TRIM(E19))="UNITED KINGDOM"),"United Kingdom",IF(OR(UPPER(TRIM(E19))="UAE",UPPER(TRIM(E19))="U.A.E.",UPPER(TRIM(E19))="UNITED ARAB EMIRATES"),"United Arab Emirates",IF(OR(UPPER(TRIM(E19))="SG",UPPER(TRIM(E19))="SINGAPORE"),"Singapore",TRIM(E19))))))))) -> United States | G19: Mechanical Keyboard | H19: Accessories | I19: 2 | J19: 65 | K19: 31 | L19: 0.1 | M19: paypal | N19: PayPal | O19: Completed | P19: =PROPER(TRIM(O19)) -> Completed | Q19: =IF(TRIM(R19)="","Missing",IF(AND(ISNUMBER(SEARCH("@",R19)),ISNUMBER(SEARCH(".",R19,SEARCH("@",R19)+2))),"Valid","Invalid")) -> Valid | R19: lucas.jackson@example.com | S19: =I19*J19*(1-L19) -> 117 | T19: =I19*K19 -> 62 | U19: =S19-T19 -> 55 | V19: =IF(S19=0,0,U19/S19) -> 0.47008547
A20: ORD-10033 | B20: 45979 | C20: Henry Clark | D20: =PROPER(TRIM(C20)) -> Henry Clark | E20: US | F20: =IF(OR(UPPER(TRIM(E20))="AUS",UPPER(TRIM(E20))="AUSTRALIA"),"Australia",IF(OR(UPPER(TRIM(E20))="CAN",UPPER(TRIM(E20))="CANADA"),"Canada",IF(OR(UPPER(TRIM(E20))="DE",UPPER(TRIM(E20))="GERMANY"),"Germany",IF(OR(UPPER(TRIM(E20))="IN",UPPER(TRIM(E20))="INDIA"),"India",IF(OR(UPPER(TRIM(E20))="US",UPPER(TRIM(E20))="USA",UPPER(TRIM(E20))="UNITED STATES"),"United States",IF(OR(UPPER(TRIM(E20))="UK",UPPER(TRIM(E20))="U.K.",UPPER(TRIM(E20))="UNITED KINGDOM"),"United Kingdom",IF(OR(UPPER(TRIM(E20))="UAE",UPPER(TRIM(E20))="U.A.E.",UPPER(TRIM(E20))="UNITED ARAB EMIRATES"),"United Arab Emirates",IF(OR(UPPER(TRIM(E20))="SG",UPPER(TRIM(E20))="SINGAPORE"),"Singapore",TRIM(E20))))))))) -> United States | G20: Laptop Stand | H20: Accessories | I20: 4 | J20: 38 | K20: 17 | L20: 0.15 | M20: Bank Transfer | N20: =PROPER(TRIM(M20)) -> Bank Transfer | O20: Pending | P20: =PROPER(TRIM(O20)) -> Pending | Q20: =IF(TRIM(R20)="","Missing",IF(AND(ISNUMBER(SEARCH("@",R20)),ISNUMBER(SEARCH(".",R20,SEARCH("@",R20)+2))),"Valid","Invalid")) -> Missing | S20: =I20*J20*(1-L20) -> 129.2 | T20: =I20*K20 -> 68 | U20: =S20-T20 -> 61.2 | V20: =IF(S20=0,0,U20/S20) -> 0.47368421
A21: ORD-10264 | B21: 45815 | C21: Chloe Lewis | D21: =PROPER(TRIM(C21)) -> Chloe Lewis | E21: DE | F21: =IF(OR(UPPER(TRIM(E21))="AUS",UPPER(TRIM(E21))="AUSTRALIA"),"Australia",IF(OR(UPPER(TRIM(E21))="CAN",UPPER(TRIM(E21))="CANADA"),"Canada",IF(OR(UPPER(TRIM(E21))="DE",UPPER(TRIM(E21))="GERMANY"),"Germany",IF(OR(UPPER(TRIM(E21))="IN",UPPER(TRIM(E21))="INDIA"),"India",IF(OR(UPPER(TRIM(E21))="US",UPPER(TRIM(E21))="USA",UPPER(TRIM(E21))="UNITED STATES"),"United States",IF(OR(UPPER(TRIM(E21))="UK",UPPER(TRIM(E21))="U.K.",UPPER(TRIM(E21))="UNITED KINGDOM"),"United Kingdom",IF(OR(UPPER(TRIM(E21))="UAE",UPPER(TRIM(E21))="U.A.E.",UPPER(TRIM(E21))="UNITED ARAB EMIRATES"),"United Arab Emirates",IF(OR(UPPER(TRIM(E21))="SG",UPPER(TRIM(E21))="SINGAPORE"),"Singapore",TRIM(E21))))))))) -> Germany | G21: SSD 1TB | H21: Storage | I21: 1 | J21: 92 | K21: 53 | L21: 0.2 | M21: Bank Transfer | N21: =PROPER(TRIM(M21)) -> Bank Transfer | O21: Shipped | P21: =PROPER(TRIM(O21)) -> Shipped | Q21: =IF(TRIM(R21)="","Missing",IF(AND(ISNUMBER(SEARCH("@",R21)),ISNUMBER(SEARCH(".",R21,SEARCH("@",R21)+2))),"Valid","Invalid")) -> Valid | R21: chloe.lewis@example.com | S21: =I21*J21*(1-L21) -> 73.6 | T21: =I21*K21 -> 53 | U21: =S21-T21 -> 20.6 | V21: =IF(S21=0,0,U21/S21) -> 0.2798913
A22: ORD-10210 | B22: 45889 | C22: Chloe Lewis | D22: =PROPER(TRIM(C22)) -> Chloe Lewis | E22: United Kingdom | F22: =IF(OR(UPPER(TRIM(E22))="AUS",UPPER(TRIM(E22))="AUSTRALIA"),"Australia",IF(OR(UPPER(TRIM(E22))="CAN",UPPER(TRIM(E22))="CANADA"),"Canada",IF(OR(UPPER(TRIM(E22))="DE",UPPER(TRIM(E22))="GERMANY"),"Germany",IF(OR(UPPER(TRIM(E22))="IN",UPPER(TRIM(E22))="INDIA"),"India",IF(OR(UPPER(TRIM(E22))="US",UPPER(TRIM(E22))="USA",UPPER(TRIM(E22))="UNITED STATES"),"United States",IF(OR(UPPER(TRIM(E22))="UK",UPPER(TRIM(E22))="U.K.",UPPER(TRIM(E22))="UNITED KINGDOM"),"United Kingdom",IF(OR(UPPER(TRIM(E22))="UAE",UPPER(TRIM(E22))="U.A.E.",UPPER(TRIM(E22))="UNITED ARAB EMIRATES"),"United Arab Emirates",IF(OR(UPPER(TRIM(E22))="SG",UPPER(TRIM(E22))="SINGAPORE"),"Singapore",TRIM(E22))))))))) -> United Kingdom | G22: Webcam | H22: Electronics | I22: 4 | J22: 59 | K22: 30 | L22: 0.15 | M22: Credit Card | N22: =PROPER(TRIM(M22)) -> Credit Card | O22: Completed | P22: =PROPER(TRIM(O22)) -> Completed | Q22: =IF(TRIM(R22)="","Missing",IF(AND(ISNUMBER(SEARCH("@",R22)),ISNUMBER(SEARCH(".",R22,SEARCH("@",R22)+2))),"Valid","Invalid")) -> Missing | S22: =I22*J22*(1-L22) -> 200.6 | T22: =I22*K22 -> 120 | U22: =S22-T22 -> 80.6 | V22: =IF(S22=0,0,U22/S22) -> 0.40179462
A23: ORD-10274 | B23: 45831 | C23: Ava Thomas | D23: =PROPER(TRIM(C23)) -> Ava Thomas | E23: Singapore | F23: =IF(OR(UPPER(TRIM(E23))="AUS",UPPER(TRIM(E23))="AUSTRALIA"),"Australia",IF(OR(UPPER(TRIM(E23))="CAN",UPPER(TRIM(E23))="CANADA"),"Canada",IF(OR(UPPER(TRIM(E23))="DE",UPPER(TRIM(E23))="GERMANY"),"Germany",IF(OR(UPPER(TRIM(E23))="IN",UPPER(TRIM(E23))="INDIA"),"India",IF(OR(UPPER(TRIM(E23))="US",UPPER(TRIM(E23))="USA",UPPER(TRIM(E23))="UNITED STATES"),"United States",IF(OR(UPPER(TRIM(E23))="UK",UPPER(TRIM(E23))="U.K.",UPPER(TRIM(E23))="UNITED KINGDOM"),"United Kingdom",IF(OR(UPPER(TRIM(E23))="UAE",UPPER(TRIM(E23))="U.A.E.",UPPER(TRIM(E23))="UNITED ARAB EMIRATES"),"United Arab Emirates",IF(OR(UPPER(TRIM(E23))="SG",UPPER(TRIM(E23))="SINGAPORE"),"Singapore",TRIM(E23))))))))) -> Singapore | G23: External HDD 2TB | H23: Storage | I23: 4 | J23: 78 | K23: 45 | L23: 0.1 | N23: Unknown | O23: Pending | P23: =PROPER(TRIM(O23)) -> Pending | Q23: =IF(TRIM(R23)="","Missing",IF(AND(ISNUMBER(SEARCH("@",R23)),ISNUMBER(SEARCH(".",R23,SEARCH("@",R23)+2))),"Valid","Invalid")) -> Valid | R23: ava.thomas@example.com | S23: =I23*J23*(1-L23) -> 280.8 | T23: =I23*K23 -> 180 | U23: =S23-T23 -> 100.8 | V23: =IF(S23=0,0,U23/S23) -> 0.35897436
A24: ORD-10004 | B24: 45792 | C24: Noah Brown | D24: =PROPER(TRIM(C24)) -> Noah Brown | E24: Australia | F24: =IF(OR(UPPER(TRIM(E24))="AUS",UPPER(TRIM(E24))="AUSTRALIA"),"Australia",IF(OR(UPPER(TRIM(E24))="CAN",UPPER(TRIM(E24))="CANADA"),"Canada",IF(OR(UPPER(TRIM(E24))="DE",UPPER(TRIM(E24))="GERMANY"),"Germany",IF(OR(UPPER(TRIM(E24))="IN",UPPER(TRIM(E24))="INDIA"),"India",IF(OR(UPPER(TRIM(E24))="US",UPPER(TRIM(E24))="USA",UPPER(TRIM(E24))="UNITED STATES"),"United States",IF(OR(UPPER(TRIM(E24))="UK",UPPER(TRIM(E24))="U.K.",UPPER(TRIM(E24))="UNITED KINGDOM"),"United Kingdom",IF(OR(UPPER(TRIM(E24))="UAE",UPPER(TRIM(E24))="U.A.E.",UPPER(TRIM(E24))="UNITED ARAB EMIRATES"),"United Arab Emirates",IF(OR(UPPER(TRIM(E24))="SG",UPPER(TRIM(E24))="SINGAPORE"),"Singapore",TRIM(E24))))))))) -> Australia | G24: USB-C Hub | H24: Accessories | I24: 4 | J24: 42 | K24: 21 | L24: 0.05 | M24: Credit Card | N24: =PROPER(TRIM(M24)) -> Credit Card | O24: Cancelled | P24: =PROPER(TRIM(O24)) -> Cancelled | Q24: =IF(TRIM(R24)="","Missing",IF(AND(ISNUMBER(SEARCH("@",R24)),ISNUMBER(SEARCH(".",R24,SEARCH("@",R24)+2))),"Valid","Invalid")) -> Valid | R24: noah.brown@example.com | S24: =I24*J24*(1-L24) -> 159.6 | T24: =I24*K24 -> 84 | U24: =S24-T24 -> 75.6 | V24: =IF(S24=0,0,U24/S24) -> 0.47368421
A25: ORD-10200 | B25: 45933 | C25: Noah Brown | D25: =PROPER(TRIM(C25)) -> Noah Brown | E25: Canada | F25: =IF(OR(UPPER(TRIM(E25))="AUS",UPPER(TRIM(E25))="AUSTRALIA"),"Australia",IF(OR(UPPER(TRIM(E25))="CAN",UPPER(TRIM(E25))="CANADA"),"Canada",IF(OR(UPPER(TRIM(E25))="DE",UPPER(TRIM(E25))="GERMANY"),"Germany",IF(OR(UPPER(TRIM(E25))="IN",UPPER(TRIM(E25))="INDIA"),"India",IF(OR(UPPER(TRIM(E25))="US",UPPER(TRIM(E25))="USA",UPPER(TRIM(E25))="UNITED STATES"),"United States",IF(OR(UPPER(TRIM(E25))="UK",UPPER(TRIM(E25))="U.K.",UPPER(TRIM(E25))="UNITED KINGDOM"),"United Kingdom",IF(OR(UPPER(TRIM(E25))="UAE",UPPER(TRIM(E25))="U.A.E.",UPPER(TRIM(E25))="UNITED ARAB EMIRATES"),"United Arab Emirates",IF(OR(UPPER(TRIM(E25))="SG",UPPER(TRIM(E25))="SINGAPORE"),"Singapore",TRIM(E25))))))))) -> Canada | G25: Webcam | H25: Electronics | I25: 2 | J25: 59 | K25: 30 | L25: 0 | M25: PayPal | N25: PayPal | O25: Completed | P25: =PROPER(TRIM(O25)) -> Completed | Q25: =IF(TRIM(R25)="","Missing",IF(AND(ISNUMBER(SEARCH("@",R25)),ISNUMBER(SEARCH(".",R25,SEARCH("@",R25)+2))),"Valid","Invalid")) -> Valid | R25: noah.brown@example.com | S25: =I25*J25*(1-L25) -> 118 | T25: =I25*K25 -> 60 | U25: =S25-T25 -> 58 | V25: =IF(S25=0,0,U25/S25) -> 0.49152542
A26: ORD-10191 | B26: 45684 | C26: Emma Wilson | D26: =PROPER(TRIM(C26)) -> Emma Wilson | E26: US | F26: =IF(OR(UPPER(TRIM(E26))="AUS",UPPER(TRIM(E26))="AUSTRALIA"),"Australia",IF(OR(UPPER(TRIM(E26))="CAN",UPPER(TRIM(E26))="CANADA"),"Canada",IF(OR(UPPER(TRIM(E26))="DE",UPPER(TRIM(E26))="GERMANY"),"Germany",IF(OR(UPPER(TRIM(E26))="IN",UPPER(TRIM(E26))="INDIA"),"India",IF(OR(UPPER(TRIM(E26))="US",UPPER(TRIM(E26))="USA",UPPER(TRIM(E26))="UNITED STATES"),"United States",IF(OR(UPPER(TRIM(E26))="UK",UPPER(TRIM(E26))="U.K.",UPPER(TRIM(E26))="UNITED KINGDOM"),"United Kingdom",IF(OR(UPPER(TRIM(E26))="UAE",UPPER(TRIM(E26))="U.A.E.",UPPER(TRIM(E26))="UNITED ARAB EMIRATES"),"United Arab Emirates",IF(OR(UPPER(TRIM(E26))="SG",UPPER(TRIM(E26))="SINGAPORE"),"Singapore",TRIM(E26))))))))) -> United States | G26: Headphones | H26: Electronics | I26: 4 | J26: 85 | K26: 44 | L26: 0.05 | M26: paypal | N26: PayPal | O26: Cancelled | P26: =PROPER(TRIM(O26)) -> Cancelled | Q26: =IF(TRIM(R26)="","Missing",IF(AND(ISNUMBER(SEARCH("@",R26)),ISNUMBER(SEARCH(".",R26,SEARCH("@",R26)+2))),"Valid","Invalid")) -> Valid | R26: emma.wilson@example.com | S26: =I26*J26*(1-L26) -> 323 | T26: =I26*K26 -> 176 | U26: =S26-T26 -> 147 | V26: =IF(S26=0,0,U26/S26) -> 0.45510836
A27: ORD-10266 | B27: 45733 | C27: Henry Clark | D27: =PROPER(TRIM(C27)) -> Henry Clark | E27: India | F27: =IF(OR(UPPER(TRIM(E27))="AUS",UPPER(TRIM(E27))="AUSTRALIA"),"Australia",IF(OR(UPPER(TRIM(E27))="CAN",UPPER(TRIM(E27))="CANADA"),"Canada",IF(OR(UPPER(TRIM(E27))="DE",UPPER(TRIM(E27))="GERMANY"),"Germany",IF(OR(UPPER(TRIM(E27))="IN",UPPER(TRIM(E27))="INDIA"),"India",IF(OR(UPPER(TRIM(E27))="US",UPPER(TRIM(E27))="USA",UPPER(TRIM(E27))="UNITED STATES"),"United States",IF(OR(UPPER(TRIM(E27))="UK",UPPER(TRIM(E27))="U.K.",UPPER(TRIM(E27))="UNITED KINGDOM"),"United Kingdom",IF(OR(UPPER(TRIM(E27))="UAE",UPPER(TRIM(E27))="U.A.E.",UPPER(TRIM(E27))="UNITED ARAB EMIRATES"),"United Arab Emirates",IF(OR(UPPER(TRIM(E27))="SG",UPPER(TRIM(E27))="SINGAPORE"),"Singapore",TRIM(E27))))))))) -> India | G27: Mechanical Keyboard | H27: Accessories | I27: 1 | J27: 65 | K27: 31 | L27: 0 | M27: Credit Card | N27: =PROPER(TRIM(M27)) -> Credit Card | O27: Pending | P27: =PROPER(TRIM(O27)) -> Pending | Q27: =IF(TRIM(R27)="","Missing",IF(AND(ISNUMBER(SEARCH("@",R27)),ISNUMBER(SEARCH(".",R27,SEARCH("@",R27)+2))),"Valid","Invalid")) -> Valid | R27: henry.clark@example.com | S27: =I27*J27*(1-L27) -> 65 | T27: =I27*K27 -> 31 | U27: =S27-T27 -> 34 | V27: =IF(S27=0,0,U27/S27) -> 0.52307692
A28: ORD-10280 | B28: 45852 | C28: Ella Martin | D28: =PROPER(TRIM(C28)) -> Ella Martin | E28: germany | F28: =IF(OR(UPPER(TRIM(E28))="AUS",UPPER(TRIM(E28))="AUSTRALIA"),"Australia",IF(OR(UPPER(TRIM(E28))="CAN",UPPER(TRIM(E28))="CANADA"),"Canada",IF(OR(UPPER(TRIM(E28))="DE",UPPER(TRIM(E28))="GERMANY"),"Germany",IF(OR(UPPER(TRIM(E28))="IN",UPPER(TRIM(E28))="INDIA"),"India",IF(OR(UPPER(TRIM(E28))="US",UPPER(TRIM(E28))="USA",UPPER(TRIM(E28))="UNITED STATES"),"United States",IF(OR(UPPER(TRIM(E28))="UK",UPPER(TRIM(E28))="U.K.",UPPER(TRIM(E28))="UNITED KINGDOM"),"United Kingdom",IF(OR(UPPER(TRIM(E28))="UAE",UPPER(TRIM(E28))="U.A.E.",UPPER(TRIM(E28))="UNITED ARAB EMIRATES"),"United Arab Emirates",IF(OR(UPPER(TRIM(E28))="SG",UPPER(TRIM(E28))="SINGAPORE"),"Singapore",TRIM(E28))))))))) -> Germany | G28: SSD 1TB | H28: Storage | I28: 2 | J28: 92 | K28: 53 | L28: 0.05 | M28: Debit Card | N28: =PROPER(TRIM(M28)) -> Debit Card | O28: Shipped | P28: =PROPER(TRIM(O28)) -> Shipped | Q28: =IF(TRIM(R28)="","Missing",IF(AND(ISNUMBER(SEARCH("@",R28)),ISNUMBER(SEARCH(".",R28,SEARCH("@",R28)+2))),"Valid","Invalid")) -> Valid | R28: ella.martin@example.com | S28: =I28*J28*(1-L28) -> 174.8 | T28: =I28*K28 -> 106 | U28: =S28-T28 -> 68.8 | V28: =IF(S28=0,0,U28/S28) -> 0.39359268
A29: ORD-10209 | B29: 45845 | C29: Olivia Davis | D29: =PROPER(TRIM(C29)) -> Olivia Davis | E29: U.K. | F29: =IF(OR(UPPER(TRIM(E29))="AUS",UPPER(TRIM(E29))="AUSTRALIA"),"Australia",IF(OR(UPPER(TRIM(E29))="CAN",UPPER(TRIM(E29))="CANADA"),"Canada",IF(OR(UPPER(TRIM(E29))="DE",UPPER(TRIM(E29))="GERMANY"),"Germany",IF(OR(UPPER(TRIM(E29))="IN",UPPER(TRIM(E29))="INDIA"),"India",IF(OR(UPPER(TRIM(E29))="US",UPPER(TRIM(E29))="USA",UPPER(TRIM(E29))="UNITED STATES"),"United States",IF(OR(UPPER(TRIM(E29))="UK",UPPER(TRIM(E29))="U.K.",UPPER(TRIM(E29))="UNITED KINGDOM"),"United Kingdom",IF(OR(UPPER(TRIM(E29))="UAE",UPPER(TRIM(E29))="U.A.E.",UPPER(TRIM(E29))="UNITED ARAB EMIRATES"),"United Arab Emirates",IF(OR(UPPER(TRIM(E29))="SG",UPPER(TRIM(E29))="SINGAPORE"),"Singapore",TRIM(E29))))))))) -> United Kingdom | G29: Webcam | H29: Electronics | I29: 5 | J29: 59 | K29: 30 | L29: 0.2 | M29: credit card | N29: =PROPER(TRIM(M29)) -> Credit Card | O29: Completed | P29: =PROPER(TRIM(O29)) -> Completed | Q29: =IF(TRIM(R29)="","Missing",IF(AND(ISNUMBER(SEARCH("@",R29)),ISNUMBER(SEARCH(".",R29,SEARCH("@",R29)+2))),"Valid","Invalid")) -> Valid | R29: olivia.davis@example.com | S29: =I29*J29*(1-L29) -> 236 | T29: =I29*K29 -> 150 | U29: =S29-T29 -> 86 | V29: =IF(S29=0,0,U29/S29) -> 0.36440678
A30: ORD-10028 | B30: 45706 | C30: olivia davis | D30: =PROPER(TRIM(C30)) -> Olivia Davis | E30: Germany | F30: =IF(OR(UPPER(TRIM(E30))="AUS",UPPER(TRIM(E30))="AUSTRALIA"),"Australia",IF(OR(UPPER(TRIM(E30))="CAN",UPPER(TRIM(E30))="CANADA"),"Canada",IF(OR(UPPER(TRIM(E30))="DE",UPPER(TRIM(E30))="GERMANY"),"Germany",IF(OR(UPPER(TRIM(E30))="IN",UPPER(TRIM(E30))="INDIA"),"India",IF(OR(UPPER(TRIM(E30))="US",UPPER(TRIM(E30))="USA",UPPER(TRIM(E30))="UNITED STATES"),"United States",IF(OR(UPPER(TRIM(E30))="UK",UPPER(TRIM(E30))="U.K.",UPPER(TRIM(E30))="UNITED KINGDOM"),"United Kingdom",IF(OR(UPPER(TRIM(E30))="UAE",UPPER(TRIM(E30))="U.A.E.",UPPER(TRIM(E30))="UNITED ARAB EMIRATES"),"United Arab Emirates",IF(OR(UPPER(TRIM(E30))="SG",UPPER(TRIM(E30))="SINGAPORE"),"Singapore",TRIM(E30))))))))) -> Germany | G30: Wireless Mouse | H30: Accessories | I30: 4 | J30: 18 | K30: 7 | L30: 0.1 | M30: Debit Card | N30: =PROPER(TRIM(M30)) -> Debit Card | O30: Completed | P30: =PROPER(TRIM(O30)) -> Completed | Q30: =IF(TRIM(R30)="","Missing",IF(AND(ISNUMBER(SEARCH("@",R30)),ISNUMBER(SEARCH(".",R30,SEARCH("@",R30)+2))),"Valid","Invalid")) -> Valid | R30: olivia.davis@example.com | S30: =I30*J30*(1-L30) -> 64.8 | T30: =I30*K30 -> 28 | U30: =S30-T30 -> 36.8 | V30: =IF(S30=0,0,U30/S30) -> 0.56790123
A31: ORD-10211 | B31: 45674 | C31: Benjamin Walker | D31: =PROPER(TRIM(C31)) -> Benjamin Walker | E31: united kingdom | F31: =IF(OR(UPPER(TRIM(E31))="AUS",UPPER(TRIM(E31))="AUSTRALIA"),"Australia",IF(OR(UPPER(TRIM(E31))="CAN",UPPER(TRIM(E31))="CANADA"),"Canada",IF(OR(UPPER(TRIM(E31))="DE",UPPER(TRIM(E31))="GERMANY"),"Germany",IF(OR(UPPER(TRIM(E31))="IN",UPPER(TRIM(E31))="INDIA"),"India",IF(OR(UPPER(TRIM(E31))="US",UPPER(TRIM(E31))="USA",UPPER(TRIM(E31))="UNITED STATES"),"United States",IF(OR(UPPER(TRIM(E31))="UK",UPPER(TRIM(E31))="U.K.",UPPER(TRIM(E31))="UNITED KINGDOM"),"United Kingdom",IF(OR(UPPER(TRIM(E31))="UAE",UPPER(TRIM(E31))="U.A.E.",UPPER(TRIM(E31))="UNITED ARAB EMIRATES"),"United Arab Emirates",IF(OR(UPPER(TRIM(E31))="SG",UPPER(TRIM(E31))="SINGAPORE"),"Singapore",TRIM(E31))))))))) -> United Kingdom | G31: Headphones | H31: Electronics | I31: 5 | J31: 85 | K31: 44 | L31: 0.2 | M31: Credit Card | N31: =PROPER(TRIM(M31)) -> Credit Card | O31: Completed | P31: =PROPER(TRIM(O31)) -> Completed | Q31: =IF(TRIM(R31)="","Missing",IF(AND(ISNUMBER(SEARCH("@",R31)),ISNUMBER(SEARCH(".",R31,SEARCH("@",R31)+2))),"Valid","Invalid")) -> Valid | R31: benjamin.walker@example.com | S31: =I31*J31*(1-L31) -> 340 | T31: =I31*K31 -> 220 | U31: =S31-T31 -> 120 | V31: =IF(S31=0,0,U31/S31) -> 0.35294118
A32: ORD-10372 | B32: 45778 | C32: grace moore | D32: =PROPER(TRIM(C32)) -> Grace Moore | E32: Singapore | F32: =IF(OR(UPPER(TRIM(E32))="AUS",UPPER(TRIM(E32))="AUSTRALIA"),"Australia",IF(OR(UPPER(TRIM(E32))="CAN",UPPER(TRIM(E32))="CANADA"),"Canada",IF(OR(UPPER(TRIM(E32))="DE",UPPER(TRIM(E32))="GERMANY"),"Germany",IF(OR(UPPER(TRIM(E32))="IN",UPPER(TRIM(E32))="INDIA"),"India",IF(OR(UPPER(TRIM(E32))="US",UPPER(TRIM(E32))="USA",UPPER(TRIM(E32))="UNITED STATES"),"United States",IF(OR(UPPER(TRIM(E32))="UK",UPPER(TRIM(E32))="U.K.",UPPER(TRIM(E32))="UNITED KINGDOM"),"United Kingdom",IF(OR(UPPER(TRIM(E32))="UAE",UPPER(TRIM(E32))="U.A.E.",UPPER(TRIM(E32))="UNITED ARAB EMIRATES"),"United Arab Emirates",IF(OR(UPPER(TRIM(E32))="SG",UPPER(TRIM(E32))="SINGAPORE"),"Singapore",TRIM(E32))))))))) -> Singapore | G32: Desk Lamp | H32: Furniture | I32: 1 | J32: 36 | K32: 16 | L32: 0.1 | M32: paypal | N32: PayPal | O32: Completed | P32: =PROPER(TRIM(O32)) -> Completed | Q32: =IF(TRIM(R32)="","Missing",IF(AND(ISNUMBER(SEARCH("@",R32)),ISNUMBER(SEARCH(".",R32,SEARCH("@",R32)+2))),"Valid","Invalid")) -> Valid | R32: grace.moore@example.com | S32: =I32*J32*(1-L32) -> 32.4 | T32: =I32*K32 -> 16 | U32: =S32-T32 -> 16.4 | V32: =IF(S32=0,0,U32/S32) -> 0.50617284
A33: ORD-10306 | B33: 45811 | C33: Benjamin Walker | D33: =PROPER(TRIM(C33)) -> Benjamin Walker | E33: US | F33: =IF(OR(UPPER(TRIM(E33))="AUS",UPPER(TRIM(E33))="AUSTRALIA"),"Australia",IF(OR(UPPER(TRIM(E33))="CAN",UPPER(TRIM(E33))="CANADA"),"Canada",IF(OR(UPPER(TRIM(E33))="DE",UPPER(TRIM(E33))="GERMANY"),"Germany",IF(OR(UPPER(TRIM(E33))="IN",UPPER(TRIM(E33))="INDIA"),"India",IF(OR(UPPER(TRIM(E33))="US",UPPER(TRIM(E33))="USA",UPPER(TRIM(E33))="UNITED STATES"),"United States",IF(OR(UPPER(TRIM(E33))="UK",UPPER(TRIM(E33))="U.K.",UPPER(TRIM(E33))="UNITED KINGDOM"),"United Kingdom",IF(OR(UPPER(TRIM(E33))="UAE",UPPER(TRIM(E33))="U.A.E.",UPPER(TRIM(E33))="UNITED ARAB EMIRATES"),"United Arab Emirates",IF(OR(UPPER(TRIM(E33))="SG",UPPER(TRIM(E33))="SINGAPORE"),"Singapore",TRIM(E33))))))))) -> United States | G33: Office Chair | H33: Furniture | I33: 4 | J33: 210 | K33: 125 | L33: 0.05 | M33: paypal | N33: PayPal | O33: Completed | P33: =PROPER(TRIM(O33)) -> Completed | Q33: =IF(TRIM(R33)="","Missing",IF(AND(ISNUMBER(SEARCH("@",R33)),ISNUMBER(SEARCH(".",R33,SEARCH("@",R33)+2))),"Valid","Invalid")) -> Valid | R33: benjamin.walker@example.com | S33: =I33*J33*(1-L33) -> 798 | T33: =I33*K33 -> 500 | U33: =S33-T33 -> 298 | V33: =IF(S33=0,0,U33/S33) -> 0.37343358
A34: ORD-10444 | B34: 45747 | C34: Ella Martin | D34: =PROPER(TRIM(C34)) -> Ella Martin | E34: Australia | F34: =IF(OR(UPPER(TRIM(E34))="AUS",UPPER(TRIM(E34))="AUSTRALIA"),"Australia",IF(OR(UPPER(TRIM(E34))="CAN",UPPER(TRIM(E34))="CANADA"),"Canada",IF(OR(UPPER(TRIM(E34))="DE",UPPER(TRIM(E34))="GERMANY"),"Germany",IF(OR(UPPER(TRIM(E34))="IN",UPPER(TRIM(E34))="INDIA"),"India",IF(OR(UPPER(TRIM(E34))="US",UPPER(TRIM(E34))="USA",UPPER(TRIM(E34))="UNITED STATES"),"United States",IF(OR(UPPER(TRIM(E34))="UK",UPPER(TRIM(E34))="U.K.",UPPER(TRIM(E34))="UNITED KINGDOM"),"United Kingdom",IF(OR(UPPER(TRIM(E34))="UAE",UPPER(TRIM(E34))="U.A.E.",UPPER(TRIM(E34))="UNITED ARAB EMIRATES"),"United Arab Emirates",IF(OR(UPPER(TRIM(E34))="SG",UPPER(TRIM(E34))="SINGAPORE"),"Singapore",TRIM(E34))))))))) -> Australia | G34: Monitor 27-inch | H34: Electronics | I34: 3 | J34: 245 | K34: 150 | L34: 0.1 | M34: Bank Transfer | N34: =PROPER(TRIM(M34)) -> Bank Transfer | O34: Cancelled | P34: =PROPER(TRIM(O34)) -> Cancelled | Q34: =IF(TRIM(R34)="","Missing",IF(AND(ISNUMBER(SEARCH("@",R34)),ISNUMBER(SEARCH(".",R34,SEARCH("@",R34)+2))),"Valid","Invalid")) -> Valid | R34: ella.martin@example.com | S34: =I34*J34*(1-L34) -> 661.5 | T34: =I34*K34 -> 450 | U34: =S34-T34 -> 211.5 | V34: =IF(S34=0,0,U34/S34) -> 0.31972789
A35: ORD-10201 | B35: 45967 | C35: Alex Morgan | D35: =PROPER(TRIM(C35)) -> Alex Morgan | E35: US | F35: =IF(OR(UPPER(TRIM(E35))="AUS",UPPER(TRIM(E35))="AUSTRALIA"),"Australia",IF(OR(UPPER(TRIM(E35))="CAN",UPPER(TRIM(E35))="CANADA"),"Canada",IF(OR(UPPER(TRIM(E35))="DE",UPPER(TRIM(E35))="GERMANY"),"Germany",IF(OR(UPPER(TRIM(E35))="IN",UPPER(TRIM(E35))="INDIA"),"India",IF(OR(UPPER(TRIM(E35))="US",UPPER(TRIM(E35))="USA",UPPER(TRIM(E35))="UNITED STATES"),"United States",IF(OR(UPPER(TRIM(E35))="UK",UPPER(TRIM(E35))="U.K.",UPPER(TRIM(E35))="UNITED KINGDOM"),"United Kingdom",IF(OR(UPPER(TRIM(E35))="UAE",UPPER(TRIM(E35))="U.A.E.",UPPER(TRIM(E35))="UNITED ARAB EMIRATES"),"United Arab Emirates",IF(OR(UPPER(TRIM(E35))="SG",UPPER(TRIM(E35))="SINGAPORE"),"Singapore",TRIM(E35))))))))) -> United States | G35: Headphones | H35: Electronics | I35: 4 | J35: 85 | K35: 44 | L35: 0.05 | M35: credit card | N35: =PROPER(TRIM(M35)) -> Credit Card | O35: Pending | P35: =PROPER(TRIM(O35)) -> Pending | Q35: =IF(TRIM(R35)="","Missing",IF(AND(ISNUMBER(SEARCH("@",R35)),ISNUMBER(SEARCH(".",R35,SEARCH("@",R35)+2))),"Valid","Invalid")) -> Valid | R35: alex.morgan@example.com | S35: =I35*J35*(1-L35) -> 323 | T35: =I35*K35 -> 176 | U35: =S35-T35 -> 147 | V35: =IF(S35=0,0,U35/S35) -> 0.45510836
A36: ORD-10223 | B36: 45938 | C36: Ethan Anderson | D36: =PROPER(TRIM(C36)) -> Ethan Anderson | E36: India | F36: =IF(OR(UPPER(TRIM(E36))="AUS",UPPER(TRIM(E36))="AUSTRALIA"),"Australia",IF(OR(UPPER(TRIM(E36))="CAN",UPPER(TRIM(E36))="CANADA"),"Canada",IF(OR(UPPER(TRIM(E36))="DE",UPPER(TRIM(E36))="GERMANY"),"Germany",IF(OR(UPPER(TRIM(E36))="IN",UPPER(TRIM(E36))="INDIA"),"India",IF(OR(UPPER(TRIM(E36))="US",UPPER(TRIM(E36))="USA",UPPER(TRIM(E36))="UNITED STATES"),"United States",IF(OR(UPPER(TRIM(E36))="UK",UPPER(TRIM(E36))="U.K.",UPPER(TRIM(E36))="UNITED KINGDOM"),"United Kingdom",IF(OR(UPPER(TRIM(E36))="UAE",UPPER(TRIM(E36))="U.A.E.",UPPER(TRIM(E36))="UNITED ARAB EMIRATES"),"United Arab Emirates",IF(OR(UPPER(TRIM(E36))="SG",UPPER(TRIM(E36))="SINGAPORE"),"Singapore",TRIM(E36))))))))) -> India | G36: Wireless Mouse | H36: Accessories | I36: 3 | J36: 18 | K36: 7 | L36: 0 | M36: PayPal | N36: PayPal | O36: Cancelled | P36: =PROPER(TRIM(O36)) -> Cancelled | Q36: =IF(TRIM(R36)="","Missing",IF(AND(ISNUMBER(SEARCH("@",R36)),ISNUMBER(SEARCH(".",R36,SEARCH("@",R36)+2))),"Valid","Invalid")) -> Valid | R36: ethan.anderson@example.com | S36: =I36*J36*(1-L36) -> 54 | T36: =I36*K36 -> 21 | U36: =S36-T36 -> 33 | V36: =IF(S36=0,0,U36/S36) -> 0.61111111
A37: ORD-10379 | B37: 45772 | C37: Mia White | D37: =PROPER(TRIM(C37)) -> Mia White | E37: india | F37: =IF(OR(UPPER(TRIM(E37))="AUS",UPPER(TRIM(E37))="AUSTRALIA"),"Australia",IF(OR(UPPER(TRIM(E37))="CAN",UPPER(TRIM(E37))="CANADA"),"Canada",IF(OR(UPPER(TRIM(E37))="DE",UPPER(TRIM(E37))="GERMANY"),"Germany",IF(OR(UPPER(TRIM(E37))="IN",UPPER(TRIM(E37))="INDIA"),"India",IF(OR(UPPER(TRIM(E37))="US",UPPER(TRIM(E37))="USA",UPPER(TRIM(E37))="UNITED STATES"),"United States",IF(OR(UPPER(TRIM(E37))="UK",UPPER(TRIM(E37))="U.K.",UPPER(TRIM(E37))="UNITED KINGDOM"),"United Kingdom",IF(OR(UPPER(TRIM(E37))="UAE",UPPER(TRIM(E37))="U.A.E.",UPPER(TRIM(E37))="UNITED ARAB EMIRATES"),"United Arab Emirates",IF(OR(UPPER(TRIM(E37))="SG",UPPER(TRIM(E37))="SINGAPORE"),"Singapore",TRIM(E37))))))))) -> India | G37: Office Chair | H37: Furniture | I37: 2 | J37: 210 | K37: 125 | L37: 0.15 | M37: PayPal | N37: PayPal | O37: Shipped | P37: =PROPER(TRIM(O37)) -> Shipped | Q37: =IF(TRIM(R37)="","Missing",IF(AND(ISNUMBER(SEARCH("@",R37)),ISNUMBER(SEARCH(".",R37,SEARCH("@",R37)+2))),"Valid","Invalid")) -> Valid | R37: mia.white@example.com | S37: =I37*J37*(1-L37) -> 357 | T37: =I37*K37 -> 250 | U37: =S37-T37 -> 107 | V37: =IF(S37=0,0,U37/S37) -> 0.29971989
A38: ORD-10141 | B38: 45983 | C38: James Thompson | D38: =PROPER(TRIM(C38)) -> James Thompson | E38: Singapore | F38: =IF(OR(UPPER(TRIM(E38))="AUS",UPPER(TRIM(E38))="AUSTRALIA"),"Australia",IF(OR(UPPER(TRIM(E38))="CAN",UPPER(TRIM(E38))="CANADA"),"Canada",IF(OR(UPPER(TRIM(E38))="DE",UPPER(TRIM(E38))="GERMANY"),"Germany",IF(OR(UPPER(TRIM(E38))="IN",UPPER(TRIM(E38))="INDIA"),"India",IF(OR(UPPER(TRIM(E38))="US",UPPER(TRIM(E38))="USA",UPPER(TRIM(E38))="UNITED STATES"),"United States",IF(OR(UPPER(TRIM(E38))="UK",UPPER(TRIM(E38))="U.K.",UPPER(TRIM(E38))="UNITED KINGDOM"),"United Kingdom",IF(OR(UPPER(TRIM(E38))="UAE",UPPER(TRIM(E38))="U.A.E.",UPPER(TRIM(E38))="UNITED ARAB EMIRATES"),"United Arab Emirates",IF(OR(UPPER(TRIM(E38))="SG",UPPER(TRIM(E38))="SINGAPORE"),"Singapore",TRIM(E38))))))))) -> Singapore | G38: Monitor 27-inch | H38: Electronics | I38: 2 | J38: 245 | K38: 150 | L38: 0.1 | M38: paypal | N38: PayPal | O38: Completed | P38: =PROPER(TRIM(O38)) -> Completed | Q38: =IF(TRIM(R38)="","Missing",IF(AND(ISNUMBER(SEARCH("@",R38)),ISNUMBER(SEARCH(".",R38,SEARCH("@",R38)+2))),"Valid","Invalid")) -> Invalid | R38: james.thompson@example | S38: =I38*J38*(1-L38) -> 441 | T38: =I38*K38 -> 300 | U38: =S38-T38 -> 141 | V38: =IF(S38=0,0,U38/S38) -> 0.31972789
A39: ORD-10149 | B39: 45838 | C39: Ethan Anderson | D39: =PROPER(TRIM(C39)) -> Ethan Anderson | E39: IN | F39: =IF(OR(UPPER(TRIM(E39))="AUS",UPPER(TRIM(E39))="AUSTRALIA"),"Australia",IF(OR(UPPER(TRIM(E39))="CAN",UPPER(TRIM(E39))="CANADA"),"Canada",IF(OR(UPPER(TRIM(E39))="DE",UPPER(TRIM(E39))="GERMANY"),"Germany",IF(OR(UPPER(TRIM(E39))="IN",UPPER(TRIM(E39))="INDIA"),"India",IF(OR(UPPER(TRIM(E39))="US",UPPER(TRIM(E39))="USA",UPPER(TRIM(E39))="UNITED STATES"),"United States",IF(OR(UPPER(TRIM(E39))="UK",UPPER(TRIM(E39))="U.K.",UPPER(TRIM(E39))="UNITED KINGDOM"),"United Kingdom",IF(OR(UPPER(TRIM(E39))="UAE",UPPER(TRIM(E39))="U.A.E.",UPPER(TRIM(E39))="UNITED ARAB EMIRATES"),"United Arab Emirates",IF(OR(UPPER(TRIM(E39))="SG",UPPER(TRIM(E39))="SINGAPORE"),"Singapore",TRIM(E39))))))))) -> India | G39: Webcam | H39: Electronics | I39: 3 | J39: 59 | K39: 30 | L39: 0.15 | M39: PayPal | N39: PayPal | O39: Shipped | P39: =PROPER(TRIM(O39)) -> Shipped | Q39: =IF(TRIM(R39)="","Missing",IF(AND(ISNUMBER(SEARCH("@",R39)),ISNUMBER(SEARCH(".",R39,SEARCH("@",R39)+2))),"Valid","Invalid")) -> Valid | R39: ethan.anderson@example.com | S39: =I39*J39*(1-L39) -> 150.45 | T39: =I39*K39 -> 90 | U39: =S39-T39 -> 60.45 | V39: =IF(S39=0,0,U39/S39) -> 0.40179462
A40: ORD-10546 | B40: 45773 | C40: Benjamin Walker | D40: =PROPER(TRIM(C40)) -> Benjamin Walker | E40: United Arab Emirates | F40: =IF(OR(UPPER(TRIM(E40))="AUS",UPPER(TRIM(E40))="AUSTRALIA"),"Australia",IF(OR(UPPER(TRIM(E40))="CAN",UPPER(TRIM(E40))="CANADA"),"Canada",IF(OR(UPPER(TRIM(E40))="DE",UPPER(TRIM(E40))="GERMANY"),"Germany",IF(OR(UPPER(TRIM(E40))="IN",UPPER(TRIM(E40))="INDIA"),"India",IF(OR(UPPER(TRIM(E40))="US",UPPER(TRIM(E40))="USA",UPPER(TRIM(E40))="UNITED STATES"),"United States",IF(OR(UPPER(TRIM(E40))="UK",UPPER(TRIM(E40))="U.K.",UPPER(TRIM(E40))="UNITED KINGDOM"),"United Kingdom",IF(OR(UPPER(TRIM(E40))="UAE",UPPER(TRIM(E40))="U.A.E.",UPPER(TRIM(E40))="UNITED ARAB EMIRATES"),"United Arab Emirates",IF(OR(UPPER(TRIM(E40))="SG",UPPER(TRIM(E40))="SINGAPORE"),"Singapore",TRIM(E40))))))))) -> United Arab Emirates | G40: Laptop Stand | H40: Accessories | I40: 5 | J40: 38 | K40: 17 | L40: 0.15 | M40: PayPal | N40: PayPal | O40: Completed | P40: =PROPER(TRIM(O40)) -> Completed | Q40: =IF(TRIM(R40)="","Missing",IF(AND(ISNUMBER(SEARCH("@",R40)),ISNUMBER(SEARCH(".",R40,SEARCH("@",R40)+2))),"Valid","Invalid")) -> Valid | R40: benjamin.walker@example.com | S40: =I40*J40*(1-L40) -> 161.5 | T40: =I40*K40 -> 85 | U40: =S40-T40 -> 76.5 | V40: =IF(S40=0,0,U40/S40) -> 0.47368421
A41: ORD-10272 | B41: 45696 | C41: Ethan Anderson | D41: =PROPER(TRIM(C41)) -> Ethan Anderson | E41: germany | F41: =IF(OR(UPPER(TRIM(E41))="AUS",UPPER(TRIM(E41))="AUSTRALIA"),"Australia",IF(OR(UPPER(TRIM(E41))="CAN",UPPER(TRIM(E41))="CANADA"),"Canada",IF(OR(UPPER(TRIM(E41))="DE",UPPER(TRIM(E41))="GERMANY"),"Germany",IF(OR(UPPER(TRIM(E41))="IN",UPPER(TRIM(E41))="INDIA"),"India",IF(OR(UPPER(TRIM(E41))="US",UPPER(TRIM(E41))="USA",UPPER(TRIM(E41))="UNITED STATES"),"United States",IF(OR(UPPER(TRIM(E41))="UK",UPPER(TRIM(E41))="U.K.",UPPER(TRIM(E41))="UNITED KINGDOM"),"United Kingdom",IF(OR(UPPER(TRIM(E41))="UAE",UPPER(TRIM(E41))="U.A.E.",UPPER(TRIM(E41))="UNITED ARAB EMIRATES"),"United Arab Emirates",IF(OR(UPPER(TRIM(E41))="SG",UPPER(TRIM(E41))="SINGAPORE"),"Singapore",TRIM(E41))))))))) -> Germany | G41: Monitor 27-inch | H41: Electronics | I41: 1 | J41: 245 | K41: 150 | L41: 0.05 | M41: Bank Transfer | N41: =PROPER(TRIM(M41)) -> Bank Transfer | O41: Cancelled | P41: =PROPER(TRIM(O41)) -> Cancelled | Q41: =IF(TRIM(R41)="","Missing",IF(AND(ISNUMBER(SEARCH("@",R41)),ISNUMBER(SEARCH(".",R41,SEARCH("@",R41)+2))),"Valid","Invalid")) -> Valid | R41: ethan.anderson@example.com | S41: =I41*J41*(1-L41) -> 232.75 | T41: =I41*K41 -> 150 | U41: =S41-T41 -> 82.75 | V41: =IF(S41=0,0,U41/S41) -> 0.35553169
A42: ORD-10535 | B42: 45998 | C42: Ava Thomas | D42: =PROPER(TRIM(C42)) -> Ava Thomas | E42: India | F42: =IF(OR(UPPER(TRIM(E42))="AUS",UPPER(TRIM(E42))="AUSTRALIA"),"Australia",IF(OR(UPPER(TRIM(E42))="CAN",UPPER(TRIM(E42))="CANADA"),"Canada",IF(OR(UPPER(TRIM(E42))="DE",UPPER(TRIM(E42))="GERMANY"),"Germany",IF(OR(UPPER(TRIM(E42))="IN",UPPER(TRIM(E42))="INDIA"),"India",IF(OR(UPPER(TRIM(E42))="US",UPPER(TRIM(E42))="USA",UPPER(TRIM(E42))="UNITED STATES"),"United States",IF(OR(UPPER(TRIM(E42))="UK",UPPER(TRIM(E42))="U.K.",UPPER(TRIM(E42))="UNITED KINGDOM"),"United Kingdom",IF(OR(UPPER(TRIM(E42))="UAE",UPPER(TRIM(E42))="U.A.E.",UPPER(TRIM(E42))="UNITED ARAB EMIRATES"),"United Arab Emirates",IF(OR(UPPER(TRIM(E42))="SG",UPPER(TRIM(E42))="SINGAPORE"),"Singapore",TRIM(E42))))))))) -> India | G42: Headphones | H42: Electronics | I42: 4 | J42: 85 | K42: 44 | L42: 0 | M42: paypal | N42: PayPal | O42: Cancelled | P42: =PROPER(TRIM(O42)) -> Cancelled | Q42: =IF(TRIM(R42)="","Missing",IF(AND(ISNUMBER(SEARCH("@",R42)),ISNUMBER(SEARCH(".",R42,SEARCH("@",R42)+2))),"Valid","Invalid")) -> Valid | R42: ava.thomas@example.com | S42: =I42*J42*(1-L42) -> 340 | T42: =I42*K42 -> 176 | U42: =S42-T42 -> 164 | V42: =IF(S42=0,0,U42/S42) -> 0.48235294
A43: ORD-10164 | B43: 45973 | C43: James Thompson | D43: =PROPER(TRIM(C43)) -> James Thompson | E43: Singapore | F43: =IF(OR(UPPER(TRIM(E43))="AUS",UPPER(TRIM(E43))="AUSTRALIA"),"Australia",IF(OR(UPPER(TRIM(E43))="CAN",UPPER(TRIM(E43))="CANADA"),"Canada",IF(OR(UPPER(TRIM(E43))="DE",UPPER(TRIM(E43))="GERMANY"),"Germany",IF(OR(UPPER(TRIM(E43))="IN",UPPER(TRIM(E43))="INDIA"),"India",IF(OR(UPPER(TRIM(E43))="US",UPPER(TRIM(E43))="USA",UPPER(TRIM(E43))="UNITED STATES"),"United States",IF(OR(UPPER(TRIM(E43))="UK",UPPER(TRIM(E43))="U.K.",UPPER(TRIM(E43))="UNITED KINGDOM"),"United Kingdom",IF(OR(UPPER(TRIM(E43))="UAE",UPPER(TRIM(E43))="U.A.E.",UPPER(TRIM(E43))="UNITED ARAB EMIRATES"),"United Arab Emirates",IF(OR(UPPER(TRIM(E43))="SG",UPPER(TRIM(E43))="SINGAPORE"),"Singapore",TRIM(E43))))))))) -> Singapore | G43: Mechanical Keyboard | H43: Accessories | I43: 5 | J43: 65 | K43: 31 | L43: 0.15 | M43: paypal | N43: PayPal | O43: Cancelled | P43: =PROPER(TRIM(O43)) -> Cancelled | Q43: =IF(TRIM(R43)="","Missing",IF(AND(ISNUMBER(SEARCH("@",R43)),ISNUMBER(SEARCH(".",R43,SEARCH("@",R43)+2))),"Valid","Invalid")) -> Valid | R43: james.thompson@example.com | S43: =I43*J43*(1-L43) -> 276.25 | T43: =I43*K43 -> 155 | U43: =S43-T43 -> 121.25 | V43: =IF(S43=0,0,U43/S43) -> 0.43891403
A44: ORD-10236 | B44: 45839 | C44: Olivia Davis | D44: =PROPER(TRIM(C44)) -> Olivia Davis | E44: Singapore | F44: =IF(OR(UPPER(TRIM(E44))="AUS",UPPER(TRIM(E44))="AUSTRALIA"),"Australia",IF(OR(UPPER(TRIM(E44))="CAN",UPPER(TRIM(E44))="CANADA"),"Canada",IF(OR(UPPER(TRIM(E44))="DE",UPPER(TRIM(E44))="GERMANY"),"Germany",IF(OR(UPPER(TRIM(E44))="IN",UPPER(TRIM(E44))="INDIA"),"India",IF(OR(UPPER(TRIM(E44))="US",UPPER(TRIM(E44))="USA",UPPER(TRIM(E44))="UNITED STATES"),"United States",IF(OR(UPPER(TRIM(E44))="UK",UPPER(TRIM(E44))="U.K.",UPPER(TRIM(E44))="UNITED KINGDOM"),"United Kingdom",IF(OR(UPPER(TRIM(E44))="UAE",UPPER(TRIM(E44))="U.A.E.",UPPER(TRIM(E44))="UNITED ARAB EMIRATES"),"United Arab Emirates",IF(OR(UPPER(TRIM(E44))="SG",UPPER(TRIM(E44))="SINGAPORE"),"Singapore",TRIM(E44))))))))) -> Singapore | G44: Monitor 24-inch | H44: Electronics | I44: 2 | J44: 175 | K44: 105 | L44: 0.15 | M44: Debit Card | N44: =PROPER(TRIM(M44)) -> Debit Card | O44: Pending | P44: =PROPER(TRIM(O44)) -> Pending | Q44: =IF(TRIM(R44)="","Missing",IF(AND(ISNUMBER(SEARCH("@",R44)),ISNUMBER(SEARCH(".",R44,SEARCH("@",R44)+2))),"Valid","Invalid")) -> Valid | R44: olivia.davis@example.com | S44: =I44*J44*(1-L44) -> 297.5 | T44: =I44*K44 -> 210 | U44: =S44-T44 -> 87.5 | V44: =IF(S44=0,0,U44/S44) -> 0.29411765
A45: ORD-10145 | B45: 45696 | C45: Benjamin Walker | D45: =PROPER(TRIM(C45)) -> Benjamin Walker | E45: united kingdom | F45: =IF(OR(UPPER(TRIM(E45))="AUS",UPPER(TRIM(E45))="AUSTRALIA"),"Australia",IF(OR(UPPER(TRIM(E45))="CAN",UPPER(TRIM(E45))="CANADA"),"Canada",IF(OR(UPPER(TRIM(E45))="DE",UPPER(TRIM(E45))="GERMANY"),"Germany",IF(OR(UPPER(TRIM(E45))="IN",UPPER(TRIM(E45))="INDIA"),"India",IF(OR(UPPER(TRIM(E45))="US",UPPER(TRIM(E45))="USA",UPPER(TRIM(E45))="UNITED STATES"),"United States",IF(OR(UPPER(TRIM(E45))="UK",UPPER(TRIM(E45))="U.K.",UPPER(TRIM(E45))="UNITED KINGDOM"),"United Kingdom",IF(OR(UPPER(TRIM(E45))="UAE",UPPER(TRIM(E45))="U.A.E.",UPPER(TRIM(E45))="UNITED ARAB EMIRATES"),"United Arab Emirates",IF(OR(UPPER(TRIM(E45))="SG",UPPER(TRIM(E45))="SINGAPORE"),"Singapore",TRIM(E45))))))))) -> United Kingdom | G45: External HDD 2TB | H45: Storage | I45: 2 | J45: 78 | K45: 45 | L45: 0.2 | M45: credit card | N45: =PROPER(TRIM(M45)) -> Credit Card | O45: Cancelled | P45: =PROPER(TRIM(O45)) -> Cancelled | Q45: =IF(TRIM(R45)="","Missing",IF(AND(ISNUMBER(SEARCH("@",R45)),ISNUMBER(SEARCH(".",R45,SEARCH("@",R45)+2))),"Valid","Invalid")) -> Valid | R45: benjamin.walker@example.com | S45: =I45*J45*(1-L45) -> 124.8 | T45: =I45*K45 -> 90 | U45: =S45-T45 -> 34.8 | V45: =IF(S45=0,0,U45/S45) -> 0.27884615
A46: ORD-10175 | B46: 45789 | C46: Emma Wilson | D46: =PROPER(TRIM(C46)) -> Emma Wilson | E46: DE | F46: =IF(OR(UPPER(TRIM(E46))="AUS",UPPER(TRIM(E46))="AUSTRALIA"),"Australia",IF(OR(UPPER(TRIM(E46))="CAN",UPPER(TRIM(E46))="CANADA"),"Canada",IF(OR(UPPER(TRIM(E46))="DE",UPPER(TRIM(E46))="GERMANY"),"Germany",IF(OR(UPPER(TRIM(E46))="IN",UPPER(TRIM(E46))="INDIA"),"India",IF(OR(UPPER(TRIM(E46))="US",UPPER(TRIM(E46))="USA",UPPER(TRIM(E46))="UNITED STATES"),"United States",IF(OR(UPPER(TRIM(E46))="UK",UPPER(TRIM(E46))="U.K.",UPPER(TRIM(E46))="UNITED KINGDOM"),"United Kingdom",IF(OR(UPPER(TRIM(E46))="UAE",UPPER(TRIM(E46))="U.A.E.",UPPER(TRIM(E46))="UNITED ARAB EMIRATES"),"United Arab Emirates",IF(OR(UPPER(TRIM(E46))="SG",UPPER(TRIM(E46))="SINGAPORE"),"Singapore",TRIM(E46))))))))) -> Germany | G46: Webcam | H46: Electronics | I46: 1 | J46: 59 | K46: 30 | L46: 0 | M46: Bank Transfer | N46: =PROPER(TRIM(M46)) -> Bank Transfer | O46: Pending | P46: =PROPER(TRIM(O46)) -> Pending | Q46: =IF(TRIM(R46)="","Missing",IF(AND(ISNUMBER(SEARCH("@",R46)),ISNUMBER(SEARCH(".",R46,SEARCH("@",R46)+2))),"Valid","Invalid")) -> Valid | R46: emma.wilson@example.com | S46: =I46*J46*(1-L46) -> 59 | T46: =I46*K46 -> 30 | U46: =S46-T46 -> 29 | V46: =IF(S46=0,0,U46/S46) -> 0.49152542
A47: ORD-10031 | B47: 45930 | C47: Mia White | D47: =PROPER(TRIM(C47)) -> Mia White | E47: united kingdom | F47: =IF(OR(UPPER(TRIM(E47))="AUS",UPPER(TRIM(E47))="AUSTRALIA"),"Australia",IF(OR(UPPER(TRIM(E47))="CAN",UPPER(TRIM(E47))="CANADA"),"Canada",IF(OR(UPPER(TRIM(E47))="DE",UPPER(TRIM(E47))="GERMANY"),"Germany",IF(OR(UPPER(TRIM(E47))="IN",UPPER(TRIM(E47))="INDIA"),"India",IF(OR(UPPER(TRIM(E47))="US",UPPER(TRIM(E47))="USA",UPPER(TRIM(E47))="UNITED STATES"),"United States",IF(OR(UPPER(TRIM(E47))="UK",UPPER(TRIM(E47))="U.K.",UPPER(TRIM(E47))="UNITED KINGDOM"),"United Kingdom",IF(OR(UPPER(TRIM(E47))="UAE",UPPER(TRIM(E47))="U.A.E.",UPPER(TRIM(E47))="UNITED ARAB EMIRATES"),"United Arab Emirates",IF(OR(UPPER(TRIM(E47))="SG",UPPER(TRIM(E47))="SINGAPORE"),"Singapore",TRIM(E47))))))))) -> United Kingdom | G47: Monitor 27-inch | H47: Electronics | I47: 2 | J47: 245 | K47: 150 | L47: 0 | M47: Credit Card | N47: =PROPER(TRIM(M47)) -> Credit Card | O47: Completed | P47: =PROPER(TRIM(O47)) -> Completed | Q47: =IF(TRIM(R47)="","Missing",IF(AND(ISNUMBER(SEARCH("@",R47)),ISNUMBER(SEARCH(".",R47,SEARCH("@",R47)+2))),"Valid","Invalid")) -> Valid | R47: mia.white@example.com | S47: =I47*J47*(1-L47) -> 490 | T47: =I47*K47 -> 300 | U47: =S47-T47 -> 190 | V47: =IF(S47=0,0,U47/S47) -> 0.3877551
A48: ORD-10400 | B48: 45926 | C48: Henry Clark | D48: =PROPER(TRIM(C48)) -> Henry Clark | E48: canada | F48: =IF(OR(UPPER(TRIM(E48))="AUS",UPPER(TRIM(E48))="AUSTRALIA"),"Australia",IF(OR(UPPER(TRIM(E48))="CAN",UPPER(TRIM(E48))="CANADA"),"Canada",IF(OR(UPPER(TRIM(E48))="DE",UPPER(TRIM(E48))="GERMANY"),"Germany",IF(OR(UPPER(TRIM(E48))="IN",UPPER(TRIM(E48))="INDIA"),"India",IF(OR(UPPER(TRIM(E48))="US",UPPER(TRIM(E48))="USA",UPPER(TRIM(E48))="UNITED STATES"),"United States",IF(OR(UPPER(TRIM(E48))="UK",UPPER(TRIM(E48))="U.K.",UPPER(TRIM(E48))="UNITED KINGDOM"),"United Kingdom",IF(OR(UPPER(TRIM(E48))="UAE",UPPER(TRIM(E48))="U.A.E.",UPPER(TRIM(E48))="UNITED ARAB EMIRATES"),"United Arab Emirates",IF(OR(UPPER(TRIM(E48))="SG",UPPER(TRIM(E48))="SINGAPORE"),"Singapore",TRIM(E48))))))))) -> Canada | G48: External HDD 2TB | H48: Storage | I48: 5 | J48: 78 | K48: 45 | L48: 0.05 | M48: Bank Transfer | N48: =PROPER(TRIM(M48)) -> Bank Transfer | O48: Completed | P48: =PROPER(TRIM(O48)) -> Completed | Q48: =IF(TRIM(R48)="","Missing",IF(AND(ISNUMBER(SEARCH("@",R48)),ISNUMBER(SEARCH(".",R48,SEARCH("@",R48)+2))),"Valid","Invalid")) -> Invalid | R48: henry.clark@example | S48: =I48*J48*(1-L48) -> 370.5 | T48: =I48*K48 -> 225 | U48: =S48-T48 -> 145.5 | V48: =IF(S48=0,0,U48/S48) -> 0.39271255
A49: ORD-10104 | B49: 45945 | C49: alex morgan | D49: =PROPER(TRIM(C49)) -> Alex Morgan | E49: United Kingdom | F49: =IF(OR(UPPER(TRIM(E49))="AUS",UPPER(TRIM(E49))="AUSTRALIA"),"Australia",IF(OR(UPPER(TRIM(E49))="CAN",UPPER(TRIM(E49))="CANADA"),"Canada",IF(OR(UPPER(TRIM(E49))="DE",UPPER(TRIM(E49))="GERMANY"),"Germany",IF(OR(UPPER(TRIM(E49))="IN",UPPER(TRIM(E49))="INDIA"),"India",IF(OR(UPPER(TRIM(E49))="US",UPPER(TRIM(E49))="USA",UPPER(TRIM(E49))="UNITED STATES"),"United States",IF(OR(UPPER(TRIM(E49))="UK",UPPER(TRIM(E49))="U.K.",UPPER(TRIM(E49))="UNITED KINGDOM"),"United Kingdom",IF(OR(UPPER(TRIM(E49))="UAE",UPPER(TRIM(E49))="U.A.E.",UPPER(TRIM(E49))="UNITED ARAB EMIRATES"),"United Arab Emirates",IF(OR(UPPER(TRIM(E49))="SG",UPPER(TRIM(E49))="SINGAPORE"),"Singapore",TRIM(E49))))))))) -> United Kingdom | G49: External HDD 2TB | H49: Storage | I49: 3 | J49: 78 | K49: 45 | L49: 0.1 | M49: credit card | N49: =PROPER(TRIM(M49)) -> Credit Card | O49: Completed | P49: =PROPER(TRIM(O49)) -> Completed | Q49: =IF(TRIM(R49)="","Missing",IF(AND(ISNUMBER(SEARCH("@",R49)),ISNUMBER(SEARCH(".",R49,SEARCH("@",R49)+2))),"Valid","Invalid")) -> Valid | R49: alex.morgan@example.com | S49: =I49*J49*(1-L49) -> 210.6 | T49: =I49*K49 -> 135 | U49: =S49-T49 -> 75.6 | V49: =IF(S49=0,0,U49/S49) -> 0.35897436
A50: ORD-10435 | B50: 45841 | C50: Noah Brown | D50: =PROPER(TRIM(C50)) -> Noah Brown | E50: AUS | F50: =IF(OR(UPPER(TRIM(E50))="AUS",UPPER(TRIM(E50))="AUSTRALIA"),"Australia",IF(OR(UPPER(TRIM(E50))="CAN",UPPER(TRIM(E50))="CANADA"),"Canada",IF(OR(UPPER(TRIM(E50))="DE",UPPER(TRIM(E50))="GERMANY"),"Germany",IF(OR(UPPER(TRIM(E50))="IN",UPPER(TRIM(E50))="INDIA"),"India",IF(OR(UPPER(TRIM(E50))="US",UPPER(TRIM(E50))="USA",UPPER(TRIM(E50))="UNITED STATES"),"United States",IF(OR(UPPER(TRIM(E50))="UK",UPPER(TRIM(E50))="U.K.",UPPER(TRIM(E50))="UNITED KINGDOM"),"United Kingdom",IF(OR(UPPER(TRIM(E50))="UAE",UPPER(TRIM(E50))="U.A.E.",UPPER(TRIM(E50))="UNITED ARAB EMIRATES"),"United Arab Emirates",IF(OR(UPPER(TRIM(E50))="SG",UPPER(TRIM(E50))="SINGAPORE"),"Singapore",TRIM(E50))))))))) -> Australia | G50: SSD 1TB | H50: Storage | I50: 4 | J50: 92 | K50: 53 | L50: 0.2 | M50: Debit Card | N50: =PROPER(TRIM(M50)) -> Debit Card | O50: Completed | P50: =PROPER(TRIM(O50)) -> Completed | Q50: =IF(TRIM(R50)="","Missing",IF(AND(ISNUMBER(SEARCH("@",R50)),ISNUMBER(SEARCH(".",R50,SEARCH("@",R50)+2))),"Valid","Invalid")) -> Valid | R50: noah.brown@example.com | S50: =I50*J50*(1-L50) -> 294.4 | T50: =I50*K50 -> 212 | U50: =S50-T50 -> 82.4 | V50: =IF(S50=0,0,U50/S50) -> 0.2798913
A51: ORD-10262 | B51: 45821 | C51: Sophia Taylor | D51: =PROPER(TRIM(C51)) -> Sophia Taylor | E51: Canada | F51: =IF(OR(UPPER(TRIM(E51))="AUS",UPPER(TRIM(E51))="AUSTRALIA"),"Australia",IF(OR(UPPER(TRIM(E51))="CAN",UPPER(TRIM(E51))="CANADA"),"Canada",IF(OR(UPPER(TRIM(E51))="DE",UPPER(TRIM(E51))="GERMANY"),"Germany",IF(OR(UPPER(TRIM(E51))="IN",UPPER(TRIM(E51))="INDIA"),"India",IF(OR(UPPER(TRIM(E51))="US",UPPER(TRIM(E51))="USA",UPPER(TRIM(E51))="UNITED STATES"),"United States",IF(OR(UPPER(TRIM(E51))="UK",UPPER(TRIM(E51))="U.K.",UPPER(TRIM(E51))="UNITED KINGDOM"),"United Kingdom",IF(OR(UPPER(TRIM(E51))="UAE",UPPER(TRIM(E51))="U.A.E.",UPPER(TRIM(E51))="UNITED ARAB EMIRATES"),"United Arab Emirates",IF(OR(UPPER(TRIM(E51))="SG",UPPER(TRIM(E51))="SINGAPORE"),"Singapore",TRIM(E51))))))))) -> Canada | G51: Desk Lamp | H51: Furniture | I51: 4 | J51: 36 | K51: 16 | L51: 0 | M51: paypal | N51: PayPal | O51: completed | P51: =PROPER(TRIM(O51)) -> Completed | Q51: =IF(TRIM(R51)="","Missing",IF(AND(ISNUMBER(SEARCH("@",R51)),ISNUMBER(SEARCH(".",R51,SEARCH("@",R51)+2))),"Valid","Invalid")) -> Valid | R51: sophia.taylor@example.com | S51: =I51*J51*(1-L51) -> 144 | T51: =I51*K51 -> 64 | U51: =S51-T51 -> 80 | V51: =IF(S51=0,0,U51/S51) -> 0.55555556
A52: ORD-10050 | B52: 45896 | C52: Daniel Harris | D52: =PROPER(TRIM(C52)) -> Daniel Harris | E52: uae | F52: =IF(OR(UPPER(TRIM(E52))="AUS",UPPER(TRIM(E52))="AUSTRALIA"),"Australia",IF(OR(UPPER(TRIM(E52))="CAN",UPPER(TRIM(E52))="CANADA"),"Canada",IF(OR(UPPER(TRIM(E52))="DE",UPPER(TRIM(E52))="GERMANY"),"Germany",IF(OR(UPPER(TRIM(E52))="IN",UPPER(TRIM(E52))="INDIA"),"India",IF(OR(UPPER(TRIM(E52))="US",UPPER(TRIM(E52))="USA",UPPER(TRIM(E52))="UNITED STATES"),"United States",IF(OR(UPPER(TRIM(E52))="UK",UPPER(TRIM(E52))="U.K.",UPPER(TRIM(E52))="UNITED KINGDOM"),"United Kingdom",IF(OR(UPPER(TRIM(E52))="UAE",UPPER(TRIM(E52))="U.A.E.",UPPER(TRIM(E52))="UNITED ARAB EMIRATES"),"United Arab Emirates",IF(OR(UPPER(TRIM(E52))="SG",UPPER(TRIM(E52))="SINGAPORE"),"Singapore",TRIM(E52))))))))) -> United Arab Emirates | G52: Monitor 24-inch | H52: Electronics | I52: 2 | J52: 175 | K52: 105 | L52: 0.05 | M52: Credit Card | N52: =PROPER(TRIM(M52)) -> Credit Card | O52: Shipped | P52: =PROPER(TRIM(O52)) -> Shipped | Q52: =IF(TRIM(R52)="","Missing",IF(AND(ISNUMBER(SEARCH("@",R52)),ISNUMBER(SEARCH(".",R52,SEARCH("@",R52)+2))),"Valid","Invalid")) -> Valid | R52: daniel.harris@example.com | S52: =I52*J52*(1-L52) -> 332.5 | T52: =I52*K52 -> 210 | U52: =S52-T52 -> 122.5 | V52: =IF(S52=0,0,U52/S52) -> 0.36842105
A53: ORD-10112 | B53: 45691 | C53: Mia White | D53: =PROPER(TRIM(C53)) -> Mia White | E53: CAN | F53: =IF(OR(UPPER(TRIM(E53))="AUS",UPPER(TRIM(E53))="AUSTRALIA"),"Australia",IF(OR(UPPER(TRIM(E53))="CAN",UPPER(TRIM(E53))="CANADA"),"Canada",IF(OR(UPPER(TRIM(E53))="DE",UPPER(TRIM(E53))="GERMANY"),"Germany",IF(OR(UPPER(TRIM(E53))="IN",UPPER(TRIM(E53))="INDIA"),"India",IF(OR(UPPER(TRIM(E53))="US",UPPER(TRIM(E53))="USA",UPPER(TRIM(E53))="UNITED STATES"),"United States",IF(OR(UPPER(TRIM(E53))="UK",UPPER(TRIM(E53))="U.K.",UPPER(TRIM(E53))="UNITED KINGDOM"),"United Kingdom",IF(OR(UPPER(TRIM(E53))="UAE",UPPER(TRIM(E53))="U.A.E.",UPPER(TRIM(E53))="UNITED ARAB EMIRATES"),"United Arab Emirates",IF(OR(UPPER(TRIM(E53))="SG",UPPER(TRIM(E53))="SINGAPORE"),"Singapore",TRIM(E53))))))))) -> Canada | G53: Webcam | H53: Electronics | I53: 2 | J53: 59 | K53: 30 | L53: 0.05 | M53: credit card | N53: =PROPER(TRIM(M53)) -> Credit Card | O53: Completed | P53: =PROPER(TRIM(O53)) -> Completed | Q53: =IF(TRIM(R53)="","Missing",IF(AND(ISNUMBER(SEARCH("@",R53)),ISNUMBER(SEARCH(".",R53,SEARCH("@",R53)+2))),"Valid","Invalid")) -> Valid | R53: mia.white@example.com | S53: =I53*J53*(1-L53) -> 112.1 | T53: =I53*K53 -> 60 | U53: =S53-T53 -> 52.1 | V53: =IF(S53=0,0,U53/S53) -> 0.4647636
A54: ORD-10467 | B54: 45885 | C54: Liam Miller | D54: =PROPER(TRIM(C54)) -> Liam Miller | E54: DE | F54: =IF(OR(UPPER(TRIM(E54))="AUS",UPPER(TRIM(E54))="AUSTRALIA"),"Australia",IF(OR(UPPER(TRIM(E54))="CAN",UPPER(TRIM(E54))="CANADA"),"Canada",IF(OR(UPPER(TRIM(E54))="DE",UPPER(TRIM(E54))="GERMANY"),"Germany",IF(OR(UPPER(TRIM(E54))="IN",UPPER(TRIM(E54))="INDIA"),"India",IF(OR(UPPER(TRIM(E54))="US",UPPER(TRIM(E54))="USA",UPPER(TRIM(E54))="UNITED STATES"),"United States",IF(OR(UPPER(TRIM(E54))="UK",UPPER(TRIM(E54))="U.K.",UPPER(TRIM(E54))="UNITED KINGDOM"),"United Kingdom",IF(OR(UPPER(TRIM(E54))="UAE",UPPER(TRIM(E54))="U.A.E.",UPPER(TRIM(E54))="UNITED ARAB EMIRATES"),"United Arab Emirates",IF(OR(UPPER(TRIM(E54))="SG",UPPER(TRIM(E54))="SINGAPORE"),"Singapore",TRIM(E54))))))))) -> Germany | G54: Desk Lamp | H54: Furniture | I54: 2 | J54: 36 | K54: 16 | L54: 0.1 | M54: Debit Card | N54: =PROPER(TRIM(M54)) -> Debit Card | O54: Pending | P54: =PROPER(TRIM(O54)) -> Pending | Q54: =IF(TRIM(R54)="","Missing",IF(AND(ISNUMBER(SEARCH("@",R54)),ISNUMBER(SEARCH(".",R54,SEARCH("@",R54)+2))),"Valid","Invalid")) -> Valid | R54: liam.miller@example.com | S54: =I54*J54*(1-L54) -> 64.8 | T54: =I54*K54 -> 32 | U54: =S54-T54 -> 32.8 | V54: =IF(S54=0,0,U54/S54) -> 0.50617284
A55: ORD-10137 | B55: 45919 | C55: James Thompson | D55: =PROPER(TRIM(C55)) -> James Thompson | E55: india | F55: =IF(OR(UPPER(TRIM(E55))="AUS",UPPER(TRIM(E55))="AUSTRALIA"),"Australia",IF(OR(UPPER(TRIM(E55))="CAN",UPPER(TRIM(E55))="CANADA"),"Canada",IF(OR(UPPER(TRIM(E55))="DE",UPPER(TRIM(E55))="GERMANY"),"Germany",IF(OR(UPPER(TRIM(E55))="IN",UPPER(TRIM(E55))="INDIA"),"India",IF(OR(UPPER(TRIM(E55))="US",UPPER(TRIM(E55))="USA",UPPER(TRIM(E55))="UNITED STATES"),"United States",IF(OR(UPPER(TRIM(E55))="UK",UPPER(TRIM(E55))="U.K.",UPPER(TRIM(E55))="UNITED KINGDOM"),"United Kingdom",IF(OR(UPPER(TRIM(E55))="UAE",UPPER(TRIM(E55))="U.A.E.",UPPER(TRIM(E55))="UNITED ARAB EMIRATES"),"United Arab Emirates",IF(OR(UPPER(TRIM(E55))="SG",UPPER(TRIM(E55))="SINGAPORE"),"Singapore",TRIM(E55))))))))) -> India | G55: USB-C Hub | H55: Accessories | I55: 2 | J55: 42 | K55: 21 | L55: 0.05 | M55: Debit Card | N55: =PROPER(TRIM(M55)) -> Debit Card | O55: Completed | P55: =PROPER(TRIM(O55)) -> Completed | Q55: =IF(TRIM(R55)="","Missing",IF(AND(ISNUMBER(SEARCH("@",R55)),ISNUMBER(SEARCH(".",R55,SEARCH("@",R55)+2))),"Valid","Invalid")) -> Valid | R55: james.thompson@example.com | S55: =I55*J55*(1-L55) -> 79.8 | T55: =I55*K55 -> 42 | U55: =S55-T55 -> 37.8 | V55: =IF(S55=0,0,U55/S55) -> 0.47368421
A56: ORD-10283 | B56: 45688 | C56: Ella Martin | D56: =PROPER(TRIM(C56)) -> Ella Martin | E56: India | F56: =IF(OR(UPPER(TRIM(E56))="AUS",UPPER(TRIM(E56))="AUSTRALIA"),"Australia",IF(OR(UPPER(TRIM(E56))="CAN",UPPER(TRIM(E56))="CANADA"),"Canada",IF(OR(UPPER(TRIM(E56))="DE",UPPER(TRIM(E56))="GERMANY"),"Germany",IF(OR(UPPER(TRIM(E56))="IN",UPPER(TRIM(E56))="INDIA"),"India",IF(OR(UPPER(TRIM(E56))="US",UPPER(TRIM(E56))="USA",UPPER(TRIM(E56))="UNITED STATES"),"United States",IF(OR(UPPER(TRIM(E56))="UK",UPPER(TRIM(E56))="U.K.",UPPER(TRIM(E56))="UNITED KINGDOM"),"United Kingdom",IF(OR(UPPER(TRIM(E56))="UAE",UPPER(TRIM(E56))="U.A.E.",UPPER(TRIM(E56))="UNITED ARAB EMIRATES"),"United Arab Emirates",IF(OR(UPPER(TRIM(E56))="SG",UPPER(TRIM(E56))="SINGAPORE"),"Singapore",TRIM(E56))))))))) -> India | G56: Webcam | H56: Electronics | I56: 2 | J56: 59 | K56: 30 | L56: 0.15 | M56: Credit Card | N56: =PROPER(TRIM(M56)) -> Credit Card | O56: Shipped | P56: =PROPER(TRIM(O56)) -> Shipped | Q56: =IF(TRIM(R56)="","Missing",IF(AND(ISNUMBER(SEARCH("@",R56)),ISNUMBER(SEARCH(".",R56,SEARCH("@",R56)+2))),"Valid","Invalid")) -> Valid | R56: ella.martin@example.com | S56: =I56*J56*(1-L56) -> 100.3 | T56: =I56*K56 -> 60 | U56: =S56-T56 -> 40.3 | V56: =IF(S56=0,0,U56/S56) -> 0.40179462
A57: ORD-10516 | B57: 45700 | C57: Lily Hall | D57: =PROPER(TRIM(C57)) -> Lily Hall | E57: singapore | F57: =IF(OR(UPPER(TRIM(E57))="AUS",UPPER(TRIM(E57))="AUSTRALIA"),"Australia",IF(OR(UPPER(TRIM(E57))="CAN",UPPER(TRIM(E57))="CANADA"),"Canada",IF(OR(UPPER(TRIM(E57))="DE",UPPER(TRIM(E57))="GERMANY"),"Germany",IF(OR(UPPER(TRIM(E57))="IN",UPPER(TRIM(E57))="INDIA"),"India",IF(OR(UPPER(TRIM(E57))="US",UPPER(TRIM(E57))="USA",UPPER(TRIM(E57))="UNITED STATES"),"United States",IF(OR(UPPER(TRIM(E57))="UK",UPPER(TRIM(E57))="U.K.",UPPER(TRIM(E57))="UNITED KINGDOM"),"United Kingdom",IF(OR(UPPER(TRIM(E57))="UAE",UPPER(TRIM(E57))="U.A.E.",UPPER(TRIM(E57))="UNITED ARAB EMIRATES"),"United Arab Emirates",IF(OR(UPPER(TRIM(E57))="SG",UPPER(TRIM(E57))="SINGAPORE"),"Singapore",TRIM(E57))))))))) -> Singapore | G57: Headphones | H57: Electronics | I57: 5 | J57: 85 | K57: 44 | L57: 0.15 | M57: Debit Card | N57: =PROPER(TRIM(M57)) -> Debit Card | O57: Pending | P57: =PROPER(TRIM(O57)) -> Pending | Q57: =IF(TRIM(R57)="","Missing",IF(AND(ISNUMBER(SEARCH("@",R57)),ISNUMBER(SEARCH(".",R57,SEARCH("@",R57)+2))),"Valid","Invalid")) -> Valid | R57: lily.hall@example.com | S57: =I57*J57*(1-L57) -> 361.25 | T57: =I57*K57 -> 220 | U57: =S57-T57 -> 141.25 | V57: =IF(S57=0,0,U57/S57) -> 0.39100346
A58: ORD-10349 | B58: 45735 | C58: Daniel Harris | D58: =PROPER(TRIM(C58)) -> Daniel Harris | E58: India | F58: =IF(OR(UPPER(TRIM(E58))="AUS",UPPER(TRIM(E58))="AUSTRALIA"),"Australia",IF(OR(UPPER(TRIM(E58))="CAN",UPPER(TRIM(E58))="CANADA"),"Canada",IF(OR(UPPER(TRIM(E58))="DE",UPPER(TRIM(E58))="GERMANY"),"Germany",IF(OR(UPPER(TRIM(E58))="IN",UPPER(TRIM(E58))="INDIA"),"India",IF(OR(UPPER(TRIM(E58))="US",UPPER(TRIM(E58))="USA",UPPER(TRIM(E58))="UNITED STATES"),"United States",IF(OR(UPPER(TRIM(E58))="UK",UPPER(TRIM(E58))="U.K.",UPPER(TRIM(E58))="UNITED KINGDOM"),"United Kingdom",IF(OR(UPPER(TRIM(E58))="UAE",UPPER(TRIM(E58))="U.A.E.",UPPER(TRIM(E58))="UNITED ARAB EMIRATES"),"United Arab Emirates",IF(OR(UPPER(TRIM(E58))="SG",UPPER(TRIM(E58))="SINGAPORE"),"Singapore",TRIM(E58))))))))) -> India | G58: Laptop Stand | H58: Accessories | I58: 4 | J58: 38 | K58: 17 | L58: 0.05 | M58: Credit Card | N58: =PROPER(TRIM(M58)) -> Credit Card | O58: Completed | P58: =PROPER(TRIM(O58)) -> Completed | Q58: =IF(TRIM(R58)="","Missing",IF(AND(ISNUMBER(SEARCH("@",R58)),ISNUMBER(SEARCH(".",R58,SEARCH("@",R58)+2))),"Valid","Invalid")) -> Valid | R58: daniel.harris@example.com | S58: =I58*J58*(1-L58) -> 144.4 | T58: =I58*K58 -> 68 | U58: =S58-T58 -> 76.4 | V58: =IF(S58=0,0,U58/S58) -> 0.52908587
A59: ORD-10404 | B59: 45903 | C59: Ella Martin | D59: =PROPER(TRIM(C59)) -> Ella Martin | E59: Germany | F59: =IF(OR(UPPER(TRIM(E59))="AUS",UPPER(TRIM(E59))="AUSTRALIA"),"Australia",IF(OR(UPPER(TRIM(E59))="CAN",UPPER(TRIM(E59))="CANADA"),"Canada",IF(OR(UPPER(TRIM(E59))="DE",UPPER(TRIM(E59))="GERMANY"),"Germany",IF(OR(UPPER(TRIM(E59))="IN",UPPER(TRIM(E59))="INDIA"),"India",IF(OR(UPPER(TRIM(E59))="US",UPPER(TRIM(E59))="USA",UPPER(TRIM(E59))="UNITED STATES"),"United States",IF(OR(UPPER(TRIM(E59))="UK",UPPER(TRIM(E59))="U.K.",UPPER(TRIM(E59))="UNITED KINGDOM"),"United Kingdom",IF(OR(UPPER(TRIM(E59))="UAE",UPPER(TRIM(E59))="U.A.E.",UPPER(TRIM(E59))="UNITED ARAB EMIRATES"),"United Arab Emirates",IF(OR(UPPER(TRIM(E59))="SG",UPPER(TRIM(E59))="SINGAPORE"),"Singapore",TRIM(E59))))))))) -> Germany | G59: Desk Lamp | H59: Furniture | I59: 3 | J59: 36 | K59: 16 | L59: 0.05 | M59: PayPal | N59: PayPal | O59: Completed | P59: =PROPER(TRIM(O59)) -> Completed | Q59: =IF(TRIM(R59)="","Missing",IF(AND(ISNUMBER(SEARCH("@",R59)),ISNUMBER(SEARCH(".",R59,SEARCH("@",R59)+2))),"Valid","Invalid")) -> Valid | R59: ella.martin@example.com | S59: =I59*J59*(1-L59) -> 102.6 | T59: =I59*K59 -> 48 | U59: =S59-T59 -> 54.6 | V59: =IF(S59=0,0,U59/S59) -> 0.53216374
A60: ORD-10347 | B60: 45826 | C60: benjamin walker | D60: =PROPER(TRIM(C60)) -> Benjamin Walker | E60: UK | F60: =IF(OR(UPPER(TRIM(E60))="AUS",UPPER(TRIM(E60))="AUSTRALIA"),"Australia",IF(OR(UPPER(TRIM(E60))="CAN",UPPER(TRIM(E60))="CANADA"),"Canada",IF(OR(UPPER(TRIM(E60))="DE",UPPER(TRIM(E60))="GERMANY"),"Germany",IF(OR(UPPER(TRIM(E60))="IN",UPPER(TRIM(E60))="INDIA"),"India",IF(OR(UPPER(TRIM(E60))="US",UPPER(TRIM(E60))="USA",UPPER(TRIM(E60))="UNITED STATES"),"United States",IF(OR(UPPER(TRIM(E60))="UK",UPPER(TRIM(E60))="U.K.",UPPER(TRIM(E60))="UNITED KINGDOM"),"United Kingdom",IF(OR(UPPER(TRIM(E60))="UAE",UPPER(TRIM(E60))="U.A.E.",UPPER(TRIM(E60))="UNITED ARAB EMIRATES"),"United Arab Emirates",IF(OR(UPPER(TRIM(E60))="SG",UPPER(TRIM(E60))="SINGAPORE"),"Singapore",TRIM(E60))))))))) -> United Kingdom | G60: Monitor 24-inch | H60: Electronics | I60: 5 | J60: 175 | K60: 105 | L60: 0.15 | M60: Credit Card | N60: =PROPER(TRIM(M60)) -> Credit Card | O60: Cancelled | P60: =PROPER(TRIM(O60)) -> Cancelled | Q60: =IF(TRIM(R60)="","Missing",IF(AND(ISNUMBER(SEARCH("@",R60)),ISNUMBER(SEARCH(".",R60,SEARCH("@",R60)+2))),"Valid","Invalid")) -> Valid | R60: benjamin.walker@example.com | S60: =I60*J60*(1-L60) -> 743.75 | T60: =I60*K60 -> 525 | U60: =S60-T60 -> 218.75 | V60: =IF(S60=0,0,U60/S60) -> 0.29411765
A61: ORD-10167 | B61: 45861 | C61: Daniel Harris | D61: =PROPER(TRIM(C61)) -> Daniel Harris | E61: australia | F61: =IF(OR(UPPER(TRIM(E61))="AUS",UPPER(TRIM(E61))="AUSTRALIA"),"Australia",IF(OR(UPPER(TRIM(E61))="CAN",UPPER(TRIM(E61))="CANADA"),"Canada",IF(OR(UPPER(TRIM(E61))="DE",UPPER(TRIM(E61))="GERMANY"),"Germany",IF(OR(UPPER(TRIM(E61))="IN",UPPER(TRIM(E61))="INDIA"),"India",IF(OR(UPPER(TRIM(E61))="US",UPPER(TRIM(E61))="USA",UPPER(TRIM(E61))="UNITED STATES"),"United States",IF(OR(UPPER(TRIM(E61))="UK",UPPER(TRIM(E61))="U.K.",UPPER(TRIM(E61))="UNITED KINGDOM"),"United Kingdom",IF(OR(UPPER(TRIM(E61))="UAE",UPPER(TRIM(E61))="U.A.E.",UPPER(TRIM(E61))="UNITED ARAB EMIRATES"),"United Arab Emirates",IF(OR(UPPER(TRIM(E61))="SG",UPPER(TRIM(E61))="SINGAPORE"),"Singapore",TRIM(E61))))))))) -> Australia | G61: Webcam | H61: Electronics | I61: 3 | J61: 59 | K61: 30 | L61: 0.15 | M61: Credit Card | N61: =PROPER(TRIM(M61)) -> Credit Card | O61: Cancelled | P61: =PROPER(TRIM(O61)) -> Cancelled | Q61: =IF(TRIM(R61)="","Missing",IF(AND(ISNUMBER(SEARCH("@",R61)),ISNUMBER(SEARCH(".",R61,SEARCH("@",R61)+2))),"Valid","Invalid")) -> Valid | R61: daniel.harris@example.com | S61: =I61*J61*(1-L61) -> 150.45 | T61: =I61*K61 -> 90 | U61: =S61-T61 -> 60.45 | V61: =IF(S61=0,0,U61/S61) -> 0.40179462
A62: ORD-10277 | B62: 45685 | C62: Lucas Jackson | D62: =PROPER(TRIM(C62)) -> Lucas Jackson | F62: Unknown | G62: Office Chair | H62: Furniture | I62: 2 | J62: 210 | K62: 125 | L62: 0.05 | M62: Debit Card | N62: =PROPER(TRIM(M62)) -> Debit Card | O62: Completed | P62: =PROPER(TRIM(O62)) -> Completed | Q62: =IF(TRIM(R62)="","Missing",IF(AND(ISNUMBER(SEARCH("@",R62)),ISNUMBER(SEARCH(".",R62,SEARCH("@",R62)+2))),"Valid","Invalid")) -> Valid | R62: lucas.jackson@example.com | S62: =I62*J62*(1-L62) -> 399 | T62: =I62*K62 -> 250 | U62: =S62-T62 -> 149 | V62: =IF(S62=0,0,U62/S62) -> 0.37343358
A63: ORD-10003 | B63: 45716 | C63: ella martin | D63: =PROPER(TRIM(C63)) -> Ella Martin | E63: australia | F63: =IF(OR(UPPER(TRIM(E63))="AUS",UPPER(TRIM(E63))="AUSTRALIA"),"Australia",IF(OR(UPPER(TRIM(E63))="CAN",UPPER(TRIM(E63))="CANADA"),"Canada",IF(OR(UPPER(TRIM(E63))="DE",UPPER(TRIM(E63))="GERMANY"),"Germany",IF(OR(UPPER(TRIM(E63))="IN",UPPER(TRIM(E63))="INDIA"),"India",IF(OR(UPPER(TRIM(E63))="US",UPPER(TRIM(E63))="USA",UPPER(TRIM(E63))="UNITED STATES"),"United States",IF(OR(UPPER(TRIM(E63))="UK",UPPER(TRIM(E63))="U.K.",UPPER(TRIM(E63))="UNITED KINGDOM"),"United Kingdom",IF(OR(UPPER(TRIM(E63))="UAE",UPPER(TRIM(E63))="U.A.E.",UPPER(TRIM(E63))="UNITED ARAB EMIRATES"),"United Arab Emirates",IF(OR(UPPER(TRIM(E63))="SG",UPPER(TRIM(E63))="SINGAPORE"),"Singapore",TRIM(E63))))))))) -> Australia | G63: Wireless Mouse | H63: Accessories | I63: 2 | J63: 18 | K63: 7 | L63: 0.05 | M63: Debit Card | N63: =PROPER(TRIM(M63)) -> Debit Card | O63: Completed | P63: =PROPER(TRIM(O63)) -> Completed | Q63: =IF(TRIM(R63)="","Missing",IF(AND(ISNUMBER(SEARCH("@",R63)),ISNUMBER(SEARCH(".",R63,SEARCH("@",R63)+2))),"Valid","Invalid")) -> Valid | R63: ella.martin@example.com | S63: =I63*J63*(1-L63) -> 34.2 | T63: =I63*K63 -> 14 | U63: =S63-T63 -> 20.2 | V63: =IF(S63=0,0,U63/S63) -> 0.59064327
A64: ORD-10103 | B64: 45789 | C64: Sophia Taylor | D64: =PROPER(TRIM(C64)) -> Sophia Taylor | E64: australia | F64: =IF(OR(UPPER(TRIM(E64))="AUS",UPPER(TRIM(E64))="AUSTRALIA"),"Australia",IF(OR(UPPER(TRIM(E64))="CAN",UPPER(TRIM(E64))="CANADA"),"Canada",IF(OR(UPPER(TRIM(E64))="DE",UPPER(TRIM(E64))="GERMANY"),"Germany",IF(OR(UPPER(TRIM(E64))="IN",UPPER(TRIM(E64))="INDIA"),"India",IF(OR(UPPER(TRIM(E64))="US",UPPER(TRIM(E64))="USA",UPPER(TRIM(E64))="UNITED STATES"),"United States",IF(OR(UPPER(TRIM(E64))="UK",UPPER(TRIM(E64))="U.K.",UPPER(TRIM(E64))="UNITED KINGDOM"),"United Kingdom",IF(OR(UPPER(TRIM(E64))="UAE",UPPER(TRIM(E64))="U.A.E.",UPPER(TRIM(E64))="UNITED ARAB EMIRATES"),"United Arab Emirates",IF(OR(UPPER(TRIM(E64))="SG",UPPER(TRIM(E64))="SINGAPORE"),"Singapore",TRIM(E64))))))))) -> Australia | G64: Headphones | H64: Electronics | I64: 1 | J64: 85 | K64: 44 | L64: 0.05 | M64: credit card | N64: =PROPER(TRIM(M64)) -> Credit Card | O64: Completed | P64: =PROPER(TRIM(O64)) -> Completed | Q64: =IF(TRIM(R64)="","Missing",IF(AND(ISNUMBER(SEARCH("@",R64)),ISNUMBER(SEARCH(".",R64,SEARCH("@",R64)+2))),"Valid","Invalid")) -> Valid | R64: sophia.taylor@example.com | S64: =I64*J64*(1-L64) -> 80.75 | T64: =I64*K64 -> 44 | U64: =S64-T64 -> 36.75 | V64: =IF(S64=0,0,U64/S64) -> 0.45510836
A65: ORD-10248 | B65: 45729 | C65: Olivia Davis | D65: =PROPER(TRIM(C65)) -> Olivia Davis | E65: IN | F65: =IF(OR(UPPER(TRIM(E65))="AUS",UPPER(TRIM(E65))="AUSTRALIA"),"Australia",IF(OR(UPPER(TRIM(E65))="CAN",UPPER(TRIM(E65))="CANADA"),"Canada",IF(OR(UPPER(TRIM(E65))="DE",UPPER(TRIM(E65))="GERMANY"),"Germany",IF(OR(UPPER(TRIM(E65))="IN",UPPER(TRIM(E65))="INDIA"),"India",IF(OR(UPPER(TRIM(E65))="US",UPPER(TRIM(E65))="USA",UPPER(TRIM(E65))="UNITED STATES"),"United States",IF(OR(UPPER(TRIM(E65))="UK",UPPER(TRIM(E65))="U.K.",UPPER(TRIM(E65))="UNITED KINGDOM"),"United Kingdom",IF(OR(UPPER(TRIM(E65))="UAE",UPPER(TRIM(E65))="U.A.E.",UPPER(TRIM(E65))="UNITED ARAB EMIRATES"),"United Arab Emirates",IF(OR(UPPER(TRIM(E65))="SG",UPPER(TRIM(E65))="SINGAPORE"),"Singapore",TRIM(E65))))))))) -> India | G65: Monitor 27-inch | H65: Electronics | I65: 4 | J65: 245 | K65: 150 | L65: 0.1 | M65: paypal | N65: PayPal | O65: Completed | P65: =PROPER(TRIM(O65)) -> Completed | Q65: =IF(TRIM(R65)="","Missing",IF(AND(ISNUMBER(SEARCH("@",R65)),ISNUMBER(SEARCH(".",R65,SEARCH("@",R65)+2))),"Valid","Invalid")) -> Valid | R65: olivia.davis@example.com | S65: =I65*J65*(1-L65) -> 882 | T65: =I65*K65 -> 600 | U65: =S65-T65 -> 282 | V65: =IF(S65=0,0,U65/S65) -> 0.31972789
A66: ORD-10156 | B66: 45741 | C66: Lily Hall | D66: =PROPER(TRIM(C66)) -> Lily Hall | E66: U.K. | F66: =IF(OR(UPPER(TRIM(E66))="AUS",UPPER(TRIM(E66))="AUSTRALIA"),"Australia",IF(OR(UPPER(TRIM(E66))="CAN",UPPER(TRIM(E66))="CANADA"),"Canada",IF(OR(UPPER(TRIM(E66))="DE",UPPER(TRIM(E66))="GERMANY"),"Germany",IF(OR(UPPER(TRIM(E66))="IN",UPPER(TRIM(E66))="INDIA"),"India",IF(OR(UPPER(TRIM(E66))="US",UPPER(TRIM(E66))="USA",UPPER(TRIM(E66))="UNITED STATES"),"United States",IF(OR(UPPER(TRIM(E66))="UK",UPPER(TRIM(E66))="U.K.",UPPER(TRIM(E66))="UNITED KINGDOM"),"United Kingdom",IF(OR(UPPER(TRIM(E66))="UAE",UPPER(TRIM(E66))="U.A.E.",UPPER(TRIM(E66))="UNITED ARAB EMIRATES"),"United Arab Emirates",IF(OR(UPPER(TRIM(E66))="SG",UPPER(TRIM(E66))="SINGAPORE"),"Singapore",TRIM(E66))))))))) -> United Kingdom | G66: SSD 1TB | H66: Storage | I66: 4 | J66: 92 | K66: 53 | L66: 0.15 | M66: Bank Transfer | N66: =PROPER(TRIM(M66)) -> Bank Transfer | O66: Pending | P66: =PROPER(TRIM(O66)) -> Pending | Q66: =IF(TRIM(R66)="","Missing",IF(AND(ISNUMBER(SEARCH("@",R66)),ISNUMBER(SEARCH(".",R66,SEARCH("@",R66)+2))),"Valid","Invalid")) -> Valid | R66: lily.hall@example.com | S66: =I66*J66*(1-L66) -> 312.8 | T66: =I66*K66 -> 212 | U66: =S66-T66 -> 100.8 | V66: =IF(S66=0,0,U66/S66) -> 0.32225064
A67: ORD-10434 | B67: 45715 | C67: Benjamin Walker | D67: =PROPER(TRIM(C67)) -> Benjamin Walker | E67: Canada | F67: =IF(OR(UPPER(TRIM(E67))="AUS",UPPER(TRIM(E67))="AUSTRALIA"),"Australia",IF(OR(UPPER(TRIM(E67))="CAN",UPPER(TRIM(E67))="CANADA"),"Canada",IF(OR(UPPER(TRIM(E67))="DE",UPPER(TRIM(E67))="GERMANY"),"Germany",IF(OR(UPPER(TRIM(E67))="IN",UPPER(TRIM(E67))="INDIA"),"India",IF(OR(UPPER(TRIM(E67))="US",UPPER(TRIM(E67))="USA",UPPER(TRIM(E67))="UNITED STATES"),"United States",IF(OR(UPPER(TRIM(E67))="UK",UPPER(TRIM(E67))="U.K.",UPPER(TRIM(E67))="UNITED KINGDOM"),"United Kingdom",IF(OR(UPPER(TRIM(E67))="UAE",UPPER(TRIM(E67))="U.A.E.",UPPER(TRIM(E67))="UNITED ARAB EMIRATES"),"United Arab Emirates",IF(OR(UPPER(TRIM(E67))="SG",UPPER(TRIM(E67))="SINGAPORE"),"Singapore",TRIM(E67))))))))) -> Canada | G67: Webcam | H67: Electronics | I67: 4 | J67: 59 | K67: 30 | L67: 0.1 | M67: Debit Card | N67: =PROPER(TRIM(M67)) -> Debit Card | O67: Cancelled | P67: =PROPER(TRIM(O67)) -> Cancelled | Q67: =IF(TRIM(R67)="","Missing",IF(AND(ISNUMBER(SEARCH("@",R67)),ISNUMBER(SEARCH(".",R67,SEARCH("@",R67)+2))),"Valid","Invalid")) -> Valid | R67: benjamin.walker@example.com | S67: =I67*J67*(1-L67) -> 212.4 | T67: =I67*K67 -> 120 | U67: =S67-T67 -> 92.4 | V67: =IF(S67=0,0,U67/S67) -> 0.43502825
A68: ORD-10047 | B68: 45741 | C68: Benjamin Walker | D68: =PROPER(TRIM(C68)) -> Benjamin Walker | E68: US | F68: =IF(OR(UPPER(TRIM(E68))="AUS",UPPER(TRIM(E68))="AUSTRALIA"),"Australia",IF(OR(UPPER(TRIM(E68))="CAN",UPPER(TRIM(E68))="CANADA"),"Canada",IF(OR(UPPER(TRIM(E68))="DE",UPPER(TRIM(E68))="GERMANY"),"Germany",IF(OR(UPPER(TRIM(E68))="IN",UPPER(TRIM(E68))="INDIA"),"India",IF(OR(UPPER(TRIM(E68))="US",UPPER(TRIM(E68))="USA",UPPER(TRIM(E68))="UNITED STATES"),"United States",IF(OR(UPPER(TRIM(E68))="UK",UPPER(TRIM(E68))="U.K.",UPPER(TRIM(E68))="UNITED KINGDOM"),"United Kingdom",IF(OR(UPPER(TRIM(E68))="UAE",UPPER(TRIM(E68))="U.A.E.",UPPER(TRIM(E68))="UNITED ARAB EMIRATES"),"United Arab Emirates",IF(OR(UPPER(TRIM(E68))="SG",UPPER(TRIM(E68))="SINGAPORE"),"Singapore",TRIM(E68))))))))) -> United States | G68: Monitor 24-inch | H68: Electronics | I68: 3 | J68: 175 | K68: 105 | L68: 0 | M68: paypal | N68: PayPal | O68: Completed | P68: =PROPER(TRIM(O68)) -> Completed | Q68: =IF(TRIM(R68)="","Missing",IF(AND(ISNUMBER(SEARCH("@",R68)),ISNUMBER(SEARCH(".",R68,SEARCH("@",R68)+2))),"Valid","Invalid")) -> Valid | R68: benjamin.walker@example.com | S68: =I68*J68*(1-L68) -> 525 | T68: =I68*K68 -> 315 | U68: =S68-T68 -> 210 | V68: =IF(S68=0,0,U68/S68) -> 0.4
A69: ORD-10263 | B69: 45991 | C69: Noah Brown | D69: =PROPER(TRIM(C69)) -> Noah Brown | E69: AUS | F69: =IF(OR(UPPER(TRIM(E69))="AUS",UPPER(TRIM(E69))="AUSTRALIA"),"Australia",IF(OR(UPPER(TRIM(E69))="CAN",UPPER(TRIM(E69))="CANADA"),"Canada",IF(OR(UPPER(TRIM(E69))="DE",UPPER(TRIM(E69))="GERMANY"),"Germany",IF(OR(UPPER(TRIM(E69))="IN",UPPER(TRIM(E69))="INDIA"),"India",IF(OR(UPPER(TRIM(E69))="US",UPPER(TRIM(E69))="USA",UPPER(TRIM(E69))="UNITED STATES"),"United States",IF(OR(UPPER(TRIM(E69))="UK",UPPER(TRIM(E69))="U.K.",UPPER(TRIM(E69))="UNITED KINGDOM"),"United Kingdom",IF(OR(UPPER(TRIM(E69))="UAE",UPPER(TRIM(E69))="U.A.E.",UPPER(TRIM(E69))="UNITED ARAB EMIRATES"),"United Arab Emirates",IF(OR(UPPER(TRIM(E69))="SG",UPPER(TRIM(E69))="SINGAPORE"),"Singapore",TRIM(E69))))))))) -> Australia | G69: Monitor 27-inch | H69: Electronics | I69: 1 | J69: 245 | K69: 150 | L69: 0.1 | M69: Credit Card | N69: =PROPER(TRIM(M69)) -> Credit Card | O69: Pending | P69: =PROPER(TRIM(O69)) -> Pending | Q69: =IF(TRIM(R69)="","Missing",IF(AND(ISNUMBER(SEARCH("@",R69)),ISNUMBER(SEARCH(".",R69,SEARCH("@",R69)+2))),"Valid","Invalid")) -> Valid | R69: noah.brown@example.com | S69: =I69*J69*(1-L69) -> 220.5 | T69: =I69*K69 -> 150 | U69: =S69-T69 -> 70.5 | V69: =IF(S69=0,0,U69/S69) -> 0.31972789
A70: ORD-10133 | B70: 45725 | C70: henry clark | D70: =PROPER(TRIM(C70)) -> Henry Clark | E70: UAE | F70: =IF(OR(UPPER(TRIM(E70))="AUS",UPPER(TRIM(E70))="AUSTRALIA"),"Australia",IF(OR(UPPER(TRIM(E70))="CAN",UPPER(TRIM(E70))="CANADA"),"Canada",IF(OR(UPPER(TRIM(E70))="DE",UPPER(TRIM(E70))="GERMANY"),"Germany",IF(OR(UPPER(TRIM(E70))="IN",UPPER(TRIM(E70))="INDIA"),"India",IF(OR(UPPER(TRIM(E70))="US",UPPER(TRIM(E70))="USA",UPPER(TRIM(E70))="UNITED STATES"),"United States",IF(OR(UPPER(TRIM(E70))="UK",UPPER(TRIM(E70))="U.K.",UPPER(TRIM(E70))="UNITED KINGDOM"),"United Kingdom",IF(OR(UPPER(TRIM(E70))="UAE",UPPER(TRIM(E70))="U.A.E.",UPPER(TRIM(E70))="UNITED ARAB EMIRATES"),"United Arab Emirates",IF(OR(UPPER(TRIM(E70))="SG",UPPER(TRIM(E70))="SINGAPORE"),"Singapore",TRIM(E70))))))))) -> United Arab Emirates | G70: USB-C Hub | H70: Accessories | I70: 5 | J70: 42 | K70: 21 | L70: 0 | M70: credit card | N70: =PROPER(TRIM(M70)) -> Credit Card | O70: Pending | P70: =PROPER(TRIM(O70)) -> Pending | Q70: =IF(TRIM(R70)="","Missing",IF(AND(ISNUMBER(SEARCH("@",R70)),ISNUMBER(SEARCH(".",R70,SEARCH("@",R70)+2))),"Valid","Invalid")) -> Missing | S70: =I70*J70*(1-L70) -> 210 | T70: =I70*K70 -> 105 | U70: =S70-T70 -> 105 | V70: =IF(S70=0,0,U70/S70) -> 0.5
A71: ORD-10492 | B71: 45925 | C71: Chloe Lewis | D71: =PROPER(TRIM(C71)) -> Chloe Lewis | E71: canada | F71: =IF(OR(UPPER(TRIM(E71))="AUS",UPPER(TRIM(E71))="AUSTRALIA"),"Australia",IF(OR(UPPER(TRIM(E71))="CAN",UPPER(TRIM(E71))="CANADA"),"Canada",IF(OR(UPPER(TRIM(E71))="DE",UPPER(TRIM(E71))="GERMANY"),"Germany",IF(OR(UPPER(TRIM(E71))="IN",UPPER(TRIM(E71))="INDIA"),"India",IF(OR(UPPER(TRIM(E71))="US",UPPER(TRIM(E71))="USA",UPPER(TRIM(E71))="UNITED STATES"),"United States",IF(OR(UPPER(TRIM(E71))="UK",UPPER(TRIM(E71))="U.K.",UPPER(TRIM(E71))="UNITED KINGDOM"),"United Kingdom",IF(OR(UPPER(TRIM(E71))="UAE",UPPER(TRIM(E71))="U.A.E.",UPPER(TRIM(E71))="UNITED ARAB EMIRATES"),"United Arab Emirates",IF(OR(UPPER(TRIM(E71))="SG",UPPER(TRIM(E71))="SINGAPORE"),"Singapore",TRIM(E71))))))))) -> Canada | G71: Monitor 24-inch | H71: Electronics | I71: 5 | J71: 175 | K71: 105 | L71: 0.05 | M71: Bank Transfer | N71: =PROPER(TRIM(M71)) -> Bank Transfer | O71: Pending | P71: =PROPER(TRIM(O71)) -> Pending | Q71: =IF(TRIM(R71)="","Missing",IF(AND(ISNUMBER(SEARCH("@",R71)),ISNUMBER(SEARCH(".",R71,SEARCH("@",R71)+2))),"Valid","Invalid")) -> Valid | R71: chloe.lewis@example.com | S71: =I71*J71*(1-L71) -> 831.25 | T71: =I71*K71 -> 525 | U71: =S71-T71 -> 306.25 | V71: =IF(S71=0,0,U71/S71) -> 0.36842105
A72: ORD-10352 | B72: 45863 | C72: liam miller | D72: =PROPER(TRIM(C72)) -> Liam Miller | E72: australia | F72: =IF(OR(UPPER(TRIM(E72))="AUS",UPPER(TRIM(E72))="AUSTRALIA"),"Australia",IF(OR(UPPER(TRIM(E72))="CAN",UPPER(TRIM(E72))="CANADA"),"Canada",IF(OR(UPPER(TRIM(E72))="DE",UPPER(TRIM(E72))="GERMANY"),"Germany",IF(OR(UPPER(TRIM(E72))="IN",UPPER(TRIM(E72))="INDIA"),"India",IF(OR(UPPER(TRIM(E72))="US",UPPER(TRIM(E72))="USA",UPPER(TRIM(E72))="UNITED STATES"),"United States",IF(OR(UPPER(TRIM(E72))="UK",UPPER(TRIM(E72))="U.K.",UPPER(TRIM(E72))="UNITED KINGDOM"),"United Kingdom",IF(OR(UPPER(TRIM(E72))="UAE",UPPER(TRIM(E72))="U.A.E.",UPPER(TRIM(E72))="UNITED ARAB EMIRATES"),"United Arab Emirates",IF(OR(UPPER(TRIM(E72))="SG",UPPER(TRIM(E72))="SINGAPORE"),"Singapore",TRIM(E72))))))))) -> Australia | G72: Laptop Stand | H72: Accessories | I72: 2 | J72: 38 | K72: 17 | L72: 0.15 | M72: PayPal | N72: PayPal | O72: Completed | P72: =PROPER(TRIM(O72)) -> Completed | Q72: =IF(TRIM(R72)="","Missing",IF(AND(ISNUMBER(SEARCH("@",R72)),ISNUMBER(SEARCH(".",R72,SEARCH("@",R72)+2))),"Valid","Invalid")) -> Valid | R72: liam.miller@example.com | S72: =I72*J72*(1-L72) -> 64.6 | T72: =I72*K72 -> 34 | U72: =S72-T72 -> 30.6 | V72: =IF(S72=0,0,U72/S72) -> 0.47368421
A73: ORD-10142 | B73: 45853 | C73: Liam Miller | D73: =PROPER(TRIM(C73)) -> Liam Miller | E73: singapore | F73: =IF(OR(UPPER(TRIM(E73))="AUS",UPPER(TRIM(E73))="AUSTRALIA"),"Australia",IF(OR(UPPER(TRIM(E73))="CAN",UPPER(TRIM(E73))="CANADA"),"Canada",IF(OR(UPPER(TRIM(E73))="DE",UPPER(TRIM(E73))="GERMANY"),"Germany",IF(OR(UPPER(TRIM(E73))="IN",UPPER(TRIM(E73))="INDIA"),"India",IF(OR(UPPER(TRIM(E73))="US",UPPER(TRIM(E73))="USA",UPPER(TRIM(E73))="UNITED STATES"),"United States",IF(OR(UPPER(TRIM(E73))="UK",UPPER(TRIM(E73))="U.K.",UPPER(TRIM(E73))="UNITED KINGDOM"),"United Kingdom",IF(OR(UPPER(TRIM(E73))="UAE",UPPER(TRIM(E73))="U.A.E.",UPPER(TRIM(E73))="UNITED ARAB EMIRATES"),"United Arab Emirates",IF(OR(UPPER(TRIM(E73))="SG",UPPER(TRIM(E73))="SINGAPORE"),"Singapore",TRIM(E73))))))))) -> Singapore | G73: Mechanical Keyboard | H73: Accessories | I73: 4 | J73: 65 | K73: 31 | L73: 0.1 | M73: Debit Card | N73: =PROPER(TRIM(M73)) -> Debit Card | O73: Shipped | P73: =PROPER(TRIM(O73)) -> Shipped | Q73: =IF(TRIM(R73)="","Missing",IF(AND(ISNUMBER(SEARCH("@",R73)),ISNUMBER(SEARCH(".",R73,SEARCH("@",R73)+2))),"Valid","Invalid")) -> Valid | R73: liam.miller@example.com | S73: =I73*J73*(1-L73) -> 234 | T73: =I73*K73 -> 124 | U73: =S73-T73 -> 110 | V73: =IF(S73=0,0,U73/S73) -> 0.47008547
A74: ORD-10212 | B74: 45860 | C74: Ava Thomas | D74: =PROPER(TRIM(C74)) -> Ava Thomas | E74: United Kingdom | F74: =IF(OR(UPPER(TRIM(E74))="AUS",UPPER(TRIM(E74))="AUSTRALIA"),"Australia",IF(OR(UPPER(TRIM(E74))="CAN",UPPER(TRIM(E74))="CANADA"),"Canada",IF(OR(UPPER(TRIM(E74))="DE",UPPER(TRIM(E74))="GERMANY"),"Germany",IF(OR(UPPER(TRIM(E74))="IN",UPPER(TRIM(E74))="INDIA"),"India",IF(OR(UPPER(TRIM(E74))="US",UPPER(TRIM(E74))="USA",UPPER(TRIM(E74))="UNITED STATES"),"United States",IF(OR(UPPER(TRIM(E74))="UK",UPPER(TRIM(E74))="U.K.",UPPER(TRIM(E74))="UNITED KINGDOM"),"United Kingdom",IF(OR(UPPER(TRIM(E74))="UAE",UPPER(TRIM(E74))="U.A.E.",UPPER(TRIM(E74))="UNITED ARAB EMIRATES"),"United Arab Emirates",IF(OR(UPPER(TRIM(E74))="SG",UPPER(TRIM(E74))="SINGAPORE"),"Singapore",TRIM(E74))))))))) -> United Kingdom | G74: Wireless Mouse | H74: Accessories | I74: 2 | J74: 18 | K74: 7 | L74: 0 | M74: Bank Transfer | N74: =PROPER(TRIM(M74)) -> Bank Transfer | O74: Completed | P74: =PROPER(TRIM(O74)) -> Completed | Q74: =IF(TRIM(R74)="","Missing",IF(AND(ISNUMBER(SEARCH("@",R74)),ISNUMBER(SEARCH(".",R74,SEARCH("@",R74)+2))),"Valid","Invalid")) -> Valid | R74: ava.thomas@example.com | S74: =I74*J74*(1-L74) -> 36 | T74: =I74*K74 -> 14 | U74: =S74-T74 -> 22 | V74: =IF(S74=0,0,U74/S74) -> 0.61111111
A75: ORD-10114 | B75: 45967 | C75: grace moore | D75: =PROPER(TRIM(C75)) -> Grace Moore | E75: germany | F75: =IF(OR(UPPER(TRIM(E75))="AUS",UPPER(TRIM(E75))="AUSTRALIA"),"Australia",IF(OR(UPPER(TRIM(E75))="CAN",UPPER(TRIM(E75))="CANADA"),"Canada",IF(OR(UPPER(TRIM(E75))="DE",UPPER(TRIM(E75))="GERMANY"),"Germany",IF(OR(UPPER(TRIM(E75))="IN",UPPER(TRIM(E75))="INDIA"),"India",IF(OR(UPPER(TRIM(E75))="US",UPPER(TRIM(E75))="USA",UPPER(TRIM(E75))="UNITED STATES"),"United States",IF(OR(UPPER(TRIM(E75))="UK",UPPER(TRIM(E75))="U.K.",UPPER(TRIM(E75))="UNITED KINGDOM"),"United Kingdom",IF(OR(UPPER(TRIM(E75))="UAE",UPPER(TRIM(E75))="U.A.E.",UPPER(TRIM(E75))="UNITED ARAB EMIRATES"),"United Arab Emirates",IF(OR(UPPER(TRIM(E75))="SG",UPPER(TRIM(E75))="SINGAPORE"),"Singapore",TRIM(E75))))))))) -> Germany | G75: External HDD 2TB | H75: Storage | I75: 1 | J75: 78 | K75: 45 | L75: 0.05 | M75: Credit Card | N75: =PROPER(TRIM(M75)) -> Credit Card | O75: Completed | P75: =PROPER(TRIM(O75)) -> Completed | Q75: =IF(TRIM(R75)="","Missing",IF(AND(ISNUMBER(SEARCH("@",R75)),ISNUMBER(SEARCH(".",R75,SEARCH("@",R75)+2))),"Valid","Invalid")) -> Valid | R75: grace.moore@example.com | S75: =I75*J75*(1-L75) -> 74.1 | T75: =I75*K75 -> 45 | U75: =S75-T75 -> 29.1 | V75: =IF(S75=0,0,U75/S75) -> 0.39271255
A76: ORD-10018 | B76: 45787 | C76: Alex Morgan | D76: =PROPER(TRIM(C76)) -> Alex Morgan | E76: AUS | F76: =IF(OR(UPPER(TRIM(E76))="AUS",UPPER(TRIM(E76))="AUSTRALIA"),"Australia",IF(OR(UPPER(TRIM(E76))="CAN",UPPER(TRIM(E76))="CANADA"),"Canada",IF(OR(UPPER(TRIM(E76))="DE",UPPER(TRIM(E76))="GERMANY"),"Germany",IF(OR(UPPER(TRIM(E76))="IN",UPPER(TRIM(E76))="INDIA"),"India",IF(OR(UPPER(TRIM(E76))="US",UPPER(TRIM(E76))="USA",UPPER(TRIM(E76))="UNITED STATES"),"United States",IF(OR(UPPER(TRIM(E76))="UK",UPPER(TRIM(E76))="U.K.",UPPER(TRIM(E76))="UNITED KINGDOM"),"United Kingdom",IF(OR(UPPER(TRIM(E76))="UAE",UPPER(TRIM(E76))="U.A.E.",UPPER(TRIM(E76))="UNITED ARAB EMIRATES"),"United Arab Emirates",IF(OR(UPPER(TRIM(E76))="SG",UPPER(TRIM(E76))="SINGAPORE"),"Singapore",TRIM(E76))))))))) -> Australia | G76: Mechanical Keyboard | H76: Accessories | I76: 5 | J76: 65 | K76: 31 | L76: 0 | M76: Debit Card | N76: =PROPER(TRIM(M76)) -> Debit Card | O76: Cancelled | P76: =PROPER(TRIM(O76)) -> Cancelled | Q76: =IF(TRIM(R76)="","Missing",IF(AND(ISNUMBER(SEARCH("@",R76)),ISNUMBER(SEARCH(".",R76,SEARCH("@",R76)+2))),"Valid","Invalid")) -> Valid | R76: alex.morgan@example.com | S76: =I76*J76*(1-L76) -> 325 | T76: =I76*K76 -> 155 | U76: =S76-T76 -> 170 | V76: =IF(S76=0,0,U76/S76) -> 0.52307692
A77: ORD-10196 | B77: 45883 | C77: Ella Martin | D77: =PROPER(TRIM(C77)) -> Ella Martin | E77: singapore | F77: =IF(OR(UPPER(TRIM(E77))="AUS",UPPER(TRIM(E77))="AUSTRALIA"),"Australia",IF(OR(UPPER(TRIM(E77))="CAN",UPPER(TRIM(E77))="CANADA"),"Canada",IF(OR(UPPER(TRIM(E77))="DE",UPPER(TRIM(E77))="GERMANY"),"Germany",IF(OR(UPPER(TRIM(E77))="IN",UPPER(TRIM(E77))="INDIA"),"India",IF(OR(UPPER(TRIM(E77))="US",UPPER(TRIM(E77))="USA",UPPER(TRIM(E77))="UNITED STATES"),"United States",IF(OR(UPPER(TRIM(E77))="UK",UPPER(TRIM(E77))="U.K.",UPPER(TRIM(E77))="UNITED KINGDOM"),"United Kingdom",IF(OR(UPPER(TRIM(E77))="UAE",UPPER(TRIM(E77))="U.A.E.",UPPER(TRIM(E77))="UNITED ARAB EMIRATES"),"United Arab Emirates",IF(OR(UPPER(TRIM(E77))="SG",UPPER(TRIM(E77))="SINGAPORE"),"Singapore",TRIM(E77))))))))) -> Singapore | G77: Monitor 27-inch | H77: Electronics | I77: 1 | J77: 245 | K77: 150 | L77: 0.05 | M77: paypal | N77: PayPal | O77: Cancelled | P77: =PROPER(TRIM(O77)) -> Cancelled | Q77: =IF(TRIM(R77)="","Missing",IF(AND(ISNUMBER(SEARCH("@",R77)),ISNUMBER(SEARCH(".",R77,SEARCH("@",R77)+2))),"Valid","Invalid")) -> Valid | R77: ella.martin@example.com | S77: =I77*J77*(1-L77) -> 232.75 | T77: =I77*K77 -> 150 | U77: =S77-T77 -> 82.75 | V77: =IF(S77=0,0,U77/S77) -> 0.35553169
A78: ORD-10168 | B78: 45950 | C78: Lily Hall | D78: =PROPER(TRIM(C78)) -> Lily Hall | E78: australia | F78: =IF(OR(UPPER(TRIM(E78))="AUS",UPPER(TRIM(E78))="AUSTRALIA"),"Australia",IF(OR(UPPER(TRIM(E78))="CAN",UPPER(TRIM(E78))="CANADA"),"Canada",IF(OR(UPPER(TRIM(E78))="DE",UPPER(TRIM(E78))="GERMANY"),"Germany",IF(OR(UPPER(TRIM(E78))="IN",UPPER(TRIM(E78))="INDIA"),"India",IF(OR(UPPER(TRIM(E78))="US",UPPER(TRIM(E78))="USA",UPPER(TRIM(E78))="UNITED STATES"),"United States",IF(OR(UPPER(TRIM(E78))="UK",UPPER(TRIM(E78))="U.K.",UPPER(TRIM(E78))="UNITED KINGDOM"),"United Kingdom",IF(OR(UPPER(TRIM(E78))="UAE",UPPER(TRIM(E78))="U.A.E.",UPPER(TRIM(E78))="UNITED ARAB EMIRATES"),"United Arab Emirates",IF(OR(UPPER(TRIM(E78))="SG",UPPER(TRIM(E78))="SINGAPORE"),"Singapore",TRIM(E78))))))))) -> Australia | G78: Headphones | H78: Electronics | I78: 3 | J78: 85 | K78: 44 | L78: 0 | M78: PayPal | N78: PayPal | O78: Shipped | P78: =PROPER(TRIM(O78)) -> Shipped | Q78: =IF(TRIM(R78)="","Missing",IF(AND(ISNUMBER(SEARCH("@",R78)),ISNUMBER(SEARCH(".",R78,SEARCH("@",R78)+2))),"Valid","Invalid")) -> Invalid | R78: lily.hall@example | S78: =I78*J78*(1-L78) -> 255 | T78: =I78*K78 -> 132 | U78: =S78-T78 -> 123 | V78: =IF(S78=0,0,U78/S78) -> 0.48235294
A79: ORD-10307 | B79: 45814 | C79: Ella Martin | D79: =PROPER(TRIM(C79)) -> Ella Martin | E79: U.K. | F79: =IF(OR(UPPER(TRIM(E79))="AUS",UPPER(TRIM(E79))="AUSTRALIA"),"Australia",IF(OR(UPPER(TRIM(E79))="CAN",UPPER(TRIM(E79))="CANADA"),"Canada",IF(OR(UPPER(TRIM(E79))="DE",UPPER(TRIM(E79))="GERMANY"),"Germany",IF(OR(UPPER(TRIM(E79))="IN",UPPER(TRIM(E79))="INDIA"),"India",IF(OR(UPPER(TRIM(E79))="US",UPPER(TRIM(E79))="USA",UPPER(TRIM(E79))="UNITED STATES"),"United States",IF(OR(UPPER(TRIM(E79))="UK",UPPER(TRIM(E79))="U.K.",UPPER(TRIM(E79))="UNITED KINGDOM"),"United Kingdom",IF(OR(UPPER(TRIM(E79))="UAE",UPPER(TRIM(E79))="U.A.E.",UPPER(TRIM(E79))="UNITED ARAB EMIRATES"),"United Arab Emirates",IF(OR(UPPER(TRIM(E79))="SG",UPPER(TRIM(E79))="SINGAPORE"),"Singapore",TRIM(E79))))))))) -> United Kingdom | G79: Monitor 27-inch | H79: Electronics | I79: 1 | J79: 245 | K79: 150 | L79: 0 | M79: Bank Transfer | N79: =PROPER(TRIM(M79)) -> Bank Transfer | O79: Shipped | P79: =PROPER(TRIM(O79)) -> Shipped | Q79: =IF(TRIM(R79)="","Missing",IF(AND(ISNUMBER(SEARCH("@",R79)),ISNUMBER(SEARCH(".",R79,SEARCH("@",R79)+2))),"Valid","Invalid")) -> Valid | R79: ella.martin@example.com | S79: =I79*J79*(1-L79) -> 245 | T79: =I79*K79 -> 150 | U79: =S79-T79 -> 95 | V79: =IF(S79=0,0,U79/S79) -> 0.3877551
A80: ORD-10153 | B80: 45899 | C80: Mia White | D80: =PROPER(TRIM(C80)) -> Mia White | E80: United States | F80: =IF(OR(UPPER(TRIM(E80))="AUS",UPPER(TRIM(E80))="AUSTRALIA"),"Australia",IF(OR(UPPER(TRIM(E80))="CAN",UPPER(TRIM(E80))="CANADA"),"Canada",IF(OR(UPPER(TRIM(E80))="DE",UPPER(TRIM(E80))="GERMANY"),"Germany",IF(OR(UPPER(TRIM(E80))="IN",UPPER(TRIM(E80))="INDIA"),"India",IF(OR(UPPER(TRIM(E80))="US",UPPER(TRIM(E80))="USA",UPPER(TRIM(E80))="UNITED STATES"),"United States",IF(OR(UPPER(TRIM(E80))="UK",UPPER(TRIM(E80))="U.K.",UPPER(TRIM(E80))="UNITED KINGDOM"),"United Kingdom",IF(OR(UPPER(TRIM(E80))="UAE",UPPER(TRIM(E80))="U.A.E.",UPPER(TRIM(E80))="UNITED ARAB EMIRATES"),"United Arab Emirates",IF(OR(UPPER(TRIM(E80))="SG",UPPER(TRIM(E80))="SINGAPORE"),"Singapore",TRIM(E80))))))))) -> United States | G80: Desk Lamp | H80: Furniture | I80: 4 | J80: 36 | K80: 16 | L80: 0.1 | M80: Credit Card | N80: =PROPER(TRIM(M80)) -> Credit Card | O80: Shipped | P80: =PROPER(TRIM(O80)) -> Shipped | Q80: =IF(TRIM(R80)="","Missing",IF(AND(ISNUMBER(SEARCH("@",R80)),ISNUMBER(SEARCH(".",R80,SEARCH("@",R80)+2))),"Valid","Invalid")) -> Valid | R80: mia.white@example.com | S80: =I80*J80*(1-L80) -> 129.6 | T80: =I80*K80 -> 64 | U80: =S80-T80 -> 65.6 | V80: =IF(S80=0,0,U80/S80) -> 0.50617284
A81: ORD-10378 | B81: 45751 | C81: Sophia Taylor | D81: =PROPER(TRIM(C81)) -> Sophia Taylor | E81: Singapore | F81: =IF(OR(UPPER(TRIM(E81))="AUS",UPPER(TRIM(E81))="AUSTRALIA"),"Australia",IF(OR(UPPER(TRIM(E81))="CAN",UPPER(TRIM(E81))="CANADA"),"Canada",IF(OR(UPPER(TRIM(E81))="DE",UPPER(TRIM(E81))="GERMANY"),"Germany",IF(OR(UPPER(TRIM(E81))="IN",UPPER(TRIM(E81))="INDIA"),"India",IF(OR(UPPER(TRIM(E81))="US",UPPER(TRIM(E81))="USA",UPPER(TRIM(E81))="UNITED STATES"),"United States",IF(OR(UPPER(TRIM(E81))="UK",UPPER(TRIM(E81))="U.K.",UPPER(TRIM(E81))="UNITED KINGDOM"),"United Kingdom",IF(OR(UPPER(TRIM(E81))="UAE",UPPER(TRIM(E81))="U.A.E.",UPPER(TRIM(E81))="UNITED ARAB EMIRATES"),"United Arab Emirates",IF(OR(UPPER(TRIM(E81))="SG",UPPER(TRIM(E81))="SINGAPORE"),"Singapore",TRIM(E81))))))))) -> Singapore | G81: Wireless Mouse | H81: Accessories | I81: 5 | J81: 18 | K81: 7 | L81: 0.1 | M81: paypal | N81: PayPal | O81: pending | P81: =PROPER(TRIM(O81)) -> Pending | Q81: =IF(TRIM(R81)="","Missing",IF(AND(ISNUMBER(SEARCH("@",R81)),ISNUMBER(SEARCH(".",R81,SEARCH("@",R81)+2))),"Valid","Invalid")) -> Valid | R81: sophia.taylor@example.com | S81: =I81*J81*(1-L81) -> 81 | T81: =I81*K81 -> 35 | U81: =S81-T81 -> 46 | V81: =IF(S81=0,0,U81/S81) -> 0.56790123
A82: ORD-10532 | B82: 45803 | C82: Liam Miller | D82: =PROPER(TRIM(C82)) -> Liam Miller | E82: USA | F82: =IF(OR(UPPER(TRIM(E82))="AUS",UPPER(TRIM(E82))="AUSTRALIA"),"Australia",IF(OR(UPPER(TRIM(E82))="CAN",UPPER(TRIM(E82))="CANADA"),"Canada",IF(OR(UPPER(TRIM(E82))="DE",UPPER(TRIM(E82))="GERMANY"),"Germany",IF(OR(UPPER(TRIM(E82))="IN",UPPER(TRIM(E82))="INDIA"),"India",IF(OR(UPPER(TRIM(E82))="US",UPPER(TRIM(E82))="USA",UPPER(TRIM(E82))="UNITED STATES"),"United States",IF(OR(UPPER(TRIM(E82))="UK",UPPER(TRIM(E82))="U.K.",UPPER(TRIM(E82))="UNITED KINGDOM"),"United Kingdom",IF(OR(UPPER(TRIM(E82))="UAE",UPPER(TRIM(E82))="U.A.E.",UPPER(TRIM(E82))="UNITED ARAB EMIRATES"),"United Arab Emirates",IF(OR(UPPER(TRIM(E82))="SG",UPPER(TRIM(E82))="SINGAPORE"),"Singapore",TRIM(E82))))))))) -> United States | G82: USB-C Hub | H82: Accessories | I82: 4 | J82: 42 | K82: 21 | L82: 0.1 | M82: credit card | N82: =PROPER(TRIM(M82)) -> Credit Card | O82: Completed | P82: =PROPER(TRIM(O82)) -> Completed | Q82: =IF(TRIM(R82)="","Missing",IF(AND(ISNUMBER(SEARCH("@",R82)),ISNUMBER(SEARCH(".",R82,SEARCH("@",R82)+2))),"Valid","Invalid")) -> Valid | R82: liam.miller@example.com | S82: =I82*J82*(1-L82) -> 151.2 | T82: =I82*K82 -> 84 | U82: =S82-T82 -> 67.2 | V82: =IF(S82=0,0,U82/S82) -> 0.44444444
A83: ORD-10363 | B83: 45945 | C83: Grace Moore | D83: =PROPER(TRIM(C83)) -> Grace Moore | E83: UK | F83: =IF(OR(UPPER(TRIM(E83))="AUS",UPPER(TRIM(E83))="AUSTRALIA"),"Australia",IF(OR(UPPER(TRIM(E83))="CAN",UPPER(TRIM(E83))="CANADA"),"Canada",IF(OR(UPPER(TRIM(E83))="DE",UPPER(TRIM(E83))="GERMANY"),"Germany",IF(OR(UPPER(TRIM(E83))="IN",UPPER(TRIM(E83))="INDIA"),"India",IF(OR(UPPER(TRIM(E83))="US",UPPER(TRIM(E83))="USA",UPPER(TRIM(E83))="UNITED STATES"),"United States",IF(OR(UPPER(TRIM(E83))="UK",UPPER(TRIM(E83))="U.K.",UPPER(TRIM(E83))="UNITED KINGDOM"),"United Kingdom",IF(OR(UPPER(TRIM(E83))="UAE",UPPER(TRIM(E83))="U.A.E.",UPPER(TRIM(E83))="UNITED ARAB EMIRATES"),"United Arab Emirates",IF(OR(UPPER(TRIM(E83))="SG",UPPER(TRIM(E83))="SINGAPORE"),"Singapore",TRIM(E83))))))))) -> United Kingdom | G83: Wireless Mouse | H83: Accessories | I83: 4 | J83: 18 | K83: 7 | L83: 0.1 | N83: Unknown | O83: Pending | P83: =PROPER(TRIM(O83)) -> Pending | Q83: =IF(TRIM(R83)="","Missing",IF(AND(ISNUMBER(SEARCH("@",R83)),ISNUMBER(SEARCH(".",R83,SEARCH("@",R83)+2))),"Valid","Invalid")) -> Valid | R83: grace.moore@example.com | S83: =I83*J83*(1-L83) -> 64.8 | T83: =I83*K83 -> 28 | U83: =S83-T83 -> 36.8 | V83: =IF(S83=0,0,U83/S83) -> 0.56790123
A84: ORD-10119 | B84: 45960 | C84: Mia White | D84: =PROPER(TRIM(C84)) -> Mia White | E84: canada | F84: =IF(OR(UPPER(TRIM(E84))="AUS",UPPER(TRIM(E84))="AUSTRALIA"),"Australia",IF(OR(UPPER(TRIM(E84))="CAN",UPPER(TRIM(E84))="CANADA"),"Canada",IF(OR(UPPER(TRIM(E84))="DE",UPPER(TRIM(E84))="GERMANY"),"Germany",IF(OR(UPPER(TRIM(E84))="IN",UPPER(TRIM(E84))="INDIA"),"India",IF(OR(UPPER(TRIM(E84))="US",UPPER(TRIM(E84))="USA",UPPER(TRIM(E84))="UNITED STATES"),"United States",IF(OR(UPPER(TRIM(E84))="UK",UPPER(TRIM(E84))="U.K.",UPPER(TRIM(E84))="UNITED KINGDOM"),"United Kingdom",IF(OR(UPPER(TRIM(E84))="UAE",UPPER(TRIM(E84))="U.A.E.",UPPER(TRIM(E84))="UNITED ARAB EMIRATES"),"United Arab Emirates",IF(OR(UPPER(TRIM(E84))="SG",UPPER(TRIM(E84))="SINGAPORE"),"Singapore",TRIM(E84))))))))) -> Canada | G84: Office Chair | H84: Furniture | I84: 1 | J84: 210 | K84: 125 | L84: 0 | M84: paypal | N84: PayPal | O84: Shipped | P84: =PROPER(TRIM(O84)) -> Shipped | Q84: =IF(TRIM(R84)="","Missing",IF(AND(ISNUMBER(SEARCH("@",R84)),ISNUMBER(SEARCH(".",R84,SEARCH("@",R84)+2))),"Valid","Invalid")) -> Valid | R84: mia.white@example.com | S84: =I84*J84*(1-L84) -> 210 | T84: =I84*K84 -> 125 | U84: =S84-T84 -> 85 | V84: =IF(S84=0,0,U84/S84) -> 0.4047619
A85: ORD-10317 | B85: 45776 | C85: Sophia Taylor | D85: =PROPER(TRIM(C85)) -> Sophia Taylor | E85: DE | F85: =IF(OR(UPPER(TRIM(E85))="AUS",UPPER(TRIM(E85))="AUSTRALIA"),"Australia",IF(OR(UPPER(TRIM(E85))="CAN",UPPER(TRIM(E85))="CANADA"),"Canada",IF(OR(UPPER(TRIM(E85))="DE",UPPER(TRIM(E85))="GERMANY"),"Germany",IF(OR(UPPER(TRIM(E85))="IN",UPPER(TRIM(E85))="INDIA"),"India",IF(OR(UPPER(TRIM(E85))="US",UPPER(TRIM(E85))="USA",UPPER(TRIM(E85))="UNITED STATES"),"United States",IF(OR(UPPER(TRIM(E85))="UK",UPPER(TRIM(E85))="U.K.",UPPER(TRIM(E85))="UNITED KINGDOM"),"United Kingdom",IF(OR(UPPER(TRIM(E85))="UAE",UPPER(TRIM(E85))="U.A.E.",UPPER(TRIM(E85))="UNITED ARAB EMIRATES"),"United Arab Emirates",IF(OR(UPPER(TRIM(E85))="SG",UPPER(TRIM(E85))="SINGAPORE"),"Singapore",TRIM(E85))))))))) -> Germany | G85: Monitor 27-inch | H85: Electronics | I85: 3 | J85: 245 | K85: 150 | L85: 0.15 | M85: Credit Card | N85: =PROPER(TRIM(M85)) -> Credit Card | O85: Shipped | P85: =PROPER(TRIM(O85)) -> Shipped | Q85: =IF(TRIM(R85)="","Missing",IF(AND(ISNUMBER(SEARCH("@",R85)),ISNUMBER(SEARCH(".",R85,SEARCH("@",R85)+2))),"Valid","Invalid")) -> Valid | R85: sophia.taylor@example.com | S85: =I85*J85*(1-L85) -> 624.75 | T85: =I85*K85 -> 450 | U85: =S85-T85 -> 174.75 | V85: =IF(S85=0,0,U85/S85) -> 0.27971188
A86: ORD-10504 | B86: 45925 | C86: Daniel Harris | D86: =PROPER(TRIM(C86)) -> Daniel Harris | E86: India | F86: =IF(OR(UPPER(TRIM(E86))="AUS",UPPER(TRIM(E86))="AUSTRALIA"),"Australia",IF(OR(UPPER(TRIM(E86))="CAN",UPPER(TRIM(E86))="CANADA"),"Canada",IF(OR(UPPER(TRIM(E86))="DE",UPPER(TRIM(E86))="GERMANY"),"Germany",IF(OR(UPPER(TRIM(E86))="IN",UPPER(TRIM(E86))="INDIA"),"India",IF(OR(UPPER(TRIM(E86))="US",UPPER(TRIM(E86))="USA",UPPER(TRIM(E86))="UNITED STATES"),"United States",IF(OR(UPPER(TRIM(E86))="UK",UPPER(TRIM(E86))="U.K.",UPPER(TRIM(E86))="UNITED KINGDOM"),"United Kingdom",IF(OR(UPPER(TRIM(E86))="UAE",UPPER(TRIM(E86))="U.A.E.",UPPER(TRIM(E86))="UNITED ARAB EMIRATES"),"United Arab Emirates",IF(OR(UPPER(TRIM(E86))="SG",UPPER(TRIM(E86))="SINGAPORE"),"Singapore",TRIM(E86))))))))) -> India | G86: External HDD 2TB | H86: Storage | I86: 1 | J86: 78 | K86: 45 | L86: 0.1 | M86: Debit Card | N86: =PROPER(TRIM(M86)) -> Debit Card | O86: Pending | P86: =PROPER(TRIM(O86)) -> Pending | Q86: =IF(TRIM(R86)="","Missing",IF(AND(ISNUMBER(SEARCH("@",R86)),ISNUMBER(SEARCH(".",R86,SEARCH("@",R86)+2))),"Valid","Invalid")) -> Valid | R86: daniel.harris@example.com | S86: =I86*J86*(1-L86) -> 70.2 | T86: =I86*K86 -> 45 | U86: =S86-T86 -> 25.2 | V86: =IF(S86=0,0,U86/S86) -> 0.35897436
A87: ORD-10397 | B87: 45753 | C87: Sophia Taylor | D87: =PROPER(TRIM(C87)) -> Sophia Taylor | E87: IN | F87: =IF(OR(UPPER(TRIM(E87))="AUS",UPPER(TRIM(E87))="AUSTRALIA"),"Australia",IF(OR(UPPER(TRIM(E87))="CAN",UPPER(TRIM(E87))="CANADA"),"Canada",IF(OR(UPPER(TRIM(E87))="DE",UPPER(TRIM(E87))="GERMANY"),"Germany",IF(OR(UPPER(TRIM(E87))="IN",UPPER(TRIM(E87))="INDIA"),"India",IF(OR(UPPER(TRIM(E87))="US",UPPER(TRIM(E87))="USA",UPPER(TRIM(E87))="UNITED STATES"),"United States",IF(OR(UPPER(TRIM(E87))="UK",UPPER(TRIM(E87))="U.K.",UPPER(TRIM(E87))="UNITED KINGDOM"),"United Kingdom",IF(OR(UPPER(TRIM(E87))="UAE",UPPER(TRIM(E87))="U.A.E.",UPPER(TRIM(E87))="UNITED ARAB EMIRATES"),"United Arab Emirates",IF(OR(UPPER(TRIM(E87))="SG",UPPER(TRIM(E87))="SINGAPORE"),"Singapore",TRIM(E87))))))))) -> India | G87: Desk Lamp | H87: Furniture | I87: 1 | J87: 36 | K87: 16 | L87: 0.05 | M87: credit card | N87: =PROPER(TRIM(M87)) -> Credit Card | O87: Completed | P87: =PROPER(TRIM(O87)) -> Completed | Q87: =IF(TRIM(R87)="","Missing",IF(AND(ISNUMBER(SEARCH("@",R87)),ISNUMBER(SEARCH(".",R87,SEARCH("@",R87)+2))),"Valid","Invalid")) -> Missing | S87: =I87*J87*(1-L87) -> 34.2 | T87: =I87*K87 -> 16 | U87: =S87-T87 -> 18.2 | V87: =IF(S87=0,0,U87/S87) -> 0.53216374
A88: ORD-10051 | B88: 45779 | C88: Lucas Jackson | D88: =PROPER(TRIM(C88)) -> Lucas Jackson | E88: DE | F88: =IF(OR(UPPER(TRIM(E88))="AUS",UPPER(TRIM(E88))="AUSTRALIA"),"Australia",IF(OR(UPPER(TRIM(E88))="CAN",UPPER(TRIM(E88))="CANADA"),"Canada",IF(OR(UPPER(TRIM(E88))="DE",UPPER(TRIM(E88))="GERMANY"),"Germany",IF(OR(UPPER(TRIM(E88))="IN",UPPER(TRIM(E88))="INDIA"),"India",IF(OR(UPPER(TRIM(E88))="US",UPPER(TRIM(E88))="USA",UPPER(TRIM(E88))="UNITED STATES"),"United States",IF(OR(UPPER(TRIM(E88))="UK",UPPER(TRIM(E88))="U.K.",UPPER(TRIM(E88))="UNITED KINGDOM"),"United Kingdom",IF(OR(UPPER(TRIM(E88))="UAE",UPPER(TRIM(E88))="U.A.E.",UPPER(TRIM(E88))="UNITED ARAB EMIRATES"),"United Arab Emirates",IF(OR(UPPER(TRIM(E88))="SG",UPPER(TRIM(E88))="SINGAPORE"),"Singapore",TRIM(E88))))))))) -> Germany | G88: Wireless Mouse | H88: Accessories | I88: 5 | J88: 18 | K88: 7 | L88: 0 | M88: credit card | N88: =PROPER(TRIM(M88)) -> Credit Card | O88: Completed | P88: =PROPER(TRIM(O88)) -> Completed | Q88: =IF(TRIM(R88)="","Missing",IF(AND(ISNUMBER(SEARCH("@",R88)),ISNUMBER(SEARCH(".",R88,SEARCH("@",R88)+2))),"Valid","Invalid")) -> Valid | R88: lucas.jackson@example.com | S88: =I88*J88*(1-L88) -> 90 | T88: =I88*K88 -> 35 | U88: =S88-T88 -> 55 | V88: =IF(S88=0,0,U88/S88) -> 0.61111111
A89: ORD-10374 | B89: 45934 | C89: Mia White | D89: =PROPER(TRIM(C89)) -> Mia White | E89: Australia | F89: =IF(OR(UPPER(TRIM(E89))="AUS",UPPER(TRIM(E89))="AUSTRALIA"),"Australia",IF(OR(UPPER(TRIM(E89))="CAN",UPPER(TRIM(E89))="CANADA"),"Canada",IF(OR(UPPER(TRIM(E89))="DE",UPPER(TRIM(E89))="GERMANY"),"Germany",IF(OR(UPPER(TRIM(E89))="IN",UPPER(TRIM(E89))="INDIA"),"India",IF(OR(UPPER(TRIM(E89))="US",UPPER(TRIM(E89))="USA",UPPER(TRIM(E89))="UNITED STATES"),"United States",IF(OR(UPPER(TRIM(E89))="UK",UPPER(TRIM(E89))="U.K.",UPPER(TRIM(E89))="UNITED KINGDOM"),"United Kingdom",IF(OR(UPPER(TRIM(E89))="UAE",UPPER(TRIM(E89))="U.A.E.",UPPER(TRIM(E89))="UNITED ARAB EMIRATES"),"United Arab Emirates",IF(OR(UPPER(TRIM(E89))="SG",UPPER(TRIM(E89))="SINGAPORE"),"Singapore",TRIM(E89))))))))) -> Australia | G89: Wireless Mouse | H89: Accessories | I89: 4 | J89: 18 | K89: 7 | L89: 0 | M89: PayPal | N89: PayPal | O89: Cancelled | P89: =PROPER(TRIM(O89)) -> Cancelled | Q89: =IF(TRIM(R89)="","Missing",IF(AND(ISNUMBER(SEARCH("@",R89)),ISNUMBER(SEARCH(".",R89,SEARCH("@",R89)+2))),"Valid","Invalid")) -> Valid | R89: mia.white@example.com | S89: =I89*J89*(1-L89) -> 72 | T89: =I89*K89 -> 28 | U89: =S89-T89 -> 44 | V89: =IF(S89=0,0,U89/S89) -> 0.61111111
A90: ORD-10513 | B90: 45990 | C90: Lucas Jackson | D90: =PROPER(TRIM(C90)) -> Lucas Jackson | E90: singapore | F90: =IF(OR(UPPER(TRIM(E90))="AUS",UPPER(TRIM(E90))="AUSTRALIA"),"Australia",IF(OR(UPPER(TRIM(E90))="CAN",UPPER(TRIM(E90))="CANADA"),"Canada",IF(OR(UPPER(TRIM(E90))="DE",UPPER(TRIM(E90))="GERMANY"),"Germany",IF(OR(UPPER(TRIM(E90))="IN",UPPER(TRIM(E90))="INDIA"),"India",IF(OR(UPPER(TRIM(E90))="US",UPPER(TRIM(E90))="USA",UPPER(TRIM(E90))="UNITED STATES"),"United States",IF(OR(UPPER(TRIM(E90))="UK",UPPER(TRIM(E90))="U.K.",UPPER(TRIM(E90))="UNITED KINGDOM"),"United Kingdom",IF(OR(UPPER(TRIM(E90))="UAE",UPPER(TRIM(E90))="U.A.E.",UPPER(TRIM(E90))="UNITED ARAB EMIRATES"),"United Arab Emirates",IF(OR(UPPER(TRIM(E90))="SG",UPPER(TRIM(E90))="SINGAPORE"),"Singapore",TRIM(E90))))))))) -> Singapore | G90: Monitor 27-inch | H90: Electronics | I90: 5 | J90: 245 | K90: 150 | L90: 0.2 | M90: Credit Card | N90: =PROPER(TRIM(M90)) -> Credit Card | O90: Cancelled | P90: =PROPER(TRIM(O90)) -> Cancelled | Q90: =IF(TRIM(R90)="","Missing",IF(AND(ISNUMBER(SEARCH("@",R90)),ISNUMBER(SEARCH(".",R90,SEARCH("@",R90)+2))),"Valid","Invalid")) -> Valid | R90: lucas.jackson@example.com | S90: =I90*J90*(1-L90) -> 980 | T90: =I90*K90 -> 750 | U90: =S90-T90 -> 230 | V90: =IF(S90=0,0,U90/S90) -> 0.23469388
A91: ORD-10045 | B91: 45874 | C91: Daniel Harris | D91: =PROPER(TRIM(C91)) -> Daniel Harris | E91: UK | F91: =IF(OR(UPPER(TRIM(E91))="AUS",UPPER(TRIM(E91))="AUSTRALIA"),"Australia",IF(OR(UPPER(TRIM(E91))="CAN",UPPER(TRIM(E91))="CANADA"),"Canada",IF(OR(UPPER(TRIM(E91))="DE",UPPER(TRIM(E91))="GERMANY"),"Germany",IF(OR(UPPER(TRIM(E91))="IN",UPPER(TRIM(E91))="INDIA"),"India",IF(OR(UPPER(TRIM(E91))="US",UPPER(TRIM(E91))="USA",UPPER(TRIM(E91))="UNITED STATES"),"United States",IF(OR(UPPER(TRIM(E91))="UK",UPPER(TRIM(E91))="U.K.",UPPER(TRIM(E91))="UNITED KINGDOM"),"United Kingdom",IF(OR(UPPER(TRIM(E91))="UAE",UPPER(TRIM(E91))="U.A.E.",UPPER(TRIM(E91))="UNITED ARAB EMIRATES"),"United Arab Emirates",IF(OR(UPPER(TRIM(E91))="SG",UPPER(TRIM(E91))="SINGAPORE"),"Singapore",TRIM(E91))))))))) -> United Kingdom | G91: Laptop Stand | H91: Accessories | I91: 5 | J91: 38 | K91: 17 | L91: 0 | M91: credit card | N91: =PROPER(TRIM(M91)) -> Credit Card | O91: Cancelled | P91: =PROPER(TRIM(O91)) -> Cancelled | Q91: =IF(TRIM(R91)="","Missing",IF(AND(ISNUMBER(SEARCH("@",R91)),ISNUMBER(SEARCH(".",R91,SEARCH("@",R91)+2))),"Valid","Invalid")) -> Valid | R91: daniel.harris@example.com | S91: =I91*J91*(1-L91) -> 190 | T91: =I91*K91 -> 85 | U91: =S91-T91 -> 105 | V91: =IF(S91=0,0,U91/S91) -> 0.55263158
A92: ORD-10360 | B92: 46009 | C92: Mia White | D92: =PROPER(TRIM(C92)) -> Mia White | E92: U.K. | F92: =IF(OR(UPPER(TRIM(E92))="AUS",UPPER(TRIM(E92))="AUSTRALIA"),"Australia",IF(OR(UPPER(TRIM(E92))="CAN",UPPER(TRIM(E92))="CANADA"),"Canada",IF(OR(UPPER(TRIM(E92))="DE",UPPER(TRIM(E92))="GERMANY"),"Germany",IF(OR(UPPER(TRIM(E92))="IN",UPPER(TRIM(E92))="INDIA"),"India",IF(OR(UPPER(TRIM(E92))="US",UPPER(TRIM(E92))="USA",UPPER(TRIM(E92))="UNITED STATES"),"United States",IF(OR(UPPER(TRIM(E92))="UK",UPPER(TRIM(E92))="U.K.",UPPER(TRIM(E92))="UNITED KINGDOM"),"United Kingdom",IF(OR(UPPER(TRIM(E92))="UAE",UPPER(TRIM(E92))="U.A.E.",UPPER(TRIM(E92))="UNITED ARAB EMIRATES"),"United Arab Emirates",IF(OR(UPPER(TRIM(E92))="SG",UPPER(TRIM(E92))="SINGAPORE"),"Singapore",TRIM(E92))))))))) -> United Kingdom | G92: Webcam | H92: Electronics | I92: 3 | J92: 59 | K92: 30 | L92: 0 | M92: Credit Card | N92: =PROPER(TRIM(M92)) -> Credit Card | O92: Pending | P92: =PROPER(TRIM(O92)) -> Pending | Q92: =IF(TRIM(R92)="","Missing",IF(AND(ISNUMBER(SEARCH("@",R92)),ISNUMBER(SEARCH(".",R92,SEARCH("@",R92)+2))),"Valid","Invalid")) -> Valid | R92: mia.white@example.com | S92: =I92*J92*(1-L92) -> 177 | T92: =I92*K92 -> 90 | U92: =S92-T92 -> 87 | V92: =IF(S92=0,0,U92/S92) -> 0.49152542
A93: ORD-10181 | B93: 45709 | C93: Emma Wilson | D93: =PROPER(TRIM(C93)) -> Emma Wilson | E93: singapore | F93: =IF(OR(UPPER(TRIM(E93))="AUS",UPPER(TRIM(E93))="AUSTRALIA"),"Australia",IF(OR(UPPER(TRIM(E93))="CAN",UPPER(TRIM(E93))="CANADA"),"Canada",IF(OR(UPPER(TRIM(E93))="DE",UPPER(TRIM(E93))="GERMANY"),"Germany",IF(OR(UPPER(TRIM(E93))="IN",UPPER(TRIM(E93))="INDIA"),"India",IF(OR(UPPER(TRIM(E93))="US",UPPER(TRIM(E93))="USA",UPPER(TRIM(E93))="UNITED STATES"),"United States",IF(OR(UPPER(TRIM(E93))="UK",UPPER(TRIM(E93))="U.K.",UPPER(TRIM(E93))="UNITED KINGDOM"),"United Kingdom",IF(OR(UPPER(TRIM(E93))="UAE",UPPER(TRIM(E93))="U.A.E.",UPPER(TRIM(E93))="UNITED ARAB EMIRATES"),"United Arab Emirates",IF(OR(UPPER(TRIM(E93))="SG",UPPER(TRIM(E93))="SINGAPORE"),"Singapore",TRIM(E93))))))))) -> Singapore | G93: USB-C Hub | H93: Accessories | I93: 4 | J93: 42 | K93: 21 | L93: 0.15 | M93: Bank Transfer | N93: =PROPER(TRIM(M93)) -> Bank Transfer | O93: Pending | P93: =PROPER(TRIM(O93)) -> Pending | Q93: =IF(TRIM(R93)="","Missing",IF(AND(ISNUMBER(SEARCH("@",R93)),ISNUMBER(SEARCH(".",R93,SEARCH("@",R93)+2))),"Valid","Invalid")) -> Valid | R93: emma.wilson@example.com | S93: =I93*J93*(1-L93) -> 142.8 | T93: =I93*K93 -> 84 | U93: =S93-T93 -> 58.8 | V93: =IF(S93=0,0,U93/S93) -> 0.41176471
A94: ORD-10309 | B94: 45874 | C94: Alex Morgan | D94: =PROPER(TRIM(C94)) -> Alex Morgan | E94: Australia | F94: =IF(OR(UPPER(TRIM(E94))="AUS",UPPER(TRIM(E94))="AUSTRALIA"),"Australia",IF(OR(UPPER(TRIM(E94))="CAN",UPPER(TRIM(E94))="CANADA"),"Canada",IF(OR(UPPER(TRIM(E94))="DE",UPPER(TRIM(E94))="GERMANY"),"Germany",IF(OR(UPPER(TRIM(E94))="IN",UPPER(TRIM(E94))="INDIA"),"India",IF(OR(UPPER(TRIM(E94))="US",UPPER(TRIM(E94))="USA",UPPER(TRIM(E94))="UNITED STATES"),"United States",IF(OR(UPPER(TRIM(E94))="UK",UPPER(TRIM(E94))="U.K.",UPPER(TRIM(E94))="UNITED KINGDOM"),"United Kingdom",IF(OR(UPPER(TRIM(E94))="UAE",UPPER(TRIM(E94))="U.A.E.",UPPER(TRIM(E94))="UNITED ARAB EMIRATES"),"United Arab Emirates",IF(OR(UPPER(TRIM(E94))="SG",UPPER(TRIM(E94))="SINGAPORE"),"Singapore",TRIM(E94))))))))) -> Australia | G94: Monitor 27-inch | H94: Electronics | I94: 3 | J94: 245 | K94: 150 | L94: 0 | M94: credit card | N94: =PROPER(TRIM(M94)) -> Credit Card | O94: Completed | P94: =PROPER(TRIM(O94)) -> Completed | Q94: =IF(TRIM(R94)="","Missing",IF(AND(ISNUMBER(SEARCH("@",R94)),ISNUMBER(SEARCH(".",R94,SEARCH("@",R94)+2))),"Valid","Invalid")) -> Valid | R94: alex.morgan@example.com | S94: =I94*J94*(1-L94) -> 735 | T94: =I94*K94 -> 450 | U94: =S94-T94 -> 285 | V94: =IF(S94=0,0,U94/S94) -> 0.3877551
A95: ORD-10178 | B95: 45939 | C95: Lucas Jackson | D95: =PROPER(TRIM(C95)) -> Lucas Jackson | E95: UAE | F95: =IF(OR(UPPER(TRIM(E95))="AUS",UPPER(TRIM(E95))="AUSTRALIA"),"Australia",IF(OR(UPPER(TRIM(E95))="CAN",UPPER(TRIM(E95))="CANADA"),"Canada",IF(OR(UPPER(TRIM(E95))="DE",UPPER(TRIM(E95))="GERMANY"),"Germany",IF(OR(UPPER(TRIM(E95))="IN",UPPER(TRIM(E95))="INDIA"),"India",IF(OR(UPPER(TRIM(E95))="US",UPPER(TRIM(E95))="USA",UPPER(TRIM(E95))="UNITED STATES"),"United States",IF(OR(UPPER(TRIM(E95))="UK",UPPER(TRIM(E95))="U.K.",UPPER(TRIM(E95))="UNITED KINGDOM"),"United Kingdom",IF(OR(UPPER(TRIM(E95))="UAE",UPPER(TRIM(E95))="U.A.E.",UPPER(TRIM(E95))="UNITED ARAB EMIRATES"),"United Arab Emirates",IF(OR(UPPER(TRIM(E95))="SG",UPPER(TRIM(E95))="SINGAPORE"),"Singapore",TRIM(E95))))))))) -> United Arab Emirates | G95: Monitor 27-inch | H95: Electronics | I95: 2 | J95: 245 | K95: 150 | L95: 0.1 | M95: paypal | N95: PayPal | O95: Completed | P95: =PROPER(TRIM(O95)) -> Completed | Q95: =IF(TRIM(R95)="","Missing",IF(AND(ISNUMBER(SEARCH("@",R95)),ISNUMBER(SEARCH(".",R95,SEARCH("@",R95)+2))),"Valid","Invalid")) -> Missing | S95: =I95*J95*(1-L95) -> 441 | T95: =I95*K95 -> 300 | U95: =S95-T95 -> 141 | V95: =IF(S95=0,0,U95/S95) -> 0.31972789
A96: ORD-10008 | B96: 46002 | C96: Henry Clark | D96: =PROPER(TRIM(C96)) -> Henry Clark | E96: australia | F96: =IF(OR(UPPER(TRIM(E96))="AUS",UPPER(TRIM(E96))="AUSTRALIA"),"Australia",IF(OR(UPPER(TRIM(E96))="CAN",UPPER(TRIM(E96))="CANADA"),"Canada",IF(OR(UPPER(TRIM(E96))="DE",UPPER(TRIM(E96))="GERMANY"),"Germany",IF(OR(UPPER(TRIM(E96))="IN",UPPER(TRIM(E96))="INDIA"),"India",IF(OR(UPPER(TRIM(E96))="US",UPPER(TRIM(E96))="USA",UPPER(TRIM(E96))="UNITED STATES"),"United States",IF(OR(UPPER(TRIM(E96))="UK",UPPER(TRIM(E96))="U.K.",UPPER(TRIM(E96))="UNITED KINGDOM"),"United Kingdom",IF(OR(UPPER(TRIM(E96))="UAE",UPPER(TRIM(E96))="U.A.E.",UPPER(TRIM(E96))="UNITED ARAB EMIRATES"),"United Arab Emirates",IF(OR(UPPER(TRIM(E96))="SG",UPPER(TRIM(E96))="SINGAPORE"),"Singapore",TRIM(E96))))))))) -> Australia | G96: Desk Lamp | H96: Furniture | I96: 4 | J96: 36 | K96: 16 | L96: 0 | M96: Credit Card | N96: =PROPER(TRIM(M96)) -> Credit Card | O96: Completed | P96: =PROPER(TRIM(O96)) -> Completed | Q96: =IF(TRIM(R96)="","Missing",IF(AND(ISNUMBER(SEARCH("@",R96)),ISNUMBER(SEARCH(".",R96,SEARCH("@",R96)+2))),"Valid","Invalid")) -> Valid | R96: henry.clark@example.com | S96: =I96*J96*(1-L96) -> 144 | T96: =I96*K96 -> 64 | U96: =S96-T96 -> 80 | V96: =IF(S96=0,0,U96/S96) -> 0.55555556
A97: ORD-10293 | B97: 45873 | C97: Olivia Davis | D97: =PROPER(TRIM(C97)) -> Olivia Davis | E97: australia | F97: =IF(OR(UPPER(TRIM(E97))="AUS",UPPER(TRIM(E97))="AUSTRALIA"),"Australia",IF(OR(UPPER(TRIM(E97))="CAN",UPPER(TRIM(E97))="CANADA"),"Canada",IF(OR(UPPER(TRIM(E97))="DE",UPPER(TRIM(E97))="GERMANY"),"Germany",IF(OR(UPPER(TRIM(E97))="IN",UPPER(TRIM(E97))="INDIA"),"India",IF(OR(UPPER(TRIM(E97))="US",UPPER(TRIM(E97))="USA",UPPER(TRIM(E97))="UNITED STATES"),"United States",IF(OR(UPPER(TRIM(E97))="UK",UPPER(TRIM(E97))="U.K.",UPPER(TRIM(E97))="UNITED KINGDOM"),"United Kingdom",IF(OR(UPPER(TRIM(E97))="UAE",UPPER(TRIM(E97))="U.A.E.",UPPER(TRIM(E97))="UNITED ARAB EMIRATES"),"United Arab Emirates",IF(OR(UPPER(TRIM(E97))="SG",UPPER(TRIM(E97))="SINGAPORE"),"Singapore",TRIM(E97))))))))) -> Australia | G97: Desk Lamp | H97: Furniture | I97: 4 | J97: 36 | K97: 16 | L97: 0.15 | M97: Bank Transfer | N97: =PROPER(TRIM(M97)) -> Bank Transfer | O97: Completed | P97: =PROPER(TRIM(O97)) -> Completed | Q97: =IF(TRIM(R97)="","Missing",IF(AND(ISNUMBER(SEARCH("@",R97)),ISNUMBER(SEARCH(".",R97,SEARCH("@",R97)+2))),"Valid","Invalid")) -> Valid | R97: olivia.davis@example.com | S97: =I97*J97*(1-L97) -> 122.4 | T97: =I97*K97 -> 64 | U97: =S97-T97 -> 58.4 | V97: =IF(S97=0,0,U97/S97) -> 0.47712418
A98: ORD-10539 | B98: 45889 | C98: Chloe Lewis | D98: =PROPER(TRIM(C98)) -> Chloe Lewis | F98: Unknown | G98: Monitor 24-inch | H98: Electronics | I98: 3 | J98: 175 | K98: 105 | L98: 0.1 | M98: PayPal | N98: PayPal | O98: Completed | P98: =PROPER(TRIM(O98)) -> Completed | Q98: =IF(TRIM(R98)="","Missing",IF(AND(ISNUMBER(SEARCH("@",R98)),ISNUMBER(SEARCH(".",R98,SEARCH("@",R98)+2))),"Valid","Invalid")) -> Valid | R98: chloe.lewis@example.com | S98: =I98*J98*(1-L98) -> 472.5 | T98: =I98*K98 -> 315 | U98: =S98-T98 -> 157.5 | V98: =IF(S98=0,0,U98/S98) -> 0.33333333
A99: ORD-10301 | B99: 45801 | C99: Emma Wilson | D99: =PROPER(TRIM(C99)) -> Emma Wilson | E99: IN | F99: =IF(OR(UPPER(TRIM(E99))="AUS",UPPER(TRIM(E99))="AUSTRALIA"),"Australia",IF(OR(UPPER(TRIM(E99))="CAN",UPPER(TRIM(E99))="CANADA"),"Canada",IF(OR(UPPER(TRIM(E99))="DE",UPPER(TRIM(E99))="GERMANY"),"Germany",IF(OR(UPPER(TRIM(E99))="IN",UPPER(TRIM(E99))="INDIA"),"India",IF(OR(UPPER(TRIM(E99))="US",UPPER(TRIM(E99))="USA",UPPER(TRIM(E99))="UNITED STATES"),"United States",IF(OR(UPPER(TRIM(E99))="UK",UPPER(TRIM(E99))="U.K.",UPPER(TRIM(E99))="UNITED KINGDOM"),"United Kingdom",IF(OR(UPPER(TRIM(E99))="UAE",UPPER(TRIM(E99))="U.A.E.",UPPER(TRIM(E99))="UNITED ARAB EMIRATES"),"United Arab Emirates",IF(OR(UPPER(TRIM(E99))="SG",UPPER(TRIM(E99))="SINGAPORE"),"Singapore",TRIM(E99))))))))) -> India | G99: Headphones | H99: Electronics | I99: 2 | J99: 85 | K99: 44 | L99: 0 | M99: Debit Card | N99: =PROPER(TRIM(M99)) -> Debit Card | O99: Pending | P99: =PROPER(TRIM(O99)) -> Pending | Q99: =IF(TRIM(R99)="","Missing",IF(AND(ISNUMBER(SEARCH("@",R99)),ISNUMBER(SEARCH(".",R99,SEARCH("@",R99)+2))),"Valid","Invalid")) -> Valid | R99: emma.wilson@example.com | S99: =I99*J99*(1-L99) -> 170 | T99: =I99*K99 -> 88 | U99: =S99-T99 -> 82 | V99: =IF(S99=0,0,U99/S99) -> 0.48235294
A100: ORD-10334 | B100: 45774 | C100: Ethan Anderson | D100: =PROPER(TRIM(C100)) -> Ethan Anderson | E100: U.K. | F100: =IF(OR(UPPER(TRIM(E100))="AUS",UPPER(TRIM(E100))="AUSTRALIA"),"Australia",IF(OR(UPPER(TRIM(E100))="CAN",UPPER(TRIM(E100))="CANADA"),"Canada",IF(OR(UPPER(TRIM(E100))="DE",UPPER(TRIM(E100))="GERMANY"),"Germany",IF(OR(UPPER(TRIM(E100))="IN",UPPER(TRIM(E100))="INDIA"),"India",IF(OR(UPPER(TRIM(E100))="US",UPPER(TRIM(E100))="USA",UPPER(TRIM(E100))="UNITED STATES"),"United States",IF(OR(UPPER(TRIM(E100))="UK",UPPER(TRIM(E100))="U.K.",UPPER(TRIM(E100))="UNITED KINGDOM"),"United Kingdom",IF(OR(UPPER(TRIM(E100))="UAE",UPPER(TRIM(E100))="U.A.E.",UPPER(TRIM(E100))="UNITED ARAB EMIRATES"),"United Arab Emirates",IF(OR(UPPER(TRIM(E100))="SG",UPPER(TRIM(E100))="SINGAPORE"),"Singapore",TRIM(E100))))))))) -> United Kingdom | G100: Office Chair | H100: Furniture | I100: 3 | J100: 210 | K100: 125 | L100: 0.05 | M100: Bank Transfer | N100: =PROPER(TRIM(M100)) -> Bank Transfer | O100: Pending | P100: =PROPER(TRIM(O100)) -> Pending | Q100: =IF(TRIM(R100)="","Missing",IF(AND(ISNUMBER(SEARCH("@",R100)),ISNUMBER(SEARCH(".",R100,SEARCH("@",R100)+2))),"Valid","Invalid")) -> Valid | R100: ethan.anderson@example.com | S100: =I100*J100*(1-L100) -> 598.5 | T100: =I100*K100 -> 375 | U100: =S100-T100 -> 223.5 | V100: =IF(S100=0,0,U100/S100) -> 0.37343358
...

Sheet KPI_Summary
A1: KPI | B1: Value
A2: Total Revenue | B2: =SUM(Clean_Data!S2:S551) -> 147019.1
A3: Total Cost | B3: =SUM(Clean_Data!T2:T551) -> 88021
A4: Gross Profit | B4: =SUM(Clean_Data!U2:U551) -> 58998.1
A5: Overall Profit Margin | B5: =IF(B2=0,0,B4/B2) -> 0.40129548
A6: Total Orders | B6: =COUNTA(Clean_Data!A2:A551) -> 550
A7: Average Order Value | B7: =IF(B6=0,0,B2/B6) -> 267.30745

Sheet Raw_Data
A1: Order_ID | B1: Order_Date | C1: Customer_Name | D1: Country | E1: Product | F1: Category | G1: Quantity | H1: Unit_Price_USD | I1: Unit_Cost_USD | J1: Discount | K1: Payment_Method | L1: Order_Status | M1: Customer_Email
A2: ORD-10087 | B2: 45735 | C2: Liam Miller | D2: UAE | E2: Desk Lamp | F2: Furniture | G2: 3 | H2: 36 | I2: 16 | J2: 0 | K2: paypal | L2: Completed | M2: liam.miller@example.com
A3: ORD-10007 | B3: 45894 | C3: Ava Thomas | D3: UAE | E3: Laptop Stand | F3: Accessories | G3: 4 | H3: 38 | I3: 17 | J3: 0 | K3: credit card | L3: Completed | M3: ava.thomas@example.com
A4: ORD-10143 | B4: 45777 | C4: alex morgan | D4: australia | E4: Wireless Mouse | F4: Accessories | G4: 1 | H4: 18 | I4: 7 | J4: 0.05 | K4: PayPal | L4: Completed | M4: alex.morgan@example.com
A5: ORD-10127 | B5: 45834 | C5: Liam Miller | D5: UK | E5: SSD 1TB | F5: Storage | G5: 1 | H5: 92 | I5: 53 | J5: 0 | K5: credit card | L5: Completed | M5: liam.miller@example.com
A6: ORD-10470 | B6: 46000 | C6: Lily Hall | D6: AUS | E6: SSD 1TB | F6: Storage | G6: 1 | H6: 92 | I6: 53 | J6: 0.05 | K6: Bank Transfer | L6: Pending | M6: lily.hall@example.com
A7: ORD-10279 | B7: 45764 | C7: Sophia Taylor | D7: germany | E7: External HDD 2TB | F7: Storage | G7: 5 | H7: 78 | I7: 45 | J7: 0.1 | K7: Debit Card | L7: Completed | M7: sophia.taylor@example.com
A8: ORD-10463 | B8: 45900 | C8: Daniel Harris | D8: USA | E8: Desk Lamp | F8: Furniture | G8: 2 | H8: 36 | I8: 16 | J8: 0.15 | K8: Bank Transfer | L8: Completed | M8: daniel.harris@example
A9: ORD-10041 | B9: 45753 | C9: Mia White | D9: germany | E9: Headphones | F9: Electronics | G9: 4 | H9: 85 | I9: 44 | J9: 0 | K9: credit card | L9: Completed | M9: mia.white@example.com
A10: ORD-10207 | B10: 45743 | C10: Grace Moore | D10: SG | E10: USB-C Hub | F10: Accessories | G10: 3 | H10: 42 | I10: 21 | J10: 0.05 | K10: paypal | L10: Cancelled | M10: grace.moore@example.com
A11: ORD-10011 | B11: 45914 | C11: Henry Clark | D11: CAN | E11: Office Chair | F11: Furniture | G11: 1 | H11: 210 | I11: 125 | J11: 0.05 | K11: PayPal | L11: Cancelled | M11: henry.clark@example.com
A12: ORD-10049 | B12: 45801 | C12: Olivia Davis | D12: DE | E12: Webcam | F12: Electronics | G12: 3 | H12: 59 | I12: 30 | J12: 0.05 | K12: credit card | L12: Completed | M12: olivia.davis@example.com
A13: ORD-10215 | B13: 45918 | C13: Daniel Harris | D13: SG | E13: USB-C Hub | F13: Accessories | G13: 3 | H13: 42 | I13: 21 | J13: 0 | K13: paypal | L13: Pending | M13: daniel.harris@example.com
... A19: ORD-10072 | B19: 45704 | C19: Lucas Jackson | D19: USA | E19: Mechanical Keyboard | F19: Accessories | G19: 2 | H19: 65 | I19: 31 | J19: 0.1 | K19: paypal | L19: Completed | M19: lucas.jackson@example.com
A20: ORD-10033 | B20: 45979 | C20: Henry Clark | D20: US | E20: Laptop Stand | F20: Accessories | G20: 4 | H20: 38 | I20: 17 | J20: 0.15 | K20: Bank Transfer | L20: Pending
A21: ORD-10264 | B21: 45815 | C21: Chloe Lewis | D21: DE | E21: SSD 1TB | F21: Storage | G21: 1 | H21: 92 | I21: 53 | J21: 0.2 | K21: Bank Transfer | L21: Shipped | M21: chloe.lewis@example.com
A22: ORD-10210 | B22: 45889 | C22: Chloe Lewis | D22: United Kingdom | E22: Webcam | F22: Electronics | G22: 4 | H22: 59 | I22: 30 | J22: 0.15 | K22: Credit Card | L22: Completed
A23: ORD-10274 | B23: 45831 | C23: Ava Thomas | D23: Singapore | E23: External HDD 2TB | F23: Storage | G23: 4 | H23: 78 | I23: 45 | J23: 0.1 | L23: Pending | M23: ava.thomas@example.com
A24: ORD-10004 | B24: 45792 | C24: Noah Brown | D24: Australia | E24: USB-C Hub | F24: Accessories | G24: 4 | H24: 42 | I24: 21 | J24: 0.05 | K24: Credit Card | L24: Cancelled | M24: noah.brown@example.com
A25: ORD-10200 | B25: 45933 | C25: Noah Brown | D25: Canada | E25: Webcam | F25: Electronics | G25: 2 | H25: 59 | I25: 30 | J25: 0 | K25: PayPal | L25: Completed | M25: noah.brown@example.com
A26: ORD-10191 | B26: 45684 | C26: Emma Wilson | D26: US | E26: Headphones | F26: Electronics | G26: 4 | H26: 85 | I26: 44 | J26: 0.05 | K26: paypal | L26: Cancelled | M26: emma.wilson@example.com
A27: ORD-10266 | B27: 45733 | C27: Henry Clark | D27: India | E27: Mechanical Keyboard | F27: Accessories | G27: 1 | H27: 65 | I27: 31 | J27: 0 | K27: Credit Card | L27: Pending | M27: henry.clark@example.com
A28: ORD-10280 | B28: 45852 | C28: Ella Martin | D28: germany | E28: SSD 1TB | F28: Storage | G28: 2 | H28: 92 | I28: 53 | J28: 0.05 | K28: Debit Card | L28: Shipped | M28: ella.martin@example.com
A29: ORD-10209 | B29: 45845 | C29: Olivia Davis | D29: U.K. | E29: Webcam | F29: Electronics | G29: 5 | H29: 59 | I29: 30 | J29: 0.2 | K29: credit card | L29: Completed | M29: olivia.davis@example.com
A30: ORD-10028 | B30: 45706 | C30: olivia davis | D30: Germany | E30: Wireless Mouse | F30: Accessories | G30: 4 | H30: 18 | I30: 7 | J30: 0.1 | K30: Debit Card | L30: Completed | M30: olivia.davis@example.com
A31: ORD-10211 | B31: 45674 | C31: Benjamin Walker | D31: united kingdom | E31: Headphones | F31: Electronics | G31: 5 | H31: 85 | I31: 44 | J31: 0.2 | K31: Credit Card | L31: Completed | M31: benjamin.walker@example.com
A32: ORD-10372 | B32: 45778 | C32: grace moore | D32: Singapore | E32: Desk Lamp | F32: Furniture | G32: 1 | H32: 36 | I32: 16 | J32: 0.1 | K32: paypal | L32: Completed | M32: grace.moore@example.com
A33: ORD-10306 | B33: 45811 | C33: Benjamin Walker | D33: US | E33: Office Chair | F33: Furniture | G33: 4 | H33: 210 | I33: 125 | J33: 0.05 | K33: paypal | L33: Completed | M33: benjamin.walker@example.com
A34: ORD-10444 | B34: 45747 | C34: Ella Martin | D34: Australia | E34: Monitor 27-inch | F34: Electronics | G34: 3 | H34: 245 | I34: 150 | J34: 0.1 | K34: Bank Transfer | L34: Cancelled | M34: ella.martin@example.com
A35: ORD-10201 | B35: 45967 | C35: Alex Morgan | D35: US | E35: Headphones | F35: Electronics | G35: 4 | H35: 85 | I35: 44 | J35: 0.05 | K35: credit card | L35: Pending | M35: alex.morgan@example.com
... A61: ORD-10167 | B61: 45861 | C61: Daniel Harris | D61: australia | E61: Webcam | F61: Electronics | G61: 3 | H61: 59 | I61: 30 | J61: 0.15 | K61: Credit Card | L61: Cancelled | M61: daniel.harris@example.com
A62: ORD-10277 | B62: 45685 | C62: Lucas Jackson | E62: Office Chair | F62: Furniture | G62: 2 | H62: 210 | I62: 125 | J62: 0.05 | K62: Debit Card | L62: Completed | M62: lucas.jackson@example.com
A63: ORD-10003 | B63: 45716 | C63: ella martin | D63: australia | E63: Wireless Mouse | F63: Accessories | G63: 2 | H63: 18 | I63: 7 | J63: 0.05 | K63: Debit Card | L63: Completed | M63: ella.martin@example.com
A64: ORD-10103 | B64: 45789 | C64: Sophia Taylor | D64: australia | E64: Headphones | F64: Electronics | G64: 1 | H64: 85 | I64: 44 | J64: 0.05 | K64: credit card | L64: Completed | M64: sophia.taylor@example.com
A65: ORD-10248 | B65: 45729 | C65: Olivia Davis | D65: IN | E65: Monitor 27-inch | F65: Electronics | G65: 4 | H65: 245 | I65: 150 | J65: 0.1 | K65: paypal | L65: Completed | M65: olivia.davis@example.com
A66: ORD-10156 | B66: 45741 | C66: Lily Hall | D66: U.K. | E66: SSD 1TB | F66: Storage | G66: 4 | H66: 92 | I66: 53 | J66: 0.15 | K66: Bank Transfer | L66: Pending | M66: lily.hall@example.com
A67: ORD-10434 | B67: 45715 | C67: Benjamin Walker | D67: Canada | E67: Webcam | F67: Electronics | G67: 4 | H67: 59 | I67: 30 | J67: 0.1 | K67: Debit Card | L67: Cancelled | M67: benjamin.walker@example.com
A68: ORD-10047 | B68: 45741 | C68: Benjamin Walker | D68: US | E68: Monitor 24-inch | F68: Electronics | G68: 3 | H68: 175 | I68: 105 | J68: 0 | K68: paypal | L68: Completed | M68: benjamin.walker@example.com
A69: ORD-10263 | B69: 45991 | C69: Noah Brown | D69: AUS | E69: Monitor 27-inch | F69: Electronics | G69: 1 | H69: 245 | I69: 150 | J69: 0.1 | K69: Credit Card | L69: Pending | M69: noah.brown@example.com
A70: ORD-10133 | B70: 45725 | C70: henry clark | D70: UAE | E70: USB-C Hub | F70: Accessories | G70: 5 | H70: 42 | I70: 21 | J70: 0 | K70: credit card | L70: Pending
A71: ORD-10492 | B71: 45925 | C71: Chloe Lewis | D71: canada | E71: Monitor 24-inch | F71: Electronics | G71: 5 | H71: 175 | I71: 105 | J71: 0.05 | K71: Bank Transfer | L71: Pending | M71: chloe.lewis@example.com
A72: ORD-10352 | B72: 45863 | C72: liam miller | D72: australia | E72: Laptop Stand | F72: Accessories | G72: 2 | H72: 38 | I72: 17 | J72: 0.15 | K72: PayPal | L72: Completed | M72: liam.miller@example.com
A73: ORD-10142 | B73: 45853 | C73: Liam Miller | D73: singapore | E73: Mechanical Keyboard | F73: Accessories | G73: 4 | H73: 65 | I73: 31 | J73: 0.1 | K73: Debit Card | L73: Shipped | M73: liam.miller@example.com
A74: ORD-10212 | B74: 45860 | C74: Ava Thomas | D74: United Kingdom | E74: Wireless Mouse | F74: Accessories | G74: 2 | H74: 18 | I74: 7 | J74: 0 | K74: Bank Transfer | L74: Completed | M74: ava.thomas@example.com
A75: ORD-10114 | B75: 45967 | C75: grace moore | D75: germany | E75: External HDD 2TB | F75: Storage | G75: 1 | H75: 78 | I75: 45 | J75: 0.05 | K75: Credit Card | L75: Completed | M75: grace.moore@example.com
A76: ORD-10018 | B76: 45787 | C76: Alex Morgan | D76: AUS | E76: Mechanical Keyboard | F76: Accessories | G76: 5 | H76: 65 | I76: 31 | J76: 0 | K76: Debit Card | L76: Cancelled | M76: alex.morgan@example.com
A77: ORD-10196 | B77: 45883 | C77: Ella Martin | D77: singapore | E77: Monitor 27-inch | F77: Electronics | G77: 1 | H77: 245 | I77: 150 | J77: 0.05 | K77: paypal | L77: Cancelled | M77: ella.martin@example.com
A78: ORD-10168 | B78: 45950 | C78: Lily Hall | D78: australia | E78: Headphones | F78: Electronics | G78: 3 | H78: 85 | I78: 44 | J78: 0 | K78: PayPal | L78: Shipped | M78: lily.hall@example
A79: ORD-10307 | B79: 45814 | C79: Ella Martin | D79: U.K. | E79: Monitor 27-inch | F79: Electronics | G79: 1 | H79: 245 | I79: 150 | J79: 0 | K79: Bank Transfer | L79: Shipped | M79: ella.martin@example.com
A80: ORD-10153 | B80: 45899 | C80: Mia White | D80: United States | E80: Desk Lamp | F80: Furniture | G80: 4 | H80: 36 | I80: 16 | J80: 0.1 | K80: Credit Card | L80: Shipped | M80: mia.white@example.com
A81: ORD-10378 | B81: 45751 | C81: Sophia Taylor | D81: Singapore | E81: Wireless Mouse | F81: Accessories | G81: 5 | H81: 18 | I81: 7 | J81: 0.1 | K81: paypal | L81: pending | M81: sophia.taylor@example.com
A82: ORD-10532 | B82: 45803 | C82: Liam Miller | D82: USA | E82: USB-C Hub | F82: Accessories | G82: 4 | H82: 42 | I82: 21 | J82: 0.1 | K82: credit card | L82: Completed | M82: liam.miller@example.com
A83: ORD-10363 | B83: 45945 | C83: Grace Moore | D83: UK | E83: Wireless Mouse | F83: Accessories | G83: 4 | H83: 18 | I83: 7 | J83: 0.1 | L83: Pending | M83: grace.moore@example.com
A84: ORD-10119 | B84: 45960 | C84: Mia White | D84: canada | E84: Office Chair | F84: Furniture | G84: 1 | H84: 210 | I84: 125 | J84: 0 | K84: paypal | L84: Shipped | M84: mia.white@example.com
A85: ORD-10317 | B85: 45776 | C85: Sophia Taylor | D85: DE | E85: Monitor 27-inch | F85: Electronics | G85: 3 | H85: 245 | I85: 150 | J85: 0.15 | K85: Credit Card | L85: Shipped | M85: sophia.taylor@example.com
A86: ORD-10504 | B86: 45925 | C86: Daniel Harris | D86: India | E86: External HDD 2TB | F86: Storage | G86: 1 | H86: 78 | I86: 45 | J86: 0.1 | K86: Debit Card | L86: Pending | M86: daniel.harris@example.com
A87: ORD-10397 | B87: 45753 | C87: Sophia Taylor | D87: IN | E87: Desk Lamp | F87: Furniture | G87: 1 | H87: 36 | I87: 16 | J87: 0.05 | K87: credit card | L87: Completed
A88: ORD-10051 | B88: 45779 | C88: Lucas Jackson | D88: DE | E88: Wireless Mouse | F88: Accessories | G88: 5 | H88: 18 | I88: 7 | J88: 0 | K88: credit card | L88: Completed | M88: lucas.jackson@example.com
A89: ORD-10374 | B89: 45934 | C89: Mia White | D89: Australia | E89: Wireless Mouse | F89: Accessories | G89: 4 | H89: 18 | I89: 7 | J89: 0 | K89: PayPal | L89: Cancelled | M89: mia.white@example.com
A90: ORD-10513 | B90: 45990 | C90: Lucas Jackson | D90: singapore | E90: Monitor 27-inch | F90: Electronics | G90: 5 | H90: 245 | I90: 150 | J90: 0.2 | K90: Credit Card | L90: Cancelled | M90: lucas.jackson@example.com
A91: ORD-10045 | B91: 45874 | C91: Daniel Harris | D91: UK | E91: Laptop Stand | F91: Accessories | G91: 5 | H91: 38 | I91: 17 | J91: 0 | K91: credit card | L91: Cancelled | M91: daniel.harris@example.com
A92: ORD-10360 | B92: 46009 | C92: Mia White | D92: U.K. | E92: Webcam | F92: Electronics | G92: 3 | H92: 59 | I92: 30 | J92: 0 | K92: Credit Card | L92: Pending | M92: mia.white@example.com
A93: ORD-10181 | B93: 45709 | C93: Emma Wilson | D93: singapore | E93: USB-C Hub | F93: Accessories | G93: 4 | H93: 42 | I93: 21 | J93: 0.15 | K93: Bank Transfer | L93: Pending | M93: emma.wilson@example.com
A94: ORD-10309 | B94: 45874 | C94: Alex Morgan | D94: Australia | E94: Monitor 27-inch | F94: Electronics | G94: 3 | H94: 245 | I94: 150 | J94: 0 | K94: credit card | L94: Completed | M94: alex.morgan@example.com
A95: ORD-10178 | B95: 45939 | C95: Lucas Jackson | D95: UAE | E95: Monitor 27-inch | F95: Electronics | G95: 2 | H95: 245 | I95: 150 | J95: 0.1 | K95: paypal | L95: Completed
A96: ORD-10008 | B96: 46002 | C96: Henry Clark | D96: australia | E96: Desk Lamp | F96: Furniture | G96: 4 | H96: 36 | I96: 16 | J96: 0 | K96: Credit Card | L96: Completed | M96: henry.clark@example.com
A97: ORD-10293 | B97: 45873 | C97: Olivia Davis | D97: australia | E97: Desk Lamp | F97: Furniture | G97: 4 | H97: 36 | I97: 16 | J97: 0.15 | K97: Bank Transfer | L97: Completed | M97: olivia.davis@example.com
A98: ORD-10539 | B98: 45889 | C98: Chloe Lewis | E98: Monitor 24-inch | F98: Electronics | G98: 3 | H98: 175 | I98: 105 | J98: 0.1 | K98: PayPal | L98: Completed | M98: chloe.lewis@example.com
A99: ORD-10301 | B99: 45801 | C99: Emma Wilson | D99: IN | E99: Headphones | F99: Electronics | G99: 2 | H99: 85 | I99: 44 | J99: 0 | K99: Debit Card | L99: Pending | M99: emma.wilson@example.com
A100: ORD-10334 | B100: 45774 | C100: Ethan Anderson | D100: U.K. | E100: Office Chair | F100: Furniture | G100: 3 | H100: 210 | I100: 125 | J100: 0.05 | K100: Bank Transfer | L100: Pending | M100: ethan.anderson@example.com
A101: ORD-10517 | B101: 45877 | C101: Henry Clark | D101: AUS | E101: SSD 1TB | F101: Storage | G101: 3 | H101: 92 | I101: 53 | J101: 0 | K101: Debit Card | L101: completed | M101: henry.clark@example.com
A102: ORD-10189 | B102: 45937 | C102: Ethan Anderson | D102: UK | E102: Webcam | F102: Electronics | G102: 3 | H102: 59 | I102: 30 | J102: 0.05 | K102: paypal | L102: Shipped | M102: ethan.anderson@example.com
A103: ORD-10361 | B103: 45972 | C103: Mia White | D103: U.K. | E103: Desk Lamp | F103: Furniture | G103: 5 | H103: 36 | I103: 16 | J103: 0 | K103: Bank Transfer | L103: Pending | M103: mia.white@example.com
A104: ORD-10473 | B104: 45661 | C104: Daniel Harris | D104: Germany | E104: Monitor 24-inch | F104: Electronics | G104: 3 | H104: 175 | I104: 105 | J104: 0 | K104: PayPal | L104: Completed | M104: daniel.harris@example.com
A105: ORD-10521 | B105: 45756 | C105: Benjamin Walker | D105: AUS | E105: Desk Lamp | F105: Furniture | G105: 4 | H105: 36 | I105: 16 | J105: 0.05 | K105: Bank Transfer | L105: Completed | M105: benjamin.walker@example.com
A106: ORD-10172 | B106: 45771 | C106: Daniel Harris | D106: germany | E106: Headphones | F106: Electronics | G106: 2 | H106: 85 | I106: 44 | J106: 0.1 | K106: Credit Card | L106: Completed | M106: daniel.harris@example.com
A107: ORD-10187 | B107: 45806 | C107: Emma Wilson | D107: germany | E107: Mechanical Keyboard | F107: Accessories | G107: 1 | H107: 65 | I107: 31 | J107: 0.1 | K107: paypal | L107: Completed | M107: emma.wilson@example
A108: ORD-10462 | B108: 45871 | C108: daniel harris | D108: IN | E108: Laptop Stand | F108: Accessories | G108: 2 | H108: 38 | I108: 17 | J108: 0 | K108: Credit Card | L108: Cancelled | M108: daniel.harris@example.com
A109: ORD-10044 | B109: 45747 | C109: Ava Thomas | D109: U.K. | E109: USB-C Hub | F109: Accessories | G109: 3 | H109: 42 | I109: 21 | J109: 0 | K109: PayPal | L109: Pending | M109: ava.thomas@example.com
A110: ORD-10116 | B110: 45884 | C110: Olivia Davis | D110: U.A.E. | E110: Monitor 27-inch | F110: Electronics | G110: 5 | H110: 245 | I110: 150 | J110: 0.05 | K110: Bank Transfer | L110: Shipped | M110: olivia.davis@example.com
... A148: ORD-10085 | B148: 45893 | C148: Benjamin Walker | D148: U.A.E. | E148: Monitor 27-inch | F148: Electronics | G148: 3 | H148: 245 | I148: 150 | J148: 0 | K148: paypal | L148: Completed | M148: benjamin.walker@example.com
A149: ORD-10304 | B149: 45805 | C149: Ava Thomas | D149: SG | E149: Wireless Mouse | F149: Accessories | G149: 2 | H149: 18 | I149: 7 | J149: 0.05 | K149: paypal | L149: Completed
A150: ORD-10092 | B150: 45841 | C150: Olivia Davis | D150: uae | E150: Wireless Mouse | F150: Accessories | G150: 5 | H150: 18 | I150: 7 | J150: 0 | K150: credit card | L150: Cancelled | M150: olivia.davis@example.com
A151: ORD-10029 | B151: 45959 | C151: Liam Miller | D151: uae | E151: Webcam | F151: Electronics | G151: 3 | H151: 59 | I151: 30 | J151: 0.1 | K151: Bank Transfer | L151: Cancelled | M151: liam.miller@example.com
A152: ORD-10073 | B152: 45770 | C152: Olivia Davis | D152: singapore | E152: Office Chair | F152: Furniture | G152: 5 | H152: 210 | I152: 125 | J152: 0 | K152: credit card | L152: Completed | M152: olivia.davis@example.com
A153: ORD-10440 | B153: 45951 | C153: Benjamin Walker | D153: united kingdom | E153: USB-C Hub | F153: Accessories | G153: 5 | H153: 42 | I153: 21 | J153: 0.05 | K153: PayPal | L153: Cancelled | M153: benjamin.walker@example.com
A154: ORD-10544 | B154: 45829 | C154: Chloe Lewis | D154: Singapore | E154: Monitor 27-inch | F154: Electronics | G154: 3 | H154: 245 | I154: 150 | J154: 0.2 | K154: Bank Transfer | L154: Completed | M154: chloe.lewis@example.com
A155: ORD-10192 | B155: 45829 | C155: sophia taylor | D155: AUS | E155: Headphones | F155: Electronics | G155: 5 | H155: 85 | I155: 44 | J155: 0.05 | K155: paypal | L155: Completed | M155: sophia.taylor@example.com
A156: ORD-10155 | B156: 45780 | C156: Daniel Harris | D156: U.K. | E156: Mechanical Keyboard | F156: Accessories | G156: 4 | H156: 65 | I156: 31 | J156: 0 | K156: Credit Card | L156: Pending | M156: daniel.harris@example.com
A157: ORD-10313 | B157: 45873 | C157: james thompson | D157: IN | E157: Headphones | F157: Electronics | G157: 1 | H157: 85 | I157: 44 | J157: 0.1 | K157: PayPal | L157: Shipped | M157: james.thompson@example.com
A158: ORD-10296 | B158: 45955 | C158: Daniel Harris | D158: IN | E158: Monitor 24-inch | F158: Electronics | G158: 2 | H158: 175 | I158: 105 | J158: 0.05 | K158: credit card | L158: Pending | M158: daniel.harris@example.com
A159: ORD-10441 | B159: 45769 | C159: Sophia Taylor | D159: Germany | E159: SSD 1TB | F159: Storage | G159: 1 | H159: 92 | I159: 53 | J159: 0.05 | K159: Debit Card | L159: Shipped | M159: sophia.taylor@example.com
A160: ORD-10250 | B160: 45833 | C160: Ava Thomas | E160: Wireless Mouse | F160: Accessories | G160: 1 | H160: 18 | I160: 7 | J160: 0 | K160: credit card | L160: Completed | M160: ava.thomas@example.com
A161: ORD-10259 | B161: 45695 | C161: Emma Wilson | D161: CAN | E161: Mechanical Keyboard | F161: Accessories | G161: 1 | H161: 65 | I161: 31 | J161: 0.15 | K161: Debit Card | L161: Pending | M161: emma.wilson@example.com
A162: ORD-10406 | B162: 45978 | C162: Mia White | D162: SG | E162: Office Chair | F162: Furniture | G162: 1 | H162: 210 | I162: 125 | J162: 0.1 | K162: Credit Card | L162: Shipped | M162: mia.white@example.com
A163: ORD-10319 | B163: 45700 | C163: ella martin | D163: united states | E163: SSD 1TB | F163: Storage | G163: 2 | H163: 92 | I163: 53 | J163: 0 | K163: Debit Card | L163: Cancelled | M163: ella.martin@example.com
A164: ORD-10330 | B164: 45904 | C164: Daniel Harris | D164: germany | E164: Office Chair | F164: Furniture | G164: 2 | H164: 210 | I164: 125 | J164: 0.1 | K164: PayPal | L164: Cancelled | M164: daniel.harris@example.com
A165: ORD-10498 | B165: 45895 | C165: Benjamin Walker | D165: U.A.E. | E165: Laptop Stand | F165: Accessories | G165: 3 | H165: 38 | I165: 17 | J165: 0.1 | K165: Debit Card | L165: Pending | M165: benjamin.walker@example.com
A166: ORD-10294 | B166: 45832 | C166: Lily Hall | D166: US | E166: Mechanical Keyboard | F166: Accessories | G166: 3 | H166: 65 | I166: 31 | J166: 0.15 | K166: credit card | L166: Shipped | M166: lily.hall@example.com
A167: ORD-10545 | B167: 45705 | C167: Benjamin Walker | D167: U.K. | E167: Wireless Mouse | F167: Accessories | G167: 4 | H167: 18 | I167: 7 | J167: 0.05 | K167: Debit Card | L167: Completed | M167: benjamin.walker@example.com
...
